Workbook

Sheet Studies_ID
A1: id_study | B1: study_name_public | C1: study_name_contracted | D1: leading_institution | E1: id_institution | F1: rationale | G1: key_findings | H1: study_sector | I1: study_status | J1: factsheet_name | K1: factsheet_link | L1: contract_dates | M1: contact_name_sc | N1: contact_name _pi | O1: study_type | P1: imeo_objective | Q1: ccac_imeo | R1: imeo_affiliation
A2: 8b52df97-e308-43cf-a656-6a7b607d599e | B2: Baseline Scoping Study of Emissions in Nigeria | D2: Queen Mary University of London, United Kingdom (Scoping phase) Harvard University, United States (Satellite component) | E2: cc378b2c-297b-4b02-abc2-a2adce9d439a | F2: Nigeria, like many countries, faces challenges in setting effective methane reduction targets and tracking progress due to a lack of measurement-based emissions data across sectors. As a Global Methane Pledge Champion, the country has demonstrated its leadership in methane reduction efforts, and is in great need of improved data to support this. | G2: The objective of the scoping study is to determine the availability of methane data, establish a research consortium, and develop a feasibility study and quantification plan for a full two-year Baseline Study in Nigeria. To proceed to the full Baseline Study, the proposal must be approved by IMEO’s Scientific Oversight Committee. The potential Nigeria Baseline Study would be the first multisector (oil and gas, waste and agriculture) scientific study of anthropogenic methane emission on the African continent, and one of the first in the world. | H2: Multisector | I2: Ongoing | J2: Baseline Scoping Study of Emissions in Nigeria | K2: Baseline Scoping Study of Emissions in Nigeria | M2: Xuefei Li | N2: Paul Balcombe | O2: Desktop analysis | P2: 4 | Q2: IMEO
A3: 2c366808-4f57-4ca6-a4f6-53f027e06258 | B3: Upscaling Methane Measurements and Verifying Emissions Inventories in the Netherlands | D3: Utrecht University, Netherlands | E3: d57ecf4e-49ec-4bec-83b1-78ff974f2792 | F3: A wide range of scientific measurements across methane emission sources exists in the Netherlands. This provides a valuable opportunity to synthesize existing data for a more complete picture of emissions nationally and across sources. The results can inform inventory efforts, identify the most essential measurements for reliable emissions' quantification, and provide a benchmark for other efforts to baseline emissions in other countries – especially developing nations with scarcer methane measurement data available. | G3: This study will upscale existing measurements, compare them to atmospheric observations, and provide a national baseline of emissions across sources in the Netherlands. | H3: Multisector | I3: Ongoing | J3: Upscaling Methane Measurements and Verifying Emissions Inventories in the Netherlands | K3: Upscaling Methane Measurements and Verifying Emissions Inventories in the Netherlands | M3: Xuefei Li | N3: Guus Velders | O3: Desktop analysis | P3: 1 | Q3: IMEO
A4: e9c628a6-f5fe-43a2-b4b5-49f5a7a736d9 | B4: Methane emissions baseline for livestock and rice systems in Colombia | D4: Alianza Bioversity-CIAT | E4: ec4a6016-97eb-4fb6-bde0-2c44a0e56ecf | F4: The project is expected to deliver a comprehensive CH4 baseline data for rice and livestock, incorporating literature reviews, ongoing project data, and direct measurements. It will provide representative CH4 emission factors, identify key livestock and rice systems requiring further assessment, and validate multi-scale measurement techniques to enhance accuracy. The final outputs will include a roadmap for targeted CH4 measurements, methodologies for national upscaling, and recommendations for strengthening Colombia’s CH4 inventory. These efforts will contribute to improved CH4 mitigation strategies, enabling Colombia to achieve its climate goals while supporting the IMEO Colombia Baseline Study’s broader objectives. | G4: The project will achieve several key targets. It will consolidate all available CH4 emissions data for livestock and rice systems in Colombia, including unpublished and gray literature sources, and map ongoing projects to create a comprehensive CH₄ data inventory. For livestock systems, measurement gaps will be identified through the development of a prioritized list of regions, production systems, and practices requiring direct CH4 measurements using innovative tools. In contrast, for rice systems, the focus will be on compiling and analyzing existing data rather than conducting new field measurements. The project will also assess activity data requirements and propose methodologies for national-level upscaling of CH4 emissions estimates for both sectors. A deployment plan will be developed for implementing advanced atmospheric measurement techniques for livestock systems, validated through multi-scale methods. Finally, the project will provide recommendations for enhancing Colombia’s national CH4 inventory, integrating validated measurement-based approaches for livestock and rice (Tier 2), to improve accuracy and policy relevance. | H4: Agriculture | I4: Ongoing | J4: Methane emissions baseline for livestock and rice systems in Colombia | M4: Xuefei Li | N4: Ciniro Costa | O4: Measurement Campaign | P4: 4 | Q4: IMEO
A5: 597480a2-041d-45bc-8b69-e4561b325381 | B5: Waste measurements for the Baseline Study of Emissions in Colombia | D5: Carleton University, Canada | E5: 561bf82a-557c-4655-958c-8684e9d78281 | H5: Waste & Wastewater | I5: Upcoming | M5: TBD | N5: Matthew Johnson | O5: Measurement Campaign | P5: 4 | Q5: IMEO
A6: 9cd4092d-b9ec-4921-8e92-60b94271f15f | B6: Madrid Landfill Methane Emission Quantification Comparison Study | D6: Technical University of Denmark | E6: 7c2e3b01-f867-4342-a795-01c14255ece1 | F6: Significant discrepancies have been found between emissions measurements and reporting around the Las Dehehas landfill near Madrid, Spain. Emissio rates exceeding multiple tons of methane per hour have been reported from previous satellite retrievals, an order of magnitude greater than landfill operator estimates. The study will take simultaneous, comparative measurements of landfill emission via satellites and ground-based techniques, which are crucial to reconcile bottom-up and top-down landfill methane emissions measurements. Measurements will be performed during multiple field and remore-sensing campaigns. | G6: In progress | H6: Waste & Wastewater | I6: Ongoing | J6: Madrid Landfill Methane Comparison | M6: Tarek Abichou - Malika Menoud | O6: Measurement Campaign | Q6: IMEO
A7: edf2fa58-6b25-42a8-a8b7-61db47fbb4cd | B7: Nord Stream Gas Leaks Synthesis | D7: IMEO | E7: 1fccc344-9f87-4fc2-94d8-353ea21dc19f | F7: The 2022 Nord Stream underwater pipeline explosions are thought to have caused one of the largest anthropogenic methane emission event ever recorded. Despite numerous individual assessments of its impact on the global atmospheric methane budget, there is high uncertainty as to the exact amount of methane released from the pipelines. The goal of this study was to compile and reconcile emissions estimates from the Nord Stream pipeline leaks to present a more accurate methane emission estimate from the incident. Furthermore, the report showcases the different measurement approaches available (marine, airborne, tall-tower and satellite-based), for quantifying methane emissions in similar contexts. Finally, it explains and contextualizes reported emissions to a wider scientific audience. | G7: By reconciling modelled atmospheric emissions with top-down emission estimates, the study concluded that the Nord Stream pipeline emitted 465±20 thousand metric tons of methane into the atmosphere between 26 September and 3 October 2022. Although this represents the largest recorded emission of methane to the atmosphere from a single transient event, this amount is equivalent to only 0.1 per cent of anthropogenic methane emissions for 2022. The synthesis report shows how diverse, complementary measurement approaches are most effective for quantifying more accurately methane emissions, the Nord Stream pipeline leaks being a case in point. | H7: Oil and Gas | I7: Completed | J7: Synthesis report on Nord Stream gas leaks | K7: Synthesis report on Nord Stream gas leaks | M7: Stephen Harris | N7: Stephen Harris | O7: Data Integration | P7: 1 | Q7: IMEO
A8: 7fbaef23-727c-4c26-b6de-5190343955f3 | B8: Airborne Measurements from the Nord Stream Gas Leaks | D8: German Aerospace Center, Germany | E8: f08df46e-5e65-428c-9b95-282da81080e1 | F8: The 2022 Nord Stream underwater pipeline explosions are thought to have caused one of the largest anthropogenic methane emission event ever recorded. A team led by IMEO conducted the first and only aerial measurement of the event to provide rapid direct assessment of its impact. The goal of the study was to quantify the short-lived methane emissions that occurred immediately after, and directly near, the Nord Stream leak sites. | G8: While most of the methane leaked from the pipelines escaped directly into the atmosphere between 26 September and 1 October 2022, a fraction dissolved in the Baltic Sea. The atmospheric measurements of methane acquired using HELiPOD revealed that, on 5 October 2022, sea-surface outgassing rates ranged from 19 to 48 metric tons per hour. These emission rates are of similar magnitude to those of the Upper Silesian Coal Basin, which is the largest anthropogenic source of methane in Europe. Satellites are not equipped to detect the diffuse (non-point source) methane emissions measured by HELiPOD, pointing to the importance of diversifying measurement tools and approaches to obtain more accurate emission data. The study findings broadly align with oceanic methane transport and dissolution models over the Baltic region and are proving crucial to verify the simulated emission rates presented as part of IMEO’s synthesis work on the Nord Stream pipeline leaks (Harris et al., under review). | H8: Oil and Gas | I8: Completed | J8: Airborne measurements from the Nord Stream gas leaks | K8: Airborne measurements from the Nord Stream gas leaks | M8: Stephen Harris | N8: Anke Roiger | O8: Measurement Campaign | P8: 1 | Q8: IMEO
A9: 25e348c0-c485-4f68-b882-c0d489e85e86 | B9: Offshore Measurement Study in Angola and Gabon | D9: German Aerospace Center, Germany | E9: f08df46e-5e65-428c-9b95-282da81080e1 | F9: The region is home to substantial oil and gas production by both national and international oil companies and has been identified as a flaring hotspot. Quantification of methane emissions from these offshore facilities are sparse. | G9: The MTGA study will provide a comprehensive dataset on methane emissions from the offshore oil and gas industry off the coast of Angola, and significantly enhance the understanding of emission sources and patterns in the region. | H9: Oil and Gas | I9: Completed | J9: Measuring offshore oil & gas emissions in Angola and Gabon | K9: Measuring offshore oil & gas emissions in Angola and Gabon | M9: Stephen Harris | N9: Alina Fiehn | O9: Measurement Campaign | P9: 1 | Q9: CCAC
A10: f4a28a88-e041-4d66-b09e-d80c363fbd86 | B10: Coal Mine Methane Emissions: Sources, Mitigation Potential, Monitoring and Emissions Quantification (Coal Phase I) | D10: Environmental Defense Fund, United States | E10: b8f497f5-5560-4f37-9d24-4d5d006bb999 | F10: The study assesses current literature and data on coal mine methane emissions as a foundation for future measurement-based studies of the sector. This study provides a state-of-the-art understanding of coal mine methane emissions with focus upon sources, mitigation approaches, monitoring and emissions quantification. | G10: China leads the world in estimated coal mine methane emissions. Underground coal mines account for nearly 70% of global Coal Mine Methane (CMM) emissions. Mitigation is possible through drainage and ventilation air. The main variables which affect gas emission rates in coal mining are in-situ gas content of coal seams, strength and reservoir properties of the strata surrounding longwall districts, working depth, panel dimensions, face advance rate and district age. Accounting for coal mine methane emissions is complicated and conducted in variable ways around the world. | H10: Coal | I10: Completed | J10: Assessing current Coal Mine Methane Emissions quantification literature to inform future studies | K10: Assessing current Coal Mine Methane Emissions quantification literature to inform future studies | M10: Stefan Schwietzke - Robert Field | N10: Stefan Schwietzke | O10: Desktop analysis | P10: 4 | Q10: IMEO
A11: 36067f76-d150-4489-b59c-e7d016ba0c76 | B11: North Sea Offshore Emissions: United Kingdom & Netherlands | D11: German Aerospace Center, Germany University of York, United Kingdom British Antarctic Survey, United Kingdom University of Cambridge, United Kingdom | E11: f08df46e-5e65-428c-9b95-282da81080e1 | F11: This study characterized methane emissions from several UK and Netherlands offshore production sites in the North Sea. Prior to International Methane Emissions Observatory (IMEO)'s offshore studies, there were few measurement-based | G11: The study compares measurement-based emissions estimates to a global gridded inventory, which breaks down emissions into a grid based on national emissions totals reported to the UNFCCC. It finds this inventory substantially underestimates emissions from the observed UK and Netherlands offshore facilities underscoring the limitations of global inventories for field-specific characterization. The study also compared emissions to the UK national point source inventory, finding some platforms emitted more than an order of magnitude higher than what was reported. However, operator- reported emissions, for the specific survey days aligned more closely with the study measurements. The median flaring combustion efficiency of 98.4 per cent was close to industry and government assumptions, but less efficient than in the Norwegian North Sea. | H11: Oil and Gas | I11: Completed | J11: North Sea offshore emissions: United Kingdom & Netherlands | M11: Mark Lunt | N11: Anke Roiger | O11: Measurement Campaign | P11: 1 | Q11: CCAC
A12: a56c0110-40cb-4314-a1c4-f657394afb91 | B12: North Sea Offshore Emissions: Norway | D12: Royal Holloway and Bedford New College, United Kingdom University of Manchester, United Kingdom | E12: 8801f22a-989e-4359-ae26-638366dcffda | F12: Prior to the UNEP’s International Methane Emissions Observatory (IMEO)’s offshore studies, there were few estimates of methane emissions from international oil and gas offshore infrastructure based on empirical data. Since offshore facility-level emissions can vary substantially over time, large and representative sampling is needed for meaningful comparisons with reported emissions. Such comparative data is necessary to build robust and comprehensive measurement, reporting and verification frameworks such as the one set up through UNEP’s Oil and Gas Methane Partnership 2.0 (OGMP 2.0). This study characterizes methane emissions from several offshore production sites in the North Sea. The IMEO team selected Norwegian infrastructure because the country is a major European oil and gas producer. It accounts for about 45 per cent of European oil and natural gas production over the past decade and its share of production is increasing. | G12: The measurements align with the data reported by the oil and gas operator. However, they are more than 40 per cent larger than a widely cited, globally gridded fossil fuel methane emission inventory based on United Nations Framework Convention on Climate Change (UNFCCC) country-level reports. | H12: Oil and Gas | I12: Completed | J12: North Sea offshore emissions: Norway | K12: North Sea offshore emissions: Norway | M12: Stefan Schwietzke | N12: Grant Allen | O12: Measurement Campaign | P12: 1 | Q12: CCAC
A13: 594a76e0-8b42-44e7-ac72-4d385fde96de | B13: Multi-Scale Measurements of Oil & Gas Production in Romania (ROMEO) | D13: Utrecht University, Netherlands | E13: d57ecf4e-49ec-4bec-83b1-78ff974f2792 | F13: Romania is a key oil and gas (O&G) producer in the EU and may be poised to increase production due to recent discoveries of significant natural gas reserves in the Black Sea. As a country that reports to the IPCC using simple emissions factors, Romania’s current emissions estimates lack measurement-based data. Inventory uncertainties pose challenges to prioritizing and implementing methane mitigation strategies to achieve country-level reductions. | G13: Measurements using a range of ground-based and aerial methods suggest Romania’s oil and gas sector emissions are significantly underreported. For oil production sites, total methane emission in the surveyed region alone (120 kt CH4 yr−1 with a range of 79–180 kt yr−1) are roughly 2.5 times larger than reported values for all of Romania in 2020. Measured oil production sites emit on average 5.4 kg CH4 h−1 per site (3.6 %–8.4 %, 95 % confidence interval), the third highest emission factor in comparison with US production regions for this type of infrastructure. 10% of sites are responsible for more than 70% of emissions, also a relatively high skewness compared to US regions, which represents an important mitigation priority. | H13: Oil and Gas | I13: Completed | J13: Romanian methane emissions from oil and gas (ROMEO project) | K13: Romanian methane emissions from oil and gas (ROMEO project) | M13: Stefan Schwietzke | N13: Thomas Roeckmann | O13: Measurement Campaign | P13: 1 | Q13: CCAC
A14: 80137543-d0a7-4e84-b241-5a0013b2e4b1 | B14: Emissions from Coal Seam Gas Production in Australia | D14: Airborne Research Australia, Australia University of New South Wales, Australia | E14: b262de7c-c521-434c-a5e2-cebee5ede085 | F14: Coal-seam gas production is an increasing but understudied phenomenon. It is important to understand the scale and scope of emissions from the practice to better manage them. This study provides data about emissions from coal-seam gas production and represents a critical first step in understanding other places where this production occurs. The Surat Basin is Australia’s largest coal seam gas (CSG) basin accounting for almost 20 per cent of Australian natural gas production, and is the focus of this study. | G14: This study found that measurement of dual isotopic signatures of methane can help to distinguish coal seam gas emissions from other individual source sectors in the Surat basin such as agriculture, waste and coal mine methane. CSG upstream sources emit about 0.4 per cent of produced gas, which is comparable to some onshore dry gas fields (Marcellus Shale in the US and Groningen field in The Netherlands). However, it is substantially smaller than other regions, especially those where oil is co-produced (wet gas). This study identified that water management/brine ponds associated with CSG may be a mitigation opportunity overlooked by existing bottom-up emissions inventories. | H14: Coal | I14: Completed | J14: Emissions from Coal Seam Gas Production in Australia | K14: Emissions from Coal Seam Gas Production in Australia | M14: Stefan Schwietzke | N14: Jorg Hacker | O14: Measurement Campaign | P14: 1 | Q14: CCAC
A15: 73c8c107-b3d8-4fac-a667-90dbbd7a1515 | B15: Australia Bowen Basin Pilot | D15: Airborne Research Australia, Australia | E15: b262de7c-c521-434c-a5e2-cebee5ede085 | F15: Australia is the world’s fifth largest coal producer and second largest exporter. Understanding the scale and location of its coal sector emissions is needed to assess total climate impact, target mitigation, and track progress. This pilot study aims to determine the feasibility of the aircraft mass balance approach for estimating emissions from large surface mines in Australia's Bowen Basin. Validating this approach is an important step for assessing the accuracy of emissions estimates from satellite and inventory methods in the coal sector. Satellite studies indicate that coal mine methane emissions in Queensland’s Bowen Basin are many times higher than emission inventories suggest. Meanwhile, the International Energy Agency’s 2023 Global Methane Tracker indicates Australia’s coal mine emissions reported through the United Nations Framework Convention on Climate Change may be underreported by 82 per cent. | G15: Determining whether the airborne mass balance approach can be successfully applied to accurately quantify methane emissions from open pit coal mines. | H15: Coal | I15: Completed | J15: Australia Bowen basin pilot | K15: Australia Bowen basin pilot | M15: Robert Field | N15: Jorg Hacker | O15: Measurement Campaign | P15: 1 | Q15: IMEO
A16: b88434be-0a7a-4755-b7e5-1e1522cce39e | B16: Verification of Coal Emissions with Top-Down Data in Australia | D16: University of Bremen, Germany | E16: 4c54c16a-1b6c-4521-b434-1de0ed4bdc59 | F16: Australia is the world’s fifth largest coal producer and second largest exporter. Understanding the scale and location of its coal sector emissions is needed to assess total climate impact, target mitigation, and track progress. This comprehensive study aims to deploy two independent airborne methods to determine methane emissions from both underground and large surface mines in Australia's Bowen Basin. Using precise but technically contrasting methods yields the high-quality empirical data needed to independently assess the accuracy of emissions estimates from satellite and inventory methods in the coal sector. Satellite studies indicate that coal mine methane emissions in Queensland’s Bowen Basin are many times higher than emission inventories suggest. Meanwhile, the International Energy Agency’s 2023 Global Methane Tracker indicates Australia’s coal mine emissions reported through the United Nations Framework Convention on Climate Change may be underreported by 82 per cent. | G16: Quantifying methane emissions from coal mines in Australia’s Bowen Basin. | H16: Coal | I16: Ongoing | J16: Validation of coal methane emissions with Top-Down data in Australia | K16: Validation of coal methane emissions with Top-Down data in Australia | M16: Robert Field | N16: Heinrich Bovensmann | O16: Measurement Campaign | P16: 1 | Q16: IMEO
A17: 7cd4458a-5a90-4aac-a80c-af3761d4389b | B17: Aerial & Ground-Based Measurements of Coal Methane Emissions in Poland | D17: AGH University of Science and Technology, Poland German Aerospace Center, Germany Technical University of Munich, Germany Swiss Federal Laboratories for Materials Science & Technology, Switzerland | E17: 4b346865-1fd5-4c11-86c0-a67bff8ff93b | F17: Poland is the world’s ninth largest coal producer and Europe’s leading producer of high-quality metallurgical coal, which is associated with higher levels of methane emissions especially when compared to lower quality lignite coal. Understanding the scale and location of its coal sector emissions is needed to assess climate impact, target mitigation and track progress. Satellite observation shows Poland is a major hotspot of methane emissions in Europe due to its high density of coal mining operations, particularly in the Upper Silesia Basin. The largest source of emissions in this region (~70 per cent) are estimated to be from underground mines’ ventilation shafts. A series of measurement campaigns have been designed to evaluate various atmospheric methods’ ability to estimate emissions from ventilation shafts to validate current emissions inventories, which are based on generic emissions factors and not direct measurement. The results will subsequently be compared with in-mine methane safety sensors synchronized with the aerial and ground-based methods to provide more granular verification. | G17: Quantifying emissions from metallurgical coal mining in Poland’s Upper Silesia Basin. | H17: Coal | I17: Ongoing | J17: Aerial & Ground-Based Measurements of Coal Methane Emissions in Poland | K17: Aerial & Ground-Based Measurements of Coal Methane Emissions in Poland | M17: Robert Field | N17: Jaroslaw Necki | O17: Measurement Campaign | P17: 1 | Q17: IMEO
A18: 5aa9a8f7-b0c5-4232-af4f-2715b0182952 | B18: Coal Studies Bottom-Up Global Coordination | D18: AGH University of Science and Technology, Poland | E18: 4b346865-1fd5-4c11-86c0-a67bff8ff93b | F18: Coal mining is a significant source of global methane emissions. Accurate data on the sector’s emissions is needed to track climate impact, target mitigation and assess progress. However, current inventories which apply generic emissions factors don’t align with available measurement data – signaling uncertainty that needs to be resolved. This requires validating approaches for measuring coal mine methane emissions. Ventilation shafts are a major source of coal mine emissions able to be observed by satellites, in addition to other airborne and ground-based methods and in-mine safety sensors. This offers a unique opportunity to compare data across these measurement techniques to validate their effectiveness and assess the best approaches for deployment. | G18: Results will assess approaches for estimating coal mine methane emissions across mine-based measurements, inventory calculations (UNFCCC) and satellite quantifications. | H18: Coal | I18: Ongoing | J18: Coal Studies Bottom-Up Global Coordination | K18: Coal Studies Bottom-Up Global Coordination | M18: Robert Field | N18: Jaroslaw Necki | O18: Measurement Campaign | P18: 1 | Q18: IMEO
A19: c9d3782b-661c-4b9d-aa7e-4aa29ccf2237 | B19: India abandoned coal mine study | D19: Indian Institute of Technology Bombay | E19: 93c3799b-3fe5-4dd9-b869-c402a1514bdc | F19: With the accelerating pace of coal mine closures globally, sustainable and accountable mine closure practices are becoming increasingly important. Inadequately sealed or unmanaged abandoned underground mines can continue to emit methane for years due to residual gas slowly migrating through fractures, boreholes, and permeable layers. Current national inventories often rely on default Tier-1 emission factors that do not account for site-specific variations or sealing status, potentially underestimating actual emissions. This study will apply a Tier-2 approach consistent with the IPCC’s 2019 Refinement for abandoned Indian underground coal mines to develop improved estimates by combining field measurements, mine status assessments, and comparisons with default emission factors. The results will support improved inventory accuracy and guide methane mitigation in the context of mine closure. | G19: In progress | H19: Coal | I19: Ongoing | J19: Building a Bottom-Up Methane Emission Inventory for Abandoned Underground Coal Mines in India | M19: Robert Field | N19: Vikram Vishal | O19: Measurement Campaign | Q19: IMEO
A20: b694b526-f335-4ebf-a0e8-04cc8b3106b9 | B20: Quantifying Coking Coal Mine Methane Emissions Using Multiple Surface and Satellite Observations | D20: China University of Mining Technology | E20: 4d2561a3-9703-40cb-b06b-e98bb5205867 | H20: Coal | I20: Ongoing | J20: Quantifying Coking CMM | M20: Robert Field | N20: Kai Qin | O20: Measurement Campaign | Q20: IMEO
A21: a70b91d9-36aa-4cae-9d4b-0c76c1390303 | B21: Baseline Scoping Study of Emissions in Colombia | D21: Universidad Nacional de Colombia, Colombia | E21: 339835e0-2d02-47af-8f95-3e2b954c6bdf | F21: Colombia, like many countries, faces challenges setting effective methane reduction targets and tracking progress due to a lack of measurement-based emissions data across sectors. The country has already demonstrated significant leadership on methane through regulatory efforts, but better measurement data is needed to ensure mitigation efforts are targeted and effective. | G21: This effort will design a suitable measurement-based strategy for quantification of prioritized anthropogenic methane emissions in Colombia. The next step, a full Baseline Study, would estimate total methane emissions nationally and across sectors and can inform national greenhouse gas inventories, reveal areas to prioritize emission reduction, and help discover the sources of discrepancies. | H21: Multisector | I21: Completed | J21: Baseline Scoping Study of Emissions in Colombia | K21: Baseline Scoping Study of Emissions in Colombia | M21: Nataly Velandia | N21: Rodrigo Jimenez | O21: Desktop analysis | P21: 4 | Q21: IMEO
A22: e7cecf66-076a-4b5a-8cf5-658f497a904b | B22: Baseline Study of Emissions in Colombia - Inventory synthesis and communications | D22: Universidad Nacional de Colombia, Colombia | E22: 339835e0-2d02-47af-8f95-3e2b954c6bdf | H22: Multisector | I22: Upcoming | M22: Nataly Velandia | N22: Rodrigo Jimenez | O22: Measurement Campaign | P22: 4 | Q22: IMEO
A23: d27f9459-c1de-4abb-b875-0a245534e947 | B23: LNG Reconciliation Study | D23: National Physical Laboratory, United Kingdom | E23: 92fd7e5a-3de7-4b6d-98e9-e921991f1724 | F23: Liquified Natural Gas (LNG) has emerged as a major import and export product around the world, with the IEA projecting over 250 billion cubic meters of liquefaction capacity to be brought online annually through 2030. However, amid this growth there remains significant uncertainty surrounding methane emissions from LNG facilities (liquefaction, regasification and shipping). | G23: To enable more accurate assessment of LNG emissions, this study attempts to reconcile emissions estimates obtained from two independent measurement approaches at two LNG liquefaction plants. The reconciliation will compare emissions estimated from different measurement approaches and explore whether the contribution of emissions from different known emission points in a site are representative of all sources within the LNG facility when scaled by production data. | H23: Oil and Gas | I23: Completed | J23: Reconciling LNG emissions | K23: Reconciling LNG emissions | M23: Mark Lunt | N23: Rod Robinson | O23: Desktop analysis | P23: 1 | Q23: IMEO
A24: 12715187-0935-4ad8-bd8d-42ae4c8aa233 | B24: Characterization of LNG Facilities in Australia | D24: Airborne Research Australia, Australia | E24: b262de7c-c521-434c-a5e2-cebee5ede085 | F24: Liquified Natural Gas (LNG) has emerged as a major import and export product around the world, with the IEA projecting over 250 billion cubic meters of liquefaction capacity to be brought online annually through 2030. However, amid this growth there remains significant uncertainty surrounding methane emissions from LNG facilities (liquefaction, regasification and shipping). This study aims to conduct facility-level airborne measurements of all onshore LNG liquefaction facilities in Australia, a major global LNG exporter.. The results will improve knowledge of industry-wide emissions and emission intensities while identifying common factors responsible for varying levels of emissions. | G24: Multiple measurement-based quantifications at each onshore LNG liquefaction facility in Australia will derive emission estimates under a range of operating conditions. | H24: Oil and Gas | I24: Completed | J24: Measurement of LNG Facility emissions in Australia | K24: Measurement of LNG Facility emissions in Australia | M24: Mark Lunt | N24: Jorg Hacker | O24: Measurement Campaign | P24: 1 | Q24: IMEO
A25: c6c4d345-90e1-4dc3-b9cd-3b0c6354e166 | B25: Aerial Measurements of Emissions in Oman | D25: German Aerospace Center, Germany AGH University of Science and Technology, Poland | E25: f08df46e-5e65-428c-9b95-282da81080e1 | F25: Prior to this research, there has been no independent, in-depth study of oil and gas methane emissions on the Arabian Peninsula. To expand measurement-based understanding of emissions across sectors, a component on waste sector emissions was added to the oil and gas campaign. | G25: The study will assess oil and gas site-level emissions and sourcelevel distribution via aerial and ground-based methane surveys. | H25: Multisector | I25: Ongoing | J25: Aerial Measurements of Emissions in Oman | K25: Aerial Measurements of Emissions in Oman | M25: Mark Lunt | N25: Heidi Huntrieser | O25: Measurement Campaign | P25: 4 | Q25: IMEO
A26: d1a75482-6096-4292-a00c-30742826c32d | B26: Urban Controlled Methane Release Studies - Blind Release Rates and Locations | D26: Nanjing University China | E26: 30ee24bd-56bb-48fb-a00c-44554940b7e9 | F26: The detection and quantification of urban methane emissions using mobile measurements at ground level is a widely applied technique that has moved beyond the research sphere to commercial operation. However, there has been limited validation of the measurement technologies and approaches used to detect and quantify emissions in such settings. This study aims to address that by conducting a blind controlled release test within a real-world urban environment. | G26: In progress | H26: Oil and Gas | I26: Ongoing | J26: Urban Controlled Methane release studies | M26: Mark Lunt | N26: Huilin Chen | O26: Controlled release | P26: 2 | Q26: IMEO
A27: a6a9466c-4c54-4d66-86da-54f81266ac95 | B27: Feasibility Analysis For IMEO dedicated helicopter towed sensor platform | D27: Technical University of Braunschweig | E27: dfea752b-ebb7-4243-b4ba-b2199764c2fb | H27: Multisector | I27: Upcoming | M27: Mark Lunt | N27: Astrid Lampert | O27: Desktop analysis | Q27: IMEO
A28: f9d50385-5ddc-4996-a752-414616e08989 | B28: Measurement-Based Characterization of Emissions from Canadian Landfills | D28: St Francis University, United States | E28: df72143d-ada4-43a7-8812-fad702be3ec9 | F28: The waste sector is a significant source of methane emissions and measurement data is needed to assess the accuracy of emissions modelling that often forms the basis of policy decisions and mitigation action. Canada has committed to developing and implementing regulations to halve methane emissions from large municipal solid waste landfills from 2019 levels by 2030. | G28: Modelled landfill emissions for national reporting overestimated methane emissions by 1.4x relative to the measurements obtained for Canadian landfills. | H28: Waste & Wastewater | I28: Completed | J28: Measuring emissions from Canadian landfills | K28: Measuring emissions from Canadian landfills | M28: Marci Baranski | N28: Chelsie Hall | O28: Measurement Campaign | P28: 2 | Q28: IMEO
A29: f1e22d36-eae5-4e1c-b905-5330488094cc | B29: Measurement Campaign in Azerbaijan | D29: German Aerospace Center, Germany Environmental Defense Fund, United States | E29: f08df46e-5e65-428c-9b95-282da81080e1 | F29: There is currently no independent empirical data to derive representative emission estimates of oil and gas sources from former Soviet Union states apart from a limited number of point sources. Understanding oil and gas emissions is particularly salient given the country’s gas exports to markets such as the EU. The study would also provide independent data to support implementation of new EU methane legislation which requires the assessment of emissions associated with oil and gas imports. Azerbaijan is also host to some of the largest methane emitting mud volcanoes, a potentially significant natural methane source globally. The study will also measure methane emissions from this source. Given that methane from oil and gas and mud volcanoes have a similar chemical fingerprint, the study will help better apportion global total methane emissions into oil and gas sources versus mud volcanoes. | G29: This study will determine the magnitude and locations of methane emissions from several oil and gas operators, covering both national and international oil companies, as well as from mud volcanoes. | H29: Multisector | I29: Ongoing | J29: Measurement campaign in Azerbaijan | K29: Measurement campaign in Azerbaijan | M29: Malika Menoud - Andreea Calcan | N29: Anke Roiger | O29: Measurement Campaign | P29: 3 | Q29: CCAC
A30: 860c8019-d3a8-4216-be13-9c85f2265a36 | B30: Quantification of Emissions from Floating Production Storage Offloading Site | D30: University of York, United Kingdom | E30: d8a670b7-8563-4957-97bf-9c46f9480e34 | F30: Floating production storage and offloading (FPSO) vessels are widely used in the global offshore oil industry to process hydrocarbons and store oil before it is offloaded to a shuttle tanker for export. There is currently no direct measurement data for FPSOs' emissions and there is a lack of multi-scale offshore measurements in existing scientific literature from oil and gas facilities. | G30: This work will compare methane emission quantifications of a FPSO site before, after and during an offloading event at Glen Lyon, Shetland using aerial, drone and bottom-up quantification methods. | H30: Oil and Gas | I30: Ongoing | J30: Quantification of emissions from floating production storage offloading site | K30: Quantification of emissions from floating production storage offloading site | M30: James France | N30: James Lee | O30: Measurement Campaign | P30: 3 | Q30: IMEO
A31: 29dcb255-dd1a-4467-9f44-09fac0a50f70 | B31: Global Analysis of Emissions from Abandoned Wells | D31: McGill University, Canada | E31: 109f7f51-a57f-4d02-8778-4cfb99f539ec | F31: Globally, there are millions of abandoned oil and gas wells but only a very small number of methane emissions measurements of them exist outside North America. These wells have the potential to collectively emit significant methane emissions, but additional data is needed to understand their impact in regions beyond North America so that inventories can effectively account for them and mitigation resources can be effectively deployed. | G31: This work will provide data on abandoned well emissions from regions around the world and reconcile currently available data to provide an estimate of abandoned wells’ total emissions. The results will contribute to understanding the conditions that lead to high-emitting abandoned oil and gas wells. | H31: Oil and Gas | I31: Ongoing | J31: Global analysis of emissions from abandoned wells | K31: Global analysis of emissions from abandoned wells | M31: James France | N31: Mary Kang | O31: Measurement Campaign | P31: 3 | Q31: Both
A32: 38918a12-b6f5-41c7-9d2d-b64291ca87eb | B32: Validation of Methane Quantification Technologies | D32: Stanford University, United States | E32: 5e3558b7-6b43-46aa-8130-01e66830ac42 | F32: Accurate quantification of methane emissions is crucial for both tracking mitigation and informing regulatory decision making. Therefore, methodologies claiming to quantify methane emissions require independent and rigorous validation to give confidence and reassurance that accurate reporting of emissions through measurement is viable. The research being undertaken is intended to evaluate and demonstrate these capabilities and their ability to support the EU’s methane strategy and broader goals under the Global Methane Pledge. | G32: The study will assess the accuracy of various methane detection technologies. | H32: Oil and Gas | I32: Ongoing | J32: Validation of methane quantification technologies | K32: Validation of methane quantification technologies | M32: James France | N32: Adam Brandt | O32: Controlled release | P32: 2 | Q32: IMEO
A33: 2ee1bd3f-9ea0-4b14-968c-abf6d7e6a226 | B33: Local Distribution Studies | D33: Technical University of Munich, Germany University of Groningen, Netherlands University of Toronto, Canada Autonomous University of Barcelona, Spain Université de Versailles Saint-Quentin-en-Yvelines, France Environment and Climate Change Canada, Canada | E33: e7f2b433-cd11-416a-ae91-58634409cbb9 | F33: Previously, there was a lack of open, empirical data characterizing emissions from local distribution systems in Europe in comparison to systems elsewhere. These systems are important in the EU as they are a major source of nonimported oil and gas methane emissions. This study assessed emissions from a number of European (and Toronto) distribution systems and compared them to emissions from cities in the US and Canada. This set of studies also incorporated measurements of midstream facilities near sampling regions. | G33: This study provided evidence of methane leaks that can be mitigated and suggestions to target street-level methane emissions on natural gas distribution networks, sewage systems and furnaces. The study found that the waste sector is the largest methane emitter in the Toronto area. It also found that engineered waterways (not currently in inventories) may be a significant source. Based on the measurements collected, compressor stations and leaks from natural gas distribution network also contribute to emissions, though more information/ measurements are needed to fully characterize. The study demonstrated that not all methane leaks at ground level are gas distribution network infrastructure leaks. Large emissions also originate from the sewage network. This carries implications for measuring methane without also measuring co-emitted species for source identification – methane emissions may have been mis-categorized otherwise. In-building methane emissions (e.g., from stoves or boilers) may be missed in mobile street-level measurements. This study found strong indications of a large biogenic source of methane in Hamburg, correlated with rising tide of its river estuary. The addition of river emissions improved the performance of emissions modeling. The study found that all cities have a spectrum of small, medium and large methane sources in their domain. The emission rates found follow a heavy-tailed distribution, and the top 10 per cent of emitters account for 60–80 per cent of total emissions, which implies that strategic repair planning could help reduce emissions quickly. Furthermore, while cities with larger reported emissions were found to generally also have larger observed emissions, there are clear discrepancies between observation-based and inventory-based emission estimates for our 12 cities. | H33: Oil and Gas | I33: Completed | J33: Local distribution studies | K33: Local distribution studies | M33: James France | N33: Felix Vogel | O33: Measurement Campaign | P33: 1 | Q33: CCAC
A34: 55b560ec-1523-4186-a81b-043a92b4b04b | B34: Satellite-Based Detection and Quantification of Offshore Plumes | D34: València Polytechnic University, Spain | E34: b1e7baf4-b7a1-4949-8286-9b177ed06131 | F34: The study aims to further facilitate the implementation of offshore plume detection methods for use in IMEO’s Methane Alert and Response System (MARS), which notifies governments and companies of major emission events detected by satellites. Offshore oil and gas production is a sector with significant emissions uncertainty. Enabling improved satellite monitoring of offshore sites is necessary to enable better understanding and mitigation of emissions. | G34: The study will determine which offshore areas of the world are eligible to be monitored with multispectral satellites and identify the angular requirements to detect an offshore emission with hyperspectral satellites. | H34: Oil and Gas | I34: Ongoing | J34: Satellite-based detection and quantification of offshore plumes | K34: Satellite-based detection and quantification of offshore plumes | M34: Itziar Irakulis - Alba Lorente | N34: Luis Guanter | O34: Remote Sensing | P34: 3 | Q34: IMEO
A35: 29df8f34-6a80-4e90-bce4-f22613bc94ee | B35: TROPOMI-Based Quantification of Regional Emissions | D35: Netherlands Institute for Space Research, Netherlands | E35: fd165b68-89ef-4b22-bb12-a019eb5e1ae7 | F35: Individual countries report their emissions to the United Nations Framework Convention on Climate Change (UNFCCC) and these provide targets for Nationally Determined Contributions (NDCs) to climate change mitigation under the Paris Agreement. However, these inventories have high uncertainty in assessing emissions at the regional/national scale. Satellites can decrease this uncertainty by providing global monitoring of emissions. This study will generate a worldwide quantification of total methane emissions from oil, gas, and coal production on national and basin scales by inversion of multi-year TROPOMI observations with prior point source and infrastructure information. | G35: This study will quantify regional (national and basin scale) methane emissions from oil and gas production worldwide by timedependent inversion of TROPOMI observations at 25-50 km resolution. The results (including error characterization) will be used to evaluate the national emission reports to the UNFCCC, thereby enabling the formulation of improved NDCs | H35: Multisector | I35: Completed | J35: TROPOMI-based worldwide characterization of emissions | K35: TROPOMI-based worldwide characterization of emissions | M35: Itziar Irakulis - Alba Lorente | N35: Ilse Aben | O35: Remote Sensing | P35: 2 | Q35: CCAC
A36: 1923b621-10ef-4a5b-8480-420078fe65dc | B36: Continuous Monitoring of Methane Emissions with TROPOMI Satellite Observations in Support of IMEO | D36: Harvard University, United States | E36: b85535b7-577a-4f54-b447-68d75847bf3c | F36: Methane-monitoring satellites offer a valuable tool to track emissions, target mitigation and assess progress. The European Space Agency’s TROPOspheric Monitoring Instrument (TROPOMI) on board the Sentinel-5P satellite is an area mapping instrument that surveys larger regions at a time for methane emissions. There is an opportunity to integrate data from other satellite missions which have higher resolution over smaller areas (point source mappers) to refine insights and provide more granular and actionable methane data. The Integrated Methane Inversion (IMI) provides a ready-made open access tool to make these integrated observations available to users. | G36: The study will quantify high-frequency (weekly, monthly) methane emissions from satellite measurements, allowing the identification of factors driving the variability of the emissions. The study underscores the potential of satellite-based remote sensing as a tool for accurate, continuous and large-scale monitoring of methane emissions. | H36: Multisector | I36: Ongoing | J36: Continuous Monitoring of Methane Emissions with TROPOMI Satellite Observations | K36: Continuous Monitoring of Methane Emissions with TROPOMI Satellite Observations | M36: Itziar Irakulis - Alba Lorente | N36: Daniel Jacob | O36: Remote Sensing | P36: 2 | Q36: IMEO
A37: 9b2fe3ff-1709-4a42-81d7-82c5f924e6a0 | B37: TROPOMI-Based Worldwide Characterization of Emissions | D37: Harvard University, United States | E37: b85535b7-577a-4f54-b447-68d75847bf3c | F37: Individual countries report their emissions to the United Nations Framework Convention on Climate Change (UNFCCC) and these provide targets for Nationally Determined Contributions (NDCs) to climate change mitigation under the Paris Agreement. However, these inventories have high uncertainty in assessing emissions at the regional/national scale. Satellites can decrease this uncertainty by providing global monitoring of emissions. This study will generate a worldwide quantification of total methane emissions from oil, gas, and coal production on national and basin scales by inversion of multi-year TROPOMI observations with prior point source and infrastructure information. | G37: This study will quantify regional (national and basin scale) methane emissions from the oil and gas production worldwide by time-dependent inversion of TROPOMI observations at 25-50 km resolution. The results (including error characterization) will be used to evaluate the national emission reports to the UNFCCC, thereby enabling the formulation of improved NDCs. | H37: Multisector | I37: Ongoing | J37: TROPOMI-based worldwide characterization of emissions | M37: Itziar Irakulis - Alba Lorente | N37: Daniel Jacob | O37: Remote Sensing | P37: 2 | Q37: IMEO
A38: 9a8309bb-73ed-46ff-b5a6-ff6578cf8a50 | B38: MARS contract | D38: SRON | E38: fd165b68-89ef-4b22-bb12-a019eb5e1ae7 | F38: Satellite-based methods and capabilities for methane detection are rapidly evolving, in favor of higher transparency and accuracy in emissions estimates across different sectors. In particular, emissions from open-pit coal mines remain challenging due to their diffuse nature over large areas, requiring the development of accurate and reliable methods to obtain estimates based on empirical measurements. Satellite data enable replication and extrapolation of these methods across the globe quickly and at lower cost compared to other measurement approaches. On the other hand, satellite sensors already in operation with high revisit frequency and the potential to detect methane, such as VIIRS sensors, open up the possibility of more frequent methane emissions monitoring at different times of the day. However, as these sensors were not initially designed to detect methane, their low sensitivity requires careful processing and specific methods to extract methane emissions data. | G38: The study to assess the potential of VIIRS to detect point-source methane emissions demonstrated that this sensor can retrieve atmospheric methane enhancements with high spatial resolution and effectively track super-emitter events multiple times per day. Combining VIIRS and TROPOMI observations enables both detection and direct source attribution, while allowing for cross-validation between instruments. Furthermore, integrating the three VIIRS satellites with Sentinel-3 SLSTR data provides global coverage at least four times per day, offering valuable insight into short-lived and transient methane emissions. Overall, the study establishes the basis for a daily, global, and operational methane monitoring system. The study, focused on estimating methane emissions from this type of mine, aims to develop the methodology necessary to obtain emission estimates based on data from the TROPOMI sensor aboard the Sentinel-5P satellite. It will provide results for three large coal mines in three different countries. The developed methodology is expected to be extrapolable to other mines worldwide, offering more reliable and accurate emission estimates and improving those estimates only based on emission factors. | H38: Multisector | I38: Ongoing | J38: MARS support with Satellite Methane detection methods development | M38: Itziar Irakulis - Alba Lorente | N38: Ilse Aben | O38: Remote Sensing | P38: 2 | Q38: IMEO
A39: 338c51db-d03a-4384-87e3-bc177143bbf5 | B39: Multi-Scale Measurements in Colombia | D39: Carleton University, Canada | E39: 561bf82a-557c-4655-958c-8684e9d78281 | F39: There are few empirically-based estimates of methane emissions from South American oil and gas producing countries. This study will combine measurements at regional, site and source level to characterize emissions from oil and gas production in Colombia. | G39: This study will combine measurements at regional, site and source level to characterize emissions from oil and gas production in Colombia. | H39: Multisector | I39: Ongoing | J39: Multi-scale measurements in Colombia | K39: Multi-scale measurements in Colombia | M39: Daniel Zavala - Andreea Calcan | N39: Matthew Johnson | O39: Measurement Campaign | P39: 1 | Q39: IMEO
A40: 70f2024b-e279-4d03-9ca1-d8c1be5c09b0 | B40: Emissions from Offshore Production in the United States Gulf of Mexico | D40: University of Michigan, United States | E40: 69e5ee87-975c-46ec-b3dd-7acbd626fac3 | F40: Before this study, there were few to no empirical-based estimates of methane emissions from oil and gas offshore infrastructure. This study, undertaken in the US, is the first to provide offshore emissions assessment via direct measurement. This measurement data is necessary to understand the amount, locations, and sources of emissions to accurately assess and mitigate them. | G40: The study highlights that offshore production in shallow waters emits at higher rates than that in deepwater, as well as indicates the significant contribution of super-emitters to overall emissions. The new estimates are consistent with the EPA inventory in deep water but appear higher for shallow water. The study’s inventory, informed by regional airborne estimates, reports emissions to be twice as high as reported by the Environmental Protection Agency Greenhouse Gas Inventory (GHGI) with regional airborne estimates. Measurements taken from ships of over 100 offshore sites found emission rates were highly variable – but the distribution is heavily skewed with the top two emitters accounting for 20 per cent of the total methane emissions. Ship-based measurements agreed that emissions appear greater from shallow water sites | H40: Oil and Gas | I40: Completed | J40: Emissions from offshore production in the US Gulf of Mexico | K40: Emissions from offshore production in the US Gulf of Mexico | M40: Daniel Zavala | O40: Measurement Campaign | P40: 1 | Q40: CCAC
A41: 9efced68-1348-4e0d-a01b-de82fc334aed | B41: Emissions from Onshore & Offshore Production in Mexico | D41: Environmental Defense Fund, United States | E41: b8f497f5-5560-4f37-9d24-4d5d006bb999 | F41: Prior to UNEP IMEO studies of offshore emissions, there was little available information characterizing the difference between onshore and offshore emission – including for Mexico, which is a major oil and gas production country that relies on simple emission factors for its emissions inventories. This study integrates satellite and airborne monitoring to characterize emissions from these sources. | G41: This study integrated airbornebased measurements with remote sensing data (TROPOMI and VIIRS night-time flare data) and found large discrepancies (more than an order of magnitude) in emission estimates, with offshore production being overestimated and onshore production being underestimated in current inventories. One single facility, an onshore gas processing facility, was responsible for greater emissions than then entirety of the largest offshore production region. | H41: Oil and Gas | I41: Completed | J41: Emissions from onshore & offshore production in Mexico | K41: Emissions from onshore & offshore production in Mexico | M41: Daniel Zavala | O41: Measurement Campaign | P41: 1 | Q41: CCAC
A42: 5e855cb1-844c-4dba-84a8-055f4427ff3e | B42: Top-Down and Bottom-Up Reconciliation Study | D42: University of Texas at Austin, United States | E42: d9c73346-809e-4c13-91df-f7b9322d3bbb | F42: This study supports further development and implementation of the Oil and Gas Methane Partnership (OGMP 2.0) by performing reconciliation of source and site-level data globally. | H42: Oil and Gas | I42: Completed | J42: NA | K42: NA | M42: Daniel Zavala | N42: David Allen | O42: Desktop analysis | Q42: CCAC
A43: 1370995b-5032-4a4b-87d5-1a6fd7df10e1 | B43: Top-Down Measurement and Root Cause Analysis of Emissions in British Columbia | D43: Carleton University, Canada | E43: 561bf82a-557c-4655-958c-8684e9d78281 | F43: British Columbia is Canda’s second largest natural gas-producing province underscoring the need for credible data to manage associated methane emissions. A measurement-based inventory of emissions is needed to improve understanding of where emissions are coming from and how extensive they are so that stakeholders can deploy solutions. | G43: This study will establish robust procedures for producing quantitative, measurement-based methane inventories backed by robust uncertainty analysis, while supporting development of comprehensive measurement, reporting and verification protocols. | H43: Oil and Gas | I43: Completed | J43: Top-down measurement and root cause analysis of emissions in British Columbia | K43: Top-down measurement and root cause analysis of emissions in British Columbia | M43: Daniel Zavala | N43: Matthew Johnson | O43: Measurement Campaign | P43: 1 | Q43: IMEO
A44: 80dff756-0475-4737-8df5-628dbf9a12c0 | B44: Measurement of LNG Facilities | D44: National Physical Laboratory, United Kingdom | E44: 92fd7e5a-3de7-4b6d-98e9-e921991f1724 | F44: At the time this study was initiated, there was significant uncertainty surrounding methane emissions from LNG facilities (liquefaction, regasification, and shipping) with no empirical measurements publicly available. This study surveyed methane emissions from 5 LNG terminals (3 liquefaction – export and 2 regasification – import), representing approximately 6 per cent of global liquefaction and 3.5 per cent of re-gasification at the time, to improve the accuracy of emissions inventories. This was done by dividing measured facilities based on “Functional Elements” to derive accurate emissions factors for areas related to different liquefaction/regasification processes. | G44: Measurements confirmed large leaks and intermittent sources of emissions, demonstrating a continuing need for full site surveying for leak detection, maintenance, and repair processes to minimize emissions. On average methane emission rates were 0.018 per cent and 0.070 per cent of throughput at regasification and liquefaction facilities, respectively. This suggests nearly 0.1 per cent combined loss along the supply chain excluding LNG shipping and pipeline transport to and from the LNG facilities. Calculated emissions factors at liquefaction sites were significantly lower (approximately 1/6th) compared to other emissions factor literature values. | H44: Oil and Gas | I44: Completed | J44: Measurement of LNG facilities' methane impact | K44: Measurement of LNG facilities' methane impact | M44: Daniel Zavala | N44: Rod Robinson | O44: Measurement Campaign | P44: 3 | Q44: CCAC
A45: aac3e8db-eaba-4b55-97a7-d393ad660bf4 | B45: OGMP 2.0 Level 5 Feasibility Case Studies | D45: Queen Mary University of London, United Kingdom | E45: cc378b2c-297b-4b02-abc2-a2adce9d439a | F45: UNEP’s Oil and Gas Methane Partnership 2.0 (OGMP 2.0) is the only comprehensive, measurement-based emissions reporting framework for the oil and gas sector. Level 5 reporting is OGMP 2.0’s highest data quality level, and requires reconciling emissions at both the source and site level. Achieving Level 5 reporting is necessary for OGMP 2.0 member companies to improve accuracy, thoroughness and confidence in their reported emissions and uncertainties, providing a basis for targeting and tracking efforts to reduce emissions with confidence. | G45: This study assesses strategies for site-level emissions monitoring based on source-level reporting, local weather conditions and atmospheric modelling. The study aims to provide considerations for companies looking to achieve OGMP 2.0 Level 5 emissions reporting, which requires the reconciliation of source- and site-level data. | H45: Oil and Gas | I45: Ongoing | J45: OGMP 2.0 Level 5 Feasibility Case Studies | M45: Andreea Calcan - Alba Lorente | N45: Paul Balcombe | O45: Desktop analysis | P45: 3 | Q45: IMEO
A46: a5f62f74-0dfe-454d-9846-7d4dc9df6f83 | B46: Global Methane Budget | D46: Stanford University, United States | E46: 5e3558b7-6b43-46aa-8130-01e66830ac42 | F46: This project aims at supporting the Global Carbon Project (GCP) to better understand global methane emissions at large. The availability of new measurement-based data can provide further granularity on total atmospheric quantities of methane to better inform inventories, identify opportunities and track progress. IMEO is funding two additional elements to GCP’s biennial overview reports: (1) Addition of supplementary measurements to aid in distinguishing fossil fuels from other sources, and (2) Field campaign to measure some of the largest natural geological methane seeps. | G46: This study aims to update the Global Methane Budget using comprehensive databases and observations that will better differentiate fossil fuel vs. other sources of emissions and provide additional information on the largest natural geological methane seeps. | H46: Multisector | I46: Ongoing | J46: Global Methane Budget | M46: Andreea Calcan | N46: Rob Jackson | O46: Measurement Campaign | P46: 1 | Q46: CCAC
A47: 48e25358-1f5e-440d-a09a-c19453db0ca6 | B47: High-resolution quantification of national methane emissions by inversions of satellite data | D47: Harvard University, United States | E47: b85535b7-577a-4f54-b447-68d75847bf3c | F47: Inventories are instrumental in understanding country-level methane emissions. The goal of the studies is to address the critical lack of methane emissions measurement data which can better inform inventories in Colombia, Oman, and one additional country that will be identified as the study advances. The study will optimize national methane emission estimates at 12-km resolution using TROPOMI and supporting satellite data on emissions. The results will be used to identify major gaps in the bottom-up inventories and ultimately improve them. | G47: The overall objective of the project is to improve national emission inventories for the three focus countries with inversions of satellite methane data. The data collected through the studies will be integrated and reconciled with other sources of methane emissions data under IMEO’s public methane data platform. | H47: Multisector | I47: Ongoing | J47: Baselining National Methane Emissions with Satellite Data | K47: Baselining national methane emissions with satellite data | M47: Itziar Irakulis - Alba Lorente | N47: Daniel Jacob | O47: Remote Sensing | P47: 4 | Q47: IMEO
A48: 367492f7-c43f-4b75-9398-6094ec86b053 | B48: USGS LoA | D48: USGS | E48: 02768eb2-2b95-4021-bf3c-b5f6c5810bcd | H48: Coal | I48: Completed | O48: Secondary data analyis | Q48: IMEO
A49: bee72032-fa91-4372-a291-f959178fb04c | B49: IMEO internal satellite study | D49: IMEO | E49: 1fccc344-9f87-4fc2-94d8-353ea21dc19f | H49: Multisector | I49: Completed | O49: Remote Sensing | Q49: IMEO
A50: 6164e215-af65-44ab-b08c-c7535ec19e1d | B50: Non-IMEO study | C50: None | D50: Various | E50: 6b4e6133-9965-40e4-bcbd-3803ba5efc9f | F50: This row allows for measurements from non-IMEO studies to be included in this database and to be easily filtered out if desired.

Sheet Paper_ID
A1: id_paper | B1: id_study | C1: paper_title | D1: first_author | E1: paper_short_title | F1: doi | G1: publication_date | H1: collection_method | I1: paper_status | J1: type_of_data | K1: paper_key_findings | L1: paper_imeo_received | M1: paper_soc_reviewed | N1: journal_name | O1: in_house_study | P1: contact_name_imeo_author | Q1: flag_location
A2: db509759-4f90-4df1-9c2b-5951a791810f | B2: 12715187-0935-4ad8-bd8d-42ae4c8aa233 | C2: Isotope bag sampler methods | D2: Wolfgang Junkermann | H2: Airborne | I2: Manuscript Drafting | J2: Empirical | O2: No | Q2: Yes
A3: 949eb05e-57e9-46c8-af70-4bf5190114ad | B3: 12715187-0935-4ad8-bd8d-42ae4c8aa233 | C3: An evaluation of airborne mass balance and tracer correlation approaches to estimate site-level CH4 emissions from LNG facilities using CO2 as a tracer of opportunity | D3: Lunt et al., 2025 | E3: Tracer correlation at LNG facilities | F3: https://doi.org/10.5194/egusphere-2025-1926 | G3: 45911 | H3: Airborne | I3: Published | J3: Empirical | L3: 45689 | M3: 45717 | N3: Atmospheric Measurement Techniques | O3: Yes | P3: Mark Lunt | Q3: Yes
A4: afccf0a5-d14b-4906-bc65-674875539e01 | B4: 12715187-0935-4ad8-bd8d-42ae4c8aa233 | C4: Characterization of methane emissions from LNG liquefaction facilities in Australia via airborne measurements | D4: Jorg Hacker | H4: Airborne | I4: Manuscript Drafting | J4: Empirical | Q4: No
A5: 38c928db-e63f-4c5a-9e3f-a1e3887a8fb5 | B5: 1370995b-5032-4a4b-87d5-1a6fd7df10e1 | C5: The Efficacy of LDAR Programs in Practice | D5: Shona Wilde | E5: The Efficacy of LDAR Programs in Practice | H5: Airborne | I5: Submitted to Journal | J5: Empirical | L5: 45627 | M5: 45717 | O5: No | Q5: No
A6: fd6cb0ce-cf68-4d2f-a8cd-9c403cbeba26 | B6: 1370995b-5032-4a4b-87d5-1a6fd7df10e1 | C6: Catalytic Heaters at Oil and Gas Sites May be a Significant yet Overlooked Seasonal Source of Methane Emissions | D6: Festa-Bianchet et al. 2024 | E6: Catalytic heaters methane emissions | F6: https://doi.org/10.1021/acs.estlett.4c00453 | G6: 45516 | H6: Ground-based static | I6: Published | J6: Empirical | N6: Environmental Science & Technology (ES&T) | O6: No | P6: None | Q6: Yes
A7: 36651729-c0d4-499f-a46f-9e8a91b27d47 | B7: 1923b621-10ef-4a5b-8480-420078fe65dc | C7: Global Rice Paddy Inventory (GRPI): a high-resolution inventory of methane emissions from rice agriculture based on Landsat satellite inundation data | D7: Chen et al., 2024 | E7: Global rice paddy inventory | F7: https://doi.org/10.1029/2024EF005479 | G7: 45773 | H7: Satellite | I7: Published | J7: Empirical | L7: 45505 | N7: Earth's Future | O7: No | P7: None | Q7: No
A8: c225135b-8c23-46ac-84a4-54def66f9a94 | B8: 25e348c0-c485-4f68-b882-c0d489e85e86 | C8: Airborne quantification of Angolan offshore oil and gas methane emissions | D8: Fiehn et al., 2025 | E8: Angolan offshore oil and gas methane emissions | F8: https://doi.org/10.5194/egusphere-2025-635 | H8: Airborne | I8: Submitted to Journal | J8: Empirical | L8: 45505 | M8: 45658 | N8: Atmospheric Chemistry and Physics | O8: No | P8: None | Q8: Yes
A9: 23d195b9-f63b-452d-a552-4f028a3a037a | B9: 25e348c0-c485-4f68-b882-c0d489e85e86 | C9: Airborne quantification of Angolan offshore oil and gas methane emissions | D9: Alina Fiehn | F9: https://doi.org/10.5194/egusphere-2025-635 | H9: Airborne | I9: Submitted to Journal | J9: Empirical | N9: Atmospheric Chemistry and Physics | O9: No | P9: None | Q9: Yes
A10: a452377e-ced5-41b4-a1c8-ece961eb6dfa | B10: 29dcb255-dd1a-4467-9f44-09fac0a50f70 | C10: Methane Emission estimates from Italian Abandoned oil and gas wells | D10: Monia Prosecci | H10: Ground-based static | I10: SOC review | J10: Empirical | L10: 45778 | O10: No | Q10: Yes
A11: 7484fd90-a1c7-4f92-a6c0-1fbed4eb21c9 | B11: 29dcb255-dd1a-4467-9f44-09fac0a50f70 | C11: Overview of methane emissions from global abandoned oil and gas wells | D11: Mary Kang (or Student of Mary) | H11: Ground-based static | I11: Manuscript Drafting | J11: Empirical | Q11: No
A12: 0fa404ea-f6b5-4895-8153-16c9b8c9934d | B12: 29dcb255-dd1a-4467-9f44-09fac0a50f70 | C12: Long-term emission of methane and ethane to the atmosphere from hybrid natural seepage and well leakage in the Sărmășel gas field (Romania) | D12: Eduard Ghiorghiu | E12: Methane emission estimations from gas fiel in Romania | H12: Ground-based static | I12: Submitted to Journal | J12: Empirical | L12: 45839 | N12: Applied geochemistry | O12: No | Q12: Yes
A13: af6ca6c2-4bf5-4e95-90a8-c5598daa7803 | B13: 29dcb255-dd1a-4467-9f44-09fac0a50f70 | C13: Methane Emission estimates from Colombian Abandoned oil and gas wells | H13: Ground-based static | I13: Project Initiation | J13: Empirical | Q13: Yes
A14: 5dd2146f-5fc1-4667-a931-2c507a40f176 | B14: 29dcb255-dd1a-4467-9f44-09fac0a50f70 | C14: Methane Emission estimates from German Abandoned oil and gas wells | H14: Ground-based static | I14: Project Initiation | J14: Empirical | Q14: Yes
A15: 2bd022e0-8b29-45bb-8fbd-1311296b23aa | B15: 29df8f34-6a80-4e90-bce4-f22613bc94ee | C15: Assessing the Relative Importance of Satellite-Detected Methane Superemitters in Quantifying Total Emissions for Oil and Gas Production Areas in Algeria | D15: Naus et al., 2023 | E15: Satellite-Detected methane supperemitters in Algeria | F15: https://doi.org/10.1021/acs.est.3c04746 | G15: 45243 | H15: Satellite | I15: Published | J15: Empirical | K15: Top-down analysis indicates that a larger fraction of Algeria’s methane emissions come from oil production than national reporting suggests. Roughly a quarter of emissions come from super-emitters in the Hassi R’Mel Basin and and half come from the Hassi Messaoud basin. | N15: Environmental Science & Technology (ES&T) | O15: No | P15: Itziar Irakulis | Q15: Yes
A16: e431bb4a-1a49-494d-841f-9cac66d149dc | B16: 29df8f34-6a80-4e90-bce4-f22613bc94ee | C16: Assessing methane emissions from collapsing Venezuelan oil production using TROPOMI | D16: Nathan et al., 2024 | E16: Methane emissions from Venezuelan oil production | F16: https://doi.org/10.5194/acp-24-6845-2024 | G16: 45456 | H16: Satellite | I16: Published | J16: Empirical | N16: Atmospheric Chemistry and Physics | O16: No | P16: Alba Lorente | Q16: Yes
A17: d84f77e2-328a-4bbf-ad1f-59c35e5c47c7 | B17: 29df8f34-6a80-4e90-bce4-f22613bc94ee | C17: Daily global methane super-emitter detection and source identification with sub-daily tracking | D17: De Jong et al., 2025 | E17: Super-Emitter Detection and Source Identification | F17: https://doi.org/10.1029/2024GL111824 | G17: 45771 | H17: Satellite | I17: Published | J17: Empirical | N17: Geophysical Research Letters | O17: No | P17: Itziar Irakulis | Q17: No
A18: 0b349592-686d-4de2-b26c-becc6511c141 | B18: 2c366808-4f57-4ca6-a4f6-53f027e06258 | H18: Desktop | I18: Analysis Ongoing | J18: Empirical | Q18: Yes
A19: d90f12c1-a4bf-476c-bf52-f17c73ccedd2 | B19: 2ee1bd3f-9ea0-4b14-968c-abf6d7e6a226 | C19: Ground-Based Mobile Measurements to Track Urban Methane Emissions from Natural Gas in 12 Cities across Eight Countries | D19: Vogel et al., 2024 | E19: Synthesis, 12 cities, 8 countries | F19: https://doi.org/10.1021/acs.est.3c03160 | G19: 45316 | H19: Ground-based mobile | I19: Published | J19: Empirical | K19: All cities have a spectrum of small, medium, and large methane sources in their domain. The emission rates found follow a heavy-tailed distribution, and the top 10% of emitters account for 60 to 80% of total emissions. While cities with larger reported emissions generally also have larger observed emissions, there are clear discrepancies between observation-based and inventory-based emission estimates for the 12 cities in the study. | N19: Environmental Science & Technology (ES&T) | O19: No | P19: James France | Q19: Yes
A20: 31f5b3fd-d340-47b3-b215-4fbf7aff539c | B20: 2ee1bd3f-9ea0-4b14-968c-abf6d7e6a226 | C20: Methane mapping, emission quantification, and attribution in two European cities: Utrecht (NL) and Hamburg (DE) | D20: Maazallahi et al., 2020 | E20: Utrecht (NL) & Hamburg (DE) | F20: https://doi.org/10.5194/acp-20-14717-2020 | G20: 44172 | H20: Ground-based mobile | I20: Published | J20: Empirical | K20: A few large leaks are responsible for a significant proportion of natural gas distribution system related methane emissions. | N20: Atmospheric Chemistry and Physics | O20: No | P20: Daniel Zavala | Q20: Yes
A21: 226875f9-7ae7-4265-8392-b6128af26012 | B21: 2ee1bd3f-9ea0-4b14-968c-abf6d7e6a226 | C21: Quantification of methane emissions in Hamburg using a network of FTIR spectrometers and an inverse modeling approach | D21: Forstmaier et al., 2023 | E21: Hamburg (DE) | F21: https://doi.org/10.5194/acp-23-6897-2023 | G21: 45099 | H21: Ground-based mobile | I21: Published | J21: Empirical | K21: In-building methane emissions (from stoves or boilers, for example) may be missed in mobile street-level measurements. There are strong indications of a large biogenic source of methane in Hamburg, correlated with the rising tide of its river estuary. The addition of river emissions improved performance of the model. | N21: Atmospheric Chemistry and Physics | O21: No | P21: Stefan Schwietzke | Q21: Yes
A22: ca2b05f4-a893-475f-872b-5ea350666b75 | B22: 2ee1bd3f-9ea0-4b14-968c-abf6d7e6a226 | C22: Street-level methane emissions of Bucharest, Romania and the dominance of urban wastewater | D22: Fernandez et al., 2022 | E22: Street-level emissions, Bucharest | F22: https://doi.org/10.1016/j.aeaoa.2022.100153 | G22: 44584 | H22: Ground-based mobile | I22: Published | J22: Empirical | K22: Not all methane leaks at ground level are gas distribution network infrastructure leaks. Large emissions also originate from the sewage network. | N22: Atmospheric Environment: X | O22: No | P22: James France | Q22: Yes
A23: 398b13af-e142-4021-9be7-136187a1f193 | B23: 2ee1bd3f-9ea0-4b14-968c-abf6d7e6a226 | C23: Street Level Methane Emissions in London | D23: Fernandez et al. | H23: Ground-based mobile | I23: Manuscript Drafting | J23: Empirical | O23: No | Q23: Yes
A24: 7210136b-bbf7-43e3-8756-d0929c691627 | B24: 2ee1bd3f-9ea0-4b14-968c-abf6d7e6a226 | C24: Mapping Urban Methane Sources in Paris, France | D24: Defratkya et al., 2021 | E24: Paris (FR) | F24: https://doi.org/10.1021/acs.est.1c00859 | G24: 44370 | H24: Ground-based mobile | I24: Published | J24: Empirical | K24: Efforts to reduce street-level methane emissions should focus on natural gas distribution network, sewage system and furnaces. | N24: Environmental Science & Technology (ES&T) | O24: No | P24: None | Q24: Yes
A25: f787d7c0-c679-48a6-9872-d8253e7c8786 | B25: 2ee1bd3f-9ea0-4b14-968c-abf6d7e6a226 | C25: Investigation of the Spatial Distribution of Methane Sources in the Greater Toronto Area Using Mobile Gas Monitoring Systems | D25: Ars et al., 2020 | E25: Toronto (Canada, for point of comparison) | F25: https://doi.org/10.1021/acs.est.0c05386 | G25: 44159 | H25: Ground-based mobile | I25: Published | J25: Empirical | K25: The waste sector is the largest methane emitter in the Toronto area and engineered waterways (not currently in inventories) may be a significant source. Compressor stations and leaks from natural gas distribution network also contribute to emissions, though more information/measurements are needed. | N25: Environmental Science & Technology (ES&T) | O25: No | P25: None | Q25: Yes
A26: 22528dee-c714-4808-9570-51e2eca37114 | B26: 338c51db-d03a-4384-87e3-bc177143bbf5 | H26: Airborne | ground-based mobile | ground-based static | I26: Analysis ongoing | J26: Empirical | Q26: Yes
A27: 6fd71c20-562a-4cd9-8083-d9fb1c9eec32 | B27: 36067f76-d150-4489-b59c-e7d016ba0c76 | C27: Flaring efficiencies and NOx emission ratios measured for offshore oil and gas facilities in the North Sea | D27: Shaw et al. 2023 | E27: Flaring efficiencies from offshore facilities | F27: https://doi.org/10.5194/acp-23-1491-2023 | G27: 44952 | H27: Airborne | I27: Published | J27: Empirical | K27: The study provided the first aircraft-based measurements of gas flaring combustion efficiency in an offshore oil and gas production area. Median combustion efficiency of 98.4% was close to industry and government assumptions that flares are 98% efficient. | N27: Atmospheric Chemistry and Physics | O27: No | P27: Stefan Schwietzke | Q27: Yes
A28: 1711685d-9f0e-4c8a-8a5e-b120c02d52b7 | B28: 36067f76-d150-4489-b59c-e7d016ba0c76 | C28: Aircraft-based mass balance estimate of methane emissions from offshore gas facilities in the southern North Sea | D28: Pühl et al. 2024 | E28: Methane emissions from offshore faciities | F28: https://doi.org/10.5194/acp-2022-826 | G28: 45315 | H28: Airborne | I28: Published | J28: Empirical | K28: There is general agreement between measurements and operator reports. Snapshot emission measurements show large discrepancies when scaled to compare to annual bottom-up inventories, demonstrating the need for Levels 4 and 5 of OGMP 2.0 reporting. | N28: Atmospheric Chemistry and Physics | O28: No | P28: Stefan Schwietzke | Q28: Yes
A29: 817550ed-7daa-4b06-98ca-ef0dd4eab28d | B29: 36067f76-d150-4489-b59c-e7d016ba0c76 | C29: Facility level measurement of offshore oil and gas installations from a medium-sized airborne platform: method development for quantification and source identification of methane emissions | D29: France et al. 2021 | E29: Method paper on medium-size airborne platform | F29: https://doi.org/10.5194/amt-14-71-2021 | G29: 44201 | H29: Airborne | I29: Published | J29: Empirical | K29: The study identifies potential pitfalls in offshore surveying and makes recommendations to improve future offshore studies in North Sea-like environments. Focus: complex meteorology of marine boundary layer and discrete plumes from airborne platform. | N29: Atmospheric Measurement Techniques | O29: No | P29: James France | Q29: Yes
A30: b702af0b-8b30-4588-86fc-ab3cf59d0fbc | B30: 367492f7-c43f-4b75-9398-6094ec86b053 | C30: Mitigating climate change by abating coal mine methane: A critical review of status and opportunities | D30: Karacan et al., 2024 | E30: Abating CMM: Critical Review of Opportunities | F30: https://doi.org/10.1016/j.coal.2024.104623 | G30: 45630 | H30: Desktop | I30: Published | J30: Empirical | M30: 45505 | N30: International Journal of Coal Geology | O30: Yes | P30: Robert Field | Q30: No
A31: c84f65f1-8fb1-4a53-ab2d-63042d068a3b | B31: 38918a12-b6f5-41c7-9d2d-b64291ca87eb | C31: Controlled release testing of multiple classes of commercially available methane detection | D31: Audrey McManemin | H31: Airborne | satellite | drone | ground-based mobile | ground-based static | I31: Submitted to Journal | J31: Empirical | N31: Atmospheric Measurement Techniques | O31: No | Q31: Yes
A32: 6ee2f9bc-93d5-4fe7-86f4-e4bcccc094c8 | B32: 38918a12-b6f5-41c7-9d2d-b64291ca87eb | C32: Single-blind testing of non commercialised methodologies for methane detection and quantification | D32: Audrey McManemin | I32: Manuscript Drafting | J32: Empirical | Q32: No
A33: 4e3e3f4e-3892-4349-abcb-d3d4197edcd2 | B33: 48e25358-1f5e-440d-a09a-c19453db0ca6 | C33: Using new geospatial data and 2020 fossil fuel methane emissions for the Global Fuel Exploitation Inventory (GFEI) v3 | D33: Tia Scarpelli | E33: GFEIv3 | F33: https://doi.org/10.5194/essd-2024-552 | H33: Desktop | I33: Submitted to Journal | J33: Empirical | N33: ESSD | O33: No | P33: None | Q33: No
A34: e405d296-ba95-4de9-ba27-310c58551ea1 | B34: 55b560ec-1523-4186-a81b-043a92b4b04b | C34: Multisatellite Data Depicts a Record-Breaking Methane Leak from a Well Blowout | D34: Luis Guanter | E34: Multisatellite analysis of a Well Blowout | F34: https://doi.org/10.1021/acs.estlett.4c00399 | G34: 45473 | H34: Satellite | I34: Published | J34: Empirical | N34: Environmental Science & Technology Letters | O34: Yes | P34: Luis Guantier | Q34: Yes
A35: a2bde78b-3e0b-4392-8d9e-6bd9bcb0a3a7 | B35: 55b560ec-1523-4186-a81b-043a92b4b04b | C35: Assessing the Detection of Methane Plumes in Offshore Areas Using High-Resolution Imaging Spectrometers | D35: Javier Roger | E35: Detection of Methane Plumes in Offshore Areas | F35: https://doi.org/10.5194/egusphere-2025-1917 | H35: Satellite | I35: Submitted to Journal | J35: Empirical | L35: 45717 | N35: Atmospheric Measurement Techniques | O35: No | P35: Luis Guantier | Q35: No
A36: 03009fd2-8d7f-4f8f-871e-e8ef59530d31 | B36: 594a76e0-8b42-44e7-ac72-4d385fde96de | C36: High potential for CH4 emission mitigation from oil infrastructure in one of EU's major production regions | D36: Stavropoulou et al., 2023 | E36: Integrated results | F36: https://doi.org/10.5194/acp-23-10399-2023 | G36: 44984 | H36: Ground-based mobile | I36: Published | J36: Empirical | K36: Oil and gas production infrastructure in Romania holds a massive mitigation potential, specifically by implementing measures to capture the gas and minimize operational venting and leaks. | N36: Atmospheric Chemistry and Physics | O36: Yes | P36: Foteini Stavropoulou | Q36: No
A37: dfd53060-b764-4ae4-8304-8138edf67e2f | B37: 594a76e0-8b42-44e7-ac72-4d385fde96de | C37: CH4 isotopic signatures of emissions from oil and gas extraction sites in Romania | D37: Menoud et al., 2022 | E37: Using isotopic signatures | F37: https://doi.org/10.1525/elementa.2021.00092 | G37: 44678 | H37: Airborne | ground-based mobile | I37: Published | J37: Empirical | K37: Oil and gas sources are top emissions sources in target regions. Average methane isotopic signatures in Romania are lower than global values commonly used for greenhouse gas emissions inventories, emphasizing importance of regional variation in CH4 isotopes. | N37: Elementa Science of the Anthropocene | O37: No | P37: Malika Menoud | Q37: Yes
A38: 3226fb42-db7e-4bd8-9ac8-82e79454e883 | B38: 594a76e0-8b42-44e7-ac72-4d385fde96de | C38: Airborne in-situ quantification of methane emissions from oil and gas production in Romania | D38: Maazallahi et al., 2025 | E38: Airborne in situ quantification of methane emissions | F38: https://doi.org/10.5194/acp-25-1497-2025 | G38: 45702 | H38: Airborne | I38: Published | J38: Empirical | N38: Atmospheric Chemistry and Physics | O38: No | P38: Foteini Stavropoulou | Q38: No
A39: 479932e2-84fa-4dea-8ea5-af69c2010666 | B39: 594a76e0-8b42-44e7-ac72-4d385fde96de | C39: Evidence of successful methane mitigation in one of Europe's most important oil production regions | D39: Kuhlmann et al., 2025 | E39: Successful methane mitigation in Romania | F39: https://doi.org/10.5194/acp-25-5371-2025 | G39: 45805 | H39: Airborne | I39: Published | J39: Empirical | N39: Atmospheric Chemistry and Physics | O39: No | P39: Foteini Stavropoulou | Q39: No
A40: 0fba82a9-13eb-4ddd-accf-f66cbbe43b53 | B40: 594a76e0-8b42-44e7-ac72-4d385fde96de | C40: Quantification of methane emission rate from oil and gas wells in Romania using ground-based measurement techniques | D40: Korben et al., 2022 | E40: Using ground-based measurement techniques | F40: https://doi.org/10.1525/elementa.2022.00070 | G40: 44881 | H40: Ground-based mobile | I40: Published | J40: Empirical | K40: In more than 1,000 oil and gas sites, 65% of methane was emitted at detectable levels. | N40: Elementa Science of the Anthropocene | O40: No | P40: Daniel Zavala | Q40: No
A41: f5ea9822-80c4-40c4-bda3-8e3cacaeadc6 | B41: 594a76e0-8b42-44e7-ac72-4d385fde96de | C41: ROMEO synthesis publication | D41: Foteini Stavropoulou | H41: Airborne | ground-based mobile | I41: Manuscript Drafting | J41: Empirical | O41: Yes | Q41: No
A42: 976b4509-8086-4e72-b866-319687274739 | B42: 594a76e0-8b42-44e7-ac72-4d385fde96de | C42: Methane and ethane emission quantifications from onshore oil and gas sites in Romania, using a tracer gas dispersion method | D42: Delre et al., 2022 | E42: Using tracer gas dispersion method | F42: https://doi.org/10.1525/elementa.2021.000111 | G42: 44720 | H42: Ground-based mobile | I42: Published | J42: Empirical | K42: Both methane (CH4) and ethane (C2H6) emissions factors for Romania were calculated to be in the lower range of values in the literature (and ethane measurements were the lowest). | N42: Elementa Science of the Anthropocene | O42: No | P42: None | Q42: Yes
A43: 6fcc0d8d-bb28-4548-9495-e31cb3fa2e99 | B43: 70f2024b-e279-4d03-9ca1-d8c1be5c09b0 | C43: Methane Emissions from Oﬀshore Oil and Gas Platforms in the Gulf of Mexico | D43: Yacovitch, Daube and Herndon 2020 | E43: Methods paper on ship-based measurements | F43: https://doi.org/10.1021/acs.est.9b07148 | G43: 43899 | H43: Shipboard (TILDAS) | Desktop (Gaussian) | I43: Published | J43: Empirical | K43: There are important differences in emissions between shallow and deep-water production infrastructure, and the presence of super-emitters. | N43: Environmental Science & Technology (ES&T) | O43: No | P43: None | Q43: Yes
A44: a317553a-aa01-43b9-96f4-9419b52fc09e | B44: 70f2024b-e279-4d03-9ca1-d8c1be5c09b0 | C44: Airborne Assessment of Methane Emissions from Offshore Platforms in the U.S. Gulf of Mexico | D44: Gorchov et al. 2020 | E44: Airborne-based measurements | F44: https://doi.org/10.1021/acs.est.0c00179 | G44: 43934 | H44: Airborne | I44: Published | J44: Empirical | K44: Highlights important differences in emissions between shallow and deep-water production infrastructure, and the presence of super-emitters. The study’s inventory reports emissions higher by a factor of 2 than the Environmental Protection Agency Greenhouse Gas Inventory (GHGI) with regional airborne estimates. | N44: Environmental Science & Technology (ES&T) | O44: No | P44: None | Q44: No
A45: 637f6d88-bd50-4ce6-b580-548d692e5a8e | B45: 73c8c107-b3d8-4fac-a667-90dbbd7a1515 | C45: Insights into elevated methane emissions from an Australian open-cut coal mine using two independent airborne techniques | D45: Borchardt et al., 2025 | E45: Coal mine methane - Two airborne techniques | F45: https://doi.org/10.1021/acs.estlett.4c01063 | G45: 45741 | H45: Airborne | I45: Published | J45: Empirical | M45: 45597 | N45: Environmental Science & Technology Letters | O45: No | P45: Robert Field | Q45: Yes
A46: d92e5da5-1f15-4338-9a56-6c3a086a8104 | B46: 7cd4458a-5a90-4aac-a80c-af3761d4389b | C46: Quantifying methane emissions from a coal mine ventilation shaft using a pellistor safety sensor and a TDLAS analyzer: A case study from Poland | D46: Jaroslaw Necki | H46: Airborne | ground-based mobile | ground-based static | I46: Submitted to Journal | J46: Empirical | M46: 45658 | N46: Measurement | O46: No | Q46: No
A47: 3d00bc68-cedc-409b-ba2b-033c28e3e648 | B47: 7cd4458a-5a90-4aac-a80c-af3761d4389b | C47: Coal mine CH4 emissions from the Upper Silesia region in Poland quantified with the AVIRIS-4 spectrometer | D47: Gerritt Kuhlmann | H47: Airborne | I47: Analysis Ongoing | J47: Empirical | O47: No | Q47: No
A48: 1bc3f4f2-414c-4709-8f7c-156eb2efbe84 | B48: 7cd4458a-5a90-4aac-a80c-af3761d4389b | C48: A helicopter-based mass balance approach for quantifying methane emissions from industrial activities, applied for coal mine ventilation shafts in Poland | D48: Förster et al., 2025 | E48: Helicopter-based mass balance approach | F48: https://doi.org/10.5194/egusphere-2025-1010 | H48: Airborne | I48: Submitted to Journal | J48: Empirical | M48: 45658 | N48: Atmospheric Measurement Techniques (AMT) | O48: No | P48: Robert Field | Q48: Yes
A49: 9b643bec-a88e-4a49-8687-40057603673c | B49: 7cd4458a-5a90-4aac-a80c-af3761d4389b | C49: Quantifying CH4 point source emissions with the new airborne AVIRIS-4 imaging spectrometer | D49: Sandro Meier | H49: Airborne | I49: Manuscript Drafting | J49: Empirical | N49: Atmospheric Measurement Techniques (AMT) | O49: No | Q49: No
A50: 691c62be-96b1-4d99-ad05-79eab7b172ee | B50: 7cd4458a-5a90-4aac-a80c-af3761d4389b | C50: Quantifying Coal Mine Methane via FTIR Observations and GRAMM/GRAL Dispersion Modelling | D50: Andreas Luther | H50: Ground-based static | I50: Analysis Ongoing | J50: Empirical | O50: No | Q50: No
A51: 797bd615-59f5-48b1-92ab-859a4de16dbe | B51: 7fbaef23-727c-4c26-b6de-5190343955f3 | C51: Airborne observations reveal the fate of the methane from the Nord Stream pipelines | D51: Reum et al. 2025 | E51: Airborne observations reveal the fate of the methane from the Nord Stream pipelines | F51: https://doi.org/10.1038/s41467-024-53780-7 | G51: 45672 | H51: Airborne | I51: Published | J51: Empirical | N51: Nature Communications | O51: No | P51: None | Q51: Yes | R51: Based on original geologic measurements and maps
A52: 33b59046-0eed-4fd1-9f85-e0ff408036f7 | B52: 5aa9a8f7-b0c5-4232-af4f-2715b0182952 | C52: Mitigating methane emissions to the atmosphere from underground coal mines: A safe and cost-effective solution for climate action | D52: Richard Mattus | H52: Desktop | I52: Manuscript Drafting | J52: Empirical | O52: No | Q52: Yes
A53: 458aae5d-c4b9-49d4-8b31-b4bc95f8dd6c | B53: 5aa9a8f7-b0c5-4232-af4f-2715b0182952 | C53: Evaluation of EF and Production BU Versus In-Mine Empirical Data Approach | D53: Justyna Swolkień | H53: In-mine | I53: Manuscript Drafting | J53: Empirical | O53: No
A54: d818edf5-ab16-4872-a77c-e99c60fccef7 | B54: 80137543-d0a7-4e84-b241-5a0013b2e4b1 | C54: Coal seam gas industry methane emissions in the Surat Basin, Australia: comparing airborne measurements with inventories | D54: Neininger et al., 2021 | E54: Inventory comparison | F54: https://doi.org/10.1098/rsta.2020.0458 | G54: 44466 | H54: Airborne | I54: Published | J54: Empirical | K54: Coal seam gas upstream sources emit about 0.4% of produced gas, which is comparable to some onshore dry gas fields (Marcellus Shale in the United States and Groningen field in The Netherlands). However, it is substantially smaller than other regions, especially those where oil is co-produced (wet gas). | N54: Philosophical Transactions of the Royal Society A | O54: No | P54: Stefan Schwietzke | Q54: No
A55: 97fe07d8-5270-45ec-bef8-5f6eec745556 | B55: 80137543-d0a7-4e84-b241-5a0013b2e4b1 | C55: Isotopic signatures of major methane sources in the coal seam gas fields and adjacent agricultural districts, Queensland, Australia | D55: Lu et al., 2021 | E55: Dual isotopic signatures | F55: https://doi.org/10.5194/acp-21-10527-2021 | G55: 44391 | H55: Ground-based mobile | I55: Published | J55: Empirical | K55: Measurement of dual isotopic signatures of methane can help to distinguish coal seam gas emissions from other individual source sectors in the Surat basin such as agriculture, waste and coal mine methane. | N55: Atmospheric Chemistry and Physics | O55: No | P55: Stephen Harris | Q55: Yes
A56: 4ddd20c9-e6c2-4ced-bb03-6ae7759db96d | B56: 80137543-d0a7-4e84-b241-5a0013b2e4b1 | C56: Atmospheric methane isotopes identify inventory knowledge gaps in the Surat Basin, Australia, coal seam gas and agricultural regions | D56: Kelly et al., 2022 | E56: Isotopes identify inventory knowledge gaps | F56: https://doi.org/10.5194/acp-22-15527-2022 | G56: 44907 | H56: Airborne | I56: Published | J56: Empirical | K56: Potential sources of methane emissions are overlooked by bottom-up inventories, including upwind coal seam gas brine ponds. | N56: Atmospheric Chemistry and Physics | O56: No | P56: Stephen Harris | Q56: No
A57: aa543491-373f-4f6f-b91d-559a3739cb4c | B57: 80dff756-0475-4737-8df5-628dbf9a12c0 | C57: Comparative Assessment of Methane Emissions from Onshore LNG Facilities Measured Using Differential Absorption Lidar | D57: Innocenti et al., 2023 | E57: Comparative assessment using DIAL technique | F57: https://doi.org/10.1021/acs.est.2c05446?urlappend=%3Fref%3DPDF&jav=VoR&rel=cite-as | G57: 44970 | H57: Ground-based static | I57: Published | J57: Empirical | K57: Average emission factors for each tonne/hr methane throughput was approximately 3.5 times higher at liquefaction terminals than at regasification terminals. Calculated emission factors at liquefaction sites are approximately 1/6th lower compared to other literature values. | N57: Environmental Science & Technology (ES&T) | O57: No | P57: None | Q57: No
A58: cdcf5563-c55e-48e0-9f8a-f8242b96d56e | B58: 860c8019-d3a8-4216-be13-9c85f2265a36 | C58: Methane emission from shuttle tankers during standard operations on a oil platform during oil loading | D58: Ruth Purvis | H58: Airborne | drone | ground-based static | I58: SOC review | J58: Empirical | O58: No | Q58: Yes
A59: 1e2d90e0-5889-4720-932d-3a33208843b2 | B59: 860c8019-d3a8-4216-be13-9c85f2265a36 | C59: A synthesis of North Sea methane emissions | D59: James Lee (or student of) | I59: Analysis ongoing | J59: Empirical | Q59: No
A60: dbf528d3-3f60-46ff-9cad-73443cfb1897 | B60: 9a8309bb-73ed-46ff-b5a6-ff6578cf8a50 | C60: Wind back-tracing to derive temporal information on emissions and improved emission quantification from TROPOMI (Title TBD) | D60: Tobias de Jong | H60: Satellite | I60: Analysis ongoing | J60: Empirical | Q60: No
A61: 4ff60fc1-dd55-49dd-9583-1ff6b85bc8e8 | B61: 9a8309bb-73ed-46ff-b5a6-ff6578cf8a50 | C61: Estimating methane emissions from surface coal mines using satellite observations | D61: Shubham Sharma | E61: Methane emissions from coal mines using satellite | H61: Satellite | I61: Submitted to Journal | J61: Empirical | M61: 45748 | N61: Environmental Science & Technology (ES&T) | Q61: No
A62: 19ea008a-b2bf-4e20-b7ae-b99f94bda60f | B62: 9b2fe3ff-1709-4a42-81d7-82c5f924e6a0 | C62: Evaluating the Utility of Satellite Observations for Improving Bottom-Up National Emission Inventories: Application to Colombia | D62: Sarah Hancock | H62: Satellite | I62: Manuscript Drafting | J62: Empirical | O62: No | Q62: Yes
A63: eaa0e625-a43e-4026-b57a-cd2428c87c9a | B63: 9b2fe3ff-1709-4a42-81d7-82c5f924e6a0 | C63: Trends in methane emissions from African countries | D63: Nicholas Balasus | H63: Satellite | I63: Analysis ongoing | J63: Empirical | O63: No | Q63: Yes
A64: 0d76ccfa-96c4-48c5-9533-080da659cff3 | B64: 9b2fe3ff-1709-4a42-81d7-82c5f924e6a0 | C64: Trends in US methane emissions | D64: Lucas Estrada | H64: Satellite | I64: Analysis ongoing | J64: Empirical | O64: No | Q64: No
A65: 88c52b09-1b31-4b02-bae7-f2ce18f29658 | B65: 9b2fe3ff-1709-4a42-81d7-82c5f924e6a0 | C65: Methane from Nigeria: constraining emissions using TROPOMI satellite observations | D65: Lauren Potyk | H65: Satellite | I65: Analysis ongoing | J65: Empirical | O65: No | Q65: Yes
A66: b0779fbc-f7dd-4ea6-8f3f-5ccff097f6c1 | B66: 9b2fe3ff-1709-4a42-81d7-82c5f924e6a0 | C66: National methane emissions estimates for all countries of the world during 2023 by inversion of satellite observations: comparison to UNFCCC reporting | D66: James East | H66: Satellite | I66: Author revisions | J66: Empirical | L66: yes | M66: yes | N66: Nature Communications | O66: No | Q66: No
A67: 212dec45-48ed-4d2c-ac4d-cc73dd4cfdf2 | B67: 9b2fe3ff-1709-4a42-81d7-82c5f924e6a0 | C67: Satellite quantification of methane emissions from South American countries: A high-resolution inversion of TROPOMI and GOSAT observations | D67: Hancock et al., 2024 | E67: Satellite quantification of emissions from South American | F67: https://doi.org/10.5194/acp-25-797-2025 | G67: 45678 | H67: Satellite | I67: Published | J67: Empirical | N67: EGUsphere | O67: No | P67: Cynthia Randles | Q67: Yes
A68: e6a5fcae-a248-4893-b151-8da78b8bacce | B68: 9b2fe3ff-1709-4a42-81d7-82c5f924e6a0 | C68: Trends in methane emissions from Turkmenistan | D68: Daniel Varon | H68: Satellite | I68: Analysis ongoing | J68: Empirical | O68: No | Q68: Yes
A69: 6d1907d8-e3be-4a40-87a3-19725cab98a3 | B69: 9b2fe3ff-1709-4a42-81d7-82c5f924e6a0 | C69: Seasonality and intensity of methane emissions from the Permian and nearby US oil and gas basins | D69: Daniel Varon | H69: Satellite | I69: Analysis ongoing | J69: Empirical | Q69: No
A70: 8784d7de-88ad-414a-aa4f-d8d137381d2a | B70: 9efced68-1348-4e0d-a01b-de82fc334aed | C70: A tale of two regions: methane emissions from oil and gas production in offshore/onshore Mexico | D70: Zavala-Araiza et al. 2021 | E70: Integrated airborne-based & remote sensing | F70: https://doi.org/10.1088/1748-9326/abceeb | G70: 44222 | H70: Airborne | satellite | I70: Published | J70: Empirical | K70: There are large discrepancies (more than an order of magnitude) in emission estimates between airborne-based measurements integrated with remote sensing data (TROPOMI and VIIRS night-time flare data) and current inventories, with offshore production being overestimated and onshore production being underestimated. | N70: Environmental Research Letters | O70: No | P70: Daniel Zavala | Q70: Yes
A71: 909ba75e-b9a2-43f6-8126-fb7229f9299e | B71: a56c0110-40cb-4314-a1c4-f657394afb91 | C71: Quantification and assessment of methane emissions from offshore oil and gas facilities on the Norwegian continental shelf | D71: Foulds et al., 2022 | E71: Norwegian offshore platform measurements | F71: https://doi.org/10.5194/acp-22-4303-2022 | G71: 44655 | H71: Airborne | I71: Published | J71: Empirical | K71: Measurements from Norwegian offshore production infrastructure in the North Sea align with oil and gas operators' reports, but are more than 40% larger than a widely cited globally gridded fossil fuel methane emission inventory based on UNFCCC country-level reports. | N71: Atmospheric Chemistry and Physics | O71: No | P71: James France | Q71: Yes
A72: 169304c1-53b5-49d1-9da5-8dafc00f8918 | B72: a5f62f74-0dfe-454d-9846-7d4dc9df6f83 | H72: To be determined | drone | I72: Analysis ongoing | J72: Empirical | Q72: No
A73: 71fe9657-1eb6-4742-99e6-d7a6bf51015d | B73: 8b52df97-e308-43cf-a656-6a7b607d599e | D73: Paul Balcombe | H73: Desktop | I73: Analysis Ongoing | J73: Empirical | Q73: Yes
A74: 33b9b2bd-81e8-4960-9f21-1c255caee36e | B74: a70b91d9-36aa-4cae-9d4b-0c76c1390303 | C74: Assessment and comparison of Colombia’s methane emissions inventories – Insights on quantification improvement and mitigation | D74: Rodrigo Jimenez | E74: Characterization of methane emissions in Colombia | H74: Desktop | I74: IMEO Science team review | J74: Empirical | Q74: Yes
A75: d35d63f2-e804-4d6e-8bf9-0ecb406be086 | B75: aac3e8db-eaba-4b55-97a7-d393ad660bf4 | H75: Desktop | I75: Manuscript Drafting | J75: Empirical | Q75: No
A76: ce9b1fcd-dc20-457f-82b4-1c9de4442b8d | B76: b88434be-0a7a-4755-b7e5-1e1522cce39e | C76: A comprehensive evaluation of methane emissions from Bowen Basin coal mines using airborne in-situ and remote sensing techniques | D76: Stephen Harris | H76: Airborne | I76: Manuscript Drafting | J76: Empirical | N76: Atmospheric Chemistry and Physics | O76: Yes | Q76: Yes
A77: 21ee59e2-121a-4254-bb7a-511a3163e529 | B77: bee72032-fa91-4372-a291-f959178fb04c | C77: CH4Net: a deep learning model for monitoring methane super-emitters with Sentinel 2 imagery | D77: Vaughan et al., 2024 | E77: CH4Net: monitoring methane super-emitters | F77: https://doi.org/10.5194/amt-17-2583-2024 | G77: 45415 | H77: Satellite | I77: Published | J77: Empirical | N77: Atmospheric Measurement Techniques | O77: Yes | P77: Itziar Irakulis-Loitxate | Q77: Yes
A78: 7fa85a4e-b3fa-4ce8-acaf-98102cb0db4a | B78: c6c4d345-90e1-4dc3-b9cd-3b0c6354e166 | C78: Quantifying methane emissions based on a helicopter-borne mass balance approach of the oil, gas and waste sector in the Sultanate of Oman | D78: Eric Förster | H78: Airborne | ground-based mobile | ground-based static | I78: Manuscript Drafting | J78: Empirical | O78: No | Q78: Yes
A79: 1ad67298-46f1-41af-929d-88a1e7d333b1 | B79: d27f9459-c1de-4abb-b875-0a245534e947 | C79: Methane emission quantification of an Australian LNG facility vs. sub-facility measurements | D79: Nigel Yarrow | H79: Desktop | I79: Manuscript drafting | J79: Empirical | O79: No | Q79: Yes
A80: edc9ce2c-cf1a-447a-a5c2-9ef67b63bc01 | B80: edf2fa58-6b25-42a8-a8b7-61db47fbb4cd | C80: Methane emissions from the Nord Stream subsea pipeline leaks | D80: Harris et al. 2025 | E80: Methane emissions from the Nord Stream subsea pipeline leaks | F80: https://doi.org/10.1038/s41586-024-08396-8 | G80: 45672 | H80: Airborne | satellite | shipboard | tower | I80: Published | J80: Empirical | K80: Emissions were nearly double some initial estimates. Nord Stream leak released up to 485,000 metric tonnes of methane to the atmosphere. Previous estimates of the Nord Stream leak varied widely, but each was just telling part of the story from a different perspective. Together, they provide a coherent and accurate view of emissions – underscoring the importance of integrating diverse complementary measurement approaches | N80: Nature | O80: Yes | P80: Stephen Harris | Q80: Yes
A81: 5ffc0a15-4713-4894-a12b-7bca37cde9f1 | B81: f1e22d36-eae5-4e1c-b905-5330488094cc | H81: Drone | I81: Analysis ongoing | J81: Empirical | Q81: Yes
A82: fa856ef7-7120-44c9-9d73-a37627bce1ae | B82: f4a28a88-e041-4d66-b09e-d80c363fbd86 | E82: A report is posted on IMEO’s website | G82: 44774 | H82: Desktop | I82: Published | J82: Empirical | O82: Yes | Q82: No
A83: 0d5ea261-4560-491c-ae5f-7ab4b8e66559 | B83: f9d50385-5ddc-4996-a752-414616e08989 | C83: Estimating Canadian Landfill Methane Emissions from Aircraft Measurements | D83: Chelsea Fougère | E83: Canadian landfill methane emissions | F83: https://papers.ssrn.com/sol3/papers.cfm?abstract_id=5186900 | H83: Airborne | I83: Submitted to Journal | J83: Empirical | N83: SSRN | O83: No | P83: None | Q83: No
A84: 3bb6c21e-a456-49b6-ae3c-bd59970c0b7b | B84: f9d50385-5ddc-4996-a752-414616e08989 | C84: Current methodologies and challenges for detecting, measuring, and quantifying methane emissions from solid waste treatment sites and landfills | D84: Dave Risk | H84: Airborne | drone | ground-based mobile | I84: Manuscript drafting | J84: Empirical | Q84: Yes
A85: 19781bb8-6da4-4e45-b840-f68ec7a1254b | B85: c9d3782b-661c-4b9d-aa7e-4aa29ccf2237 | C85: Empirical Characterization of Methane Emissions from India’s Abandoned Underground Coal Mine | D85: Vikram Vishal | E85: Methane Emissions from India’s Abandoned Underground Coal Mine | H85: Ground-based static | I85: Analysis Ongoing | J85: Empirical | O85: No | Q85: Yes
A86: b55a11a1-138d-4122-af9d-d06cdc039086 | B86: d1a75482-6096-4292-a00c-30742826c32d | I86: Analysis Ongoing | J86: Empirical | Q86: No
A87: c5a1b10c-db72-452c-b688-dcc9d698c373 | B87: b694b526-f335-4ebf-a0e8-04cc8b3106b9 | C87: Quantifying Coking Coal Mine Methane Emissions Using Multiple Surface and Satellite Observations | D87: Kai Qin | I87: Analysis Ongoing | J87: Empirical | N87: Atmospheric Chemistry and Physics | O87: No | Q87: Yes
A88: 55b0fae8-68d0-404c-a152-2bc970bcfc83 | B88: a6a9466c-4c54-4d66-86da-54f81266ac95 | I88: Analysis Ongoing | J88: Empirical | Q88: No
A89: 90d4589f-1fd4-4778-b7c7-959161ec1a6f | B89: 9cd4092d-b9ec-4921-8e92-60b94271f15f | I89: Analysis Ongoing | J89: Empirical | Q89: Yes
A90: 12fa2b0d-a8e4-4513-8451-98287201291b | B90: e9c628a6-f5fe-43a2-b4b5-49f5a7a736d9 | I90: Analysis Ongoing | J90: Empirical | Q90: Yes
A91: f8510917-3a27-4121-89d0-520340c744b3 | B91: e7cecf66-076a-4b5a-8cf5-658f497a904b | I91: Analysis Ongoing | J91: Empirical | Q91: Yes
A92: 33c3d55b-743c-4f12-b4aa-716795020748 | B92: 597480a2-041d-45bc-8b69-e4561b325381 | I92: Analysis Ongoing | J92: Empirical | Q92: Yes
A93: 40e3b567-cc39-4d52-b840-cf24ce7a00ba | B93: 6164e215-af65-44ab-b08c-c7535ec19e1d | C93: A new approach to estimate fugitive methane emissions from coal mining in China | D93: Yiwen Ju | E93: Fugitive methane emissions in coal mining (China) | F93: 10.1016/j.scitotenv.2015.11.024 | G93: 42329 | H93: Ground-based static | I93: Published | J93: Empirical | Q93: NA
A94: ab6b0e8d-7ddc-4c81-9a25-ebbf5842e446 | B94: 6164e215-af65-44ab-b08c-c7535ec19e1d | C94: Study on Characteristics and Model Prediction of Methane Emissions in Coal Mines: A Case Study of Shanxi Province, China | D94: Xueli Zhang | E94: Methane Emissions in Shanxi Coal Mines | F94: 10.3390/atmos14091422 | G94: 45180 | H94: Ground-based static | I94: Published | J94: Empirical | Q94: NA
A95: 2741c113-c99b-48d9-8f08-2e5264e2052b | B95: 6164e215-af65-44ab-b08c-c7535ec19e1d | C95: Quantification of methane emissions from typical natural gas stations using on-site measurement technology | D95: Wenlong Jia | E95: Quantification of Methane emissions from Natural Gas | F95: 10.1016/j.jpse.2024.100229 | G95: 45586 | H95: Ground-based mobile | I95: Published | J95: Empirical | Q95: NA
A96: 9dca00d6-e040-4834-a715-2b55885b332e | B96: 6164e215-af65-44ab-b08c-c7535ec19e1d | C96: A strategic approach to selecting policy mechanisms for addressing coal mine methane emissions: A case study on Kazakhstan | D96: Volha Roshchanka | E96: Selecting policy mechanisms for addressing CMM in Kazakhstan | F96: https://doi.org/10.1016/j.envsci.2017.08.005 | G96: 43070 | H96: Desktop | I96: Published | J96: Empirical | Q96: NA
A97: 916e8cc6-6d16-4a1c-943c-a2cdace08c59 | B97: 6164e215-af65-44ab-b08c-c7535ec19e1d | C97: Biogeochemical Controls on Methane Generation: A Review on Indian Coal Resources | D97: Tushar Adsul | E97: Biogeochemical Controls: A review | F97: https://doi.org/10.3390/min13050695 | G97: 45065 | H97: Desktop | I97: Published | J97: Empirical | Q97: NA
A98: 34cfccda-ec83-46b7-a0bd-711344a2aa35 | B98: 6164e215-af65-44ab-b08c-c7535ec19e1d | C98: Comparing facility-level methane emission rate estimates at natural gas gathering and boosting stations | D98: Timothy L. Vaughn | E98: Facility-level CH₄ at gas gathering stations | F98: 10.1525/elementa.257 | G98: 43063 | H98: Airborne | Ground-based mobile | Ground-based static | I98: Published | J98: Empirical | Q98: NA
A99: 2f077bf9-4f80-4a1d-955e-f987cb59bd15 | B99: 6164e215-af65-44ab-b08c-c7535ec19e1d | C99: Classification of coal seams for coal bed methane exploitation in central part of Jharia coalfield, India – A statistical approach | D99: Rima Chaterjee | E99: Classification of coal seams - statistical approach | F99: https://doi.org/10.1016/j.fuel.2013.04.007 | G99: 41518 | H99: Desktop | I99: Published | J99: Empirical | Q99: NA
A100: 837a01a1-4c8a-4403-8ff2-3231b0a10ea2 | B100: 6164e215-af65-44ab-b08c-c7535ec19e1d | C100: Methane Emissions from Natural Gas Compressor Stations in the Transmission and Storage Sector: Measurements and Comparisons with the EPA Greenhouse Gas Reporting Program Protocol | D100: R. Subramanian | E100: Methane Emissions from Natural Gas Compressor Stations | F100: 10.1021/es5060258 | G100: 42045 | H100: Ground-based mobile | Ground-based static | I100: Published | J100: Empirical | Q100: NA
...

Sheet Paper_Location
A1: id_paper | B1: id_location
A2: 6fcc0d8d-bb28-4548-9495-e31cb3fa2e99 | B2: 55d6e423-92c7-4774-a664-3132cd2c03ae
A3: a317553a-aa01-43b9-96f4-9419b52fc09e | B3: 55d6e423-92c7-4774-a664-3132cd2c03ae
A4: 8784d7de-88ad-414a-aa4f-d8d137381d2a | B4: 90de6911-8cdb-4bbc-b326-0d606644ee29
A5: 817550ed-7daa-4b06-98ca-ef0dd4eab28d | B5: 86d4c868-7c32-4f87-8f5b-0eea92d32d46
A6: 817550ed-7daa-4b06-98ca-ef0dd4eab28d | B6: a8dd3121-b37d-4403-9afc-dbebc3c3f485
A7: 1711685d-9f0e-4c8a-8a5e-b120c02d52b7 | B7: d45dc248-31bc-48c1-8d6c-4cb479faf1b4
A8: 1711685d-9f0e-4c8a-8a5e-b120c02d52b7 | B8: debfd98b-5259-4981-8584-7789af75b8ea
A9: 6fd71c20-562a-4cd9-8083-d9fb1c9eec32 | B9: 2cf8db5a-929c-458d-8809-a583cab990c7
A10: 6fd71c20-562a-4cd9-8083-d9fb1c9eec32 | B10: 7e9aa2f1-f03b-4012-83a7-88a1465d0825
A11: cdcf5563-c55e-48e0-9f8a-f8242b96d56e | B11: 01d07fb9-ffa8-4f2f-bfd9-62c25d228cea
A12: 1e2d90e0-5889-4720-932d-3a33208843b2 | B12: 01d07fb9-ffa8-4f2f-bfd9-62c25d228cea
... A117: 33c3d55b-743c-4f12-b4aa-716795020748 | B117: ed655758-d5ff-40de-810f-8dea21e9dd8a

Sheet Location_ID
A1: id_location | B1: continent_or_region | C1: country | D1: basin_or_region_studied_or_site | E1: min.lat | F1: min. long | G1: max. lat | H1: max.long | I1: flag_map | J1: Coordinates included in Paper (Yes - 1, No - 0)
A2: 55d6e423-92c7-4774-a664-3132cd2c03ae | B2: North America | C2: USA | D2: Gulf of Mexico | E2: 25.577 | F2: -97.79757 | G2: 31 | H2: -87.5 | I2: =TRUE() -> TRUE
A3: 90de6911-8cdb-4bbc-b326-0d606644ee29 | B3: North America | C3: Mexico | D3: Sureste basin | E3: 17.5 | F3: -94.5 | G3: 20 | H3: -91.2 | I3: =TRUE() -> TRUE
A4: 86d4c868-7c32-4f87-8f5b-0eea92d32d46 | B4: Europe | C4: United Kingdom | D4: North Sea | E4: 51.465539 | F4: -1.420554 | G4: 56.683291 | H4: 6.751502 | I4: =TRUE() -> TRUE
A5: a8dd3121-b37d-4403-9afc-dbebc3c3f485 | B5: Europe | C5: Netherlands | D5: North Sea | E5: 51.465539 | F5: -1.420554 | G5: 56.683291 | H5: 6.751502 | I5: =FALSE() -> FALSE
A6: d45dc248-31bc-48c1-8d6c-4cb479faf1b4 | B6: Europe | C6: United Kingdom | D6: Southern North Sea | E6: 52.159225 | F6: -0.379895 | G6: 54.665686 | H6: 4.901058 | I6: =TRUE() -> TRUE
A7: debfd98b-5259-4981-8584-7789af75b8ea | B7: Europe | C7: Netherlands | D7: Southern North Sea | E7: 52.159225 | F7: -0.379895 | G7: 54.665686 | H7: 4.901058 | I7: =FALSE() -> FALSE
A8: 2cf8db5a-929c-458d-8809-a583cab990c7 | B8: Europe | C8: United Kingdom | D8: North Sea | E8: 55.599942 | F8: -7.13022 | G8: 66.01 | H8: 9.535788 | I8: =TRUE() -> 1
A9: 7e9aa2f1-f03b-4012-83a7-88a1465d0825 | B9: Europe | C9: Norway | D9: Norwegian continental shelf | E9: 55.599942 | F9: -7.13022 | G9: 66.01 | H9: 9.535788 | I9: =FALSE() -> 0
A10: 01d07fb9-ffa8-4f2f-bfd9-62c25d228cea | B10: Europe | C10: United Kingdom | D10: North Sea | E10: 59.862141 | F10: -2.077113 | G10: 60.855065 | H10: -0.622162 | I10: =TRUE() -> TRUE
A11: 12257acf-4a35-4ac2-a31d-e3375f8c0e49 | B11: South America | C11: Colombia | D11: Several Regions | E11: -4.226944 | F11: -79.008056 | G11: 12.458333 | H11: -67.130508 | I11: =TRUE() -> 1
A12: e50068bd-7e84-4252-b2c5-4b1568e30a05 | B12: Europe | C12: Italy | D12: Several Regions | E12: 37.933333 | F12: 6.616667 | G12: 47.083333 | H12: 18.516667 | I12: =TRUE() -> 1
A13: 9ffb068b-9940-469a-9d21-7eaa1026e450 | B13: South America | C13: Colombia | D13: Several Regions | E13: -4.226944 | F13: -79.008056 | G13: 12.458333 | H13: -67.403721 | I13: =TRUE() -> 1
A14: 441ed3a4-f38f-4b3d-be05-95a6f77c55df | B14: Europe | C14: Germany | D14: Several Regions | E14: 47.270108 | F14: 5.866667 | G14: 54.9 | H14: 15.033333 | I14: =TRUE() -> 1
A15: 14336337-4b58-4cb2-810c-6cd0fe27fe60 | B15: Europe | C15: Romania | D15: Several Regions | E15: 43.666667 | F15: 20.316667 | G15: 48.25 | H15: 29.666667 | I15: =TRUE() -> 1
A16: 1ea89366-b8c1-4691-99d6-327fd7de34ce | B16: Australia_Oceania | C16: Australia | D16: Not Defined (capital for reference) | E16: -35.482343 | F16: 148.99244 | G16: -35.138733 | H16: 149.26916 | I16: =TRUE() -> TRUE
A17: 3dabadd3-7c6d-4271-845a-883f00187025 | B17: Australia_Oceania | C17: Australia | D17: Karratha | E17: -20.802778 | F17: 116.75065 | G17: -20.690407 | H17: 116.91476 | I17: =TRUE() -> 1
A18: 63c291df-fb4c-4915-ac9f-8e59f75758bd | B18: Australia_Oceania | C18: Australia | D18: Darwin | E18: -12.524777 | F18: 130.80284 | G18: -12.31757 | H18: 131.05587 | I18: =TRUE() -> 1
A19: 9669b9a9-ef48-4eee-97f9-407db6ed2dec | B19: Australia_Oceania | C19: Australia | D19: Gladstone | E19: -23.936424 | F19: 151.15382 | G19: -23.803668 | H19: 151.32278 | I19: =TRUE() -> 1
A20: 601c727b-725c-468f-aa60-e3782eb3ba6b | B20: Europe | C20: Denmark | D20: Baltic Sea | E20: 54.88 | F20: 15.39 | G20: 55.52 | H20: 15.9 | I20: =TRUE() -> TRUE
A21: edda36d2-5a20-41b9-924f-f31c37acfaba | B21: Europe | C21: Sweden | D21: Baltic Sea | E21: 54.88 | F21: 15.39 | G21: 55.52 | H21: 15.9 | I21: =FALSE() -> 0
A22: 7dfc7b57-b9ef-4757-8b92-008aa8d363db | B22: Europe | C22: Denmark | D22: Baltic Sea | E22: 54.88 | F22: 15.39 | G22: 55.52 | H22: 15.75 | I22: =TRUE() -> TRUE
A23: bd9467ea-7833-4441-9360-41ffefac6e35 | B23: Europe | C23: Sweden | D23: Baltic Sea | E23: 54.88 | F23: 15.39 | G23: 55.52 | H23: 15.75 | I23: =FALSE() -> FALSE
A24: 57cb459c-51f7-446a-81f3-490e12729070 | B24: Europe | C24: Azerbaijan | D24: Mud Volcano | E24: 40.428737 | F24: 49.694402 | G24: 40.433462 | H24: 49.703491 | I24: =TRUE() -> TRUE
A25: 6c7ad3fe-f54d-4759-836c-a80f8912b3e0 | B25: North America | C25: Canada | D25: British Columbia | E25: 48.310707 | F25: -139.04336 | G25: 60 | H25: -114.06835 | I25: =TRUE() -> 1
A26: 571ad96c-738d-408e-9b4a-ee48cb91fbca | B26: Africa | C26: Angola | D26: Luanda | E26: -10.889475 | F26: 9.5946563 | G26: -3.9601445 | H26: 14.753349 | I26: =TRUE() -> 1
A27: b1374816-da0b-4723-a6ca-e15e999e0eb4 | B27: Africa | C27: Gabon | D27: Libreville | E27: -2.7297322 | F27: 8 | G27: 2.1870252 | H27: 10.893345 | I27: =TRUE() -> 1
A28: 37cfd354-a19f-423e-84c9-2a1636c0e9d9 | B28: Europe | C28: France | D28: Lacq | E28: 43.398621 | F28: -0.647916 | G28: 43.442934 | H28: -0.57084 | I28: =TRUE() -> 1
A29: 3b17e7fc-5b8c-4255-9ff3-6c79b8a962a9 | B29: North America | C29: USA | D29: Arizona | E29: 31.332456 | F29: -114.7554 | G29: 37 | H29: -109.05 | I29: =TRUE() -> TRUE
A30: 6b02dd20-2700-4d46-ac62-f50833513641 | B30: Africa | C30: Algeria | D30: Hassi Messaoud | E30: 28.477957 | F30: 2.94678 | G30: 32.643625 | H30: 7.110599 | I30: =TRUE() -> 1
A31: cf7024e6-3cc1-4b61-ab1d-4678d2507561 | B31: South America | C31: Venezuela | D31: Lake Maracaibo | E31: 9.019514 | F31: -72.148411 | G31: 11.037049 | H31: -70.994847 | I31: =TRUE() -> TRUE
A32: 96592d31-6a5e-4b2c-be17-990307b0681b | B32: Europe | C32: Norway | D32: North Sea | E32: 59.055628 | F32: 1.6428869 | G32: 68.272085 | H32: 20.53448 | I32: =TRUE() -> TRUE
A33: 200df652-3d27-4a47-97b3-7f8fb12cb8d3 | B33: Europe | C33: Netherlands | D33: Utrecht | E33: 52.025046 | F33: 4.966103 | G33: 52.144666 | H33: 5.198532 | I33: =TRUE() -> 1
A34: 52c608e9-afae-4007-8d44-ae72baac0d71 | B34: Europe | C34: Germany | D34: Hamburg | E34: 53.39247 | F34: 9.722738 | G34: 53.745007 | H34: 10.331078 | I34: =TRUE() -> TRUE
A35: ca5e2e7d-c73e-4650-b535-40cd79f25eb8 | B35: Europe | C35: France | D35: Paris | E35: 48.81476 | F35: 2.22069 | G35: 48.904206 | H35: 2.474748 | I35: =TRUE() -> 1
... A50: 69884e59-400d-48ca-9f47-005db274a8cf | B50: Europe | C50: Poland | D50: Upper Silesian Coal Basin | E50: 49.763909 | F50: 18.397979 | G50: 50.363099 | H50: 20.054365 | I50: =TRUE() -> 1
A51: 0ddd1281-1864-49b0-8afd-471f710f3d4d | B51: Australia_Oceania | C51: Australia | D51: Surat Basin | E51: -28 | F51: 150 | G51: -26 | H51: 152 | I51: =TRUE() -> 1
A52: 8b83f327-fb0d-4ed9-9e1c-4117576038ef | B52: North America | C52: Canada | D52: Alberta | E52: 49 | F52: -120 | G52: 60 | H52: -110 | I52: =TRUE() -> 1
A53: 3becaab6-d951-4cb1-a243-06a532af576d | B53: North America | C53: Canada | D53: Ontario | E53: 41.685 | F53: -95.167012 | G53: 56.856944 | H53: -74.356533 | I53: =TRUE() -> TRUE
A54: c3310205-32f9-4553-a741-5d95f83fd2d9 | B54: North America | C54: Canada | D54: Quebec | E54: 45.06458 | F54: -79.766667 | G54: 62.627747 | H54: -57.046371 | I54: =TRUE() -> TRUE
A55: 18ff08e5-a646-4bc1-a11b-5210d3120a68 | B55: Asia | C55: Oman | D55: Ibri Landfill | E55: 23.151661 | F55: 56.499878 | G55: 23.164166 | H55: 56.516439 | I55: =TRUE() -> 1
A56: 606108ea-2762-4ef9-8f3f-43d07c952b0f | B56: South America | C56: Colombia | D56: Countrywide | E56: -4.226944 | F56: -79.008056 | G56: 12.158333 | H56: -67.403721 | I56: =TRUE() -> TRUE
A57: 57d3f87b-b4d1-4c05-ba9f-c22985301626 | B57: Africa | C57: Nigeria | D57: Several Regions | E57: 4.271006 | F57: 2.712172 | G57: 13.886373 | H57: 14.653978 | I57: =TRUE() -> TRUE
A58: bc12f4e8-1ebb-4b9c-8f46-88ba677ecd9f | B58: South America | C58: Colombia | D58: Several Regions | E58: -4.226944 | F58: -79.008056 | G58: 12.458333 | H58: -66.850278 | I58: =TRUE() -> 1
A59: ea76025a-e2f4-4340-80ac-30c69ef63a25 | B59: Europe | C59: Netherlands | D59: Countrywide | E59: 50.750417 | F59: 3.358333 | G59: 53.555 | H59: 7.227778 | I59: =TRUE() -> TRUE
A60: 445a733c-15c8-4e48-91db-eea8375dd7e7 | B60: Global | C60: Global | D60: Global | E60: NA | F60: NA | G60: NA | H60: NA | I60: =FALSE() -> 0
A61: 8eea5480-ab2d-4198-b186-ff3a2a35530b | B61: Asia | C61: Kazakhstan | D61: Mangistau | E61: 43.351682 | F61: 49.515193 | G61: 46.870201 | H61: 55.315996 | I61: =TRUE() -> 1
A62: 6fc6e256-0b50-4bb7-bd2b-327729626840 | B62: Asia | C62: Turkmenistan | D62: Countrywide | E62: 35.132628 | F62: 52.407025 | G62: 42.797688 | H62: 66.707063 | I62: =TRUE() -> TRUE
A63: 3734bc0b-edd3-43b5-a0ef-f571df049e72 | B63: Africa | C63: NA | D63: NA | E63: -34.849228 | F63: 14.74476 | G63: 37.446124 | H63: 51.374309 | I63: =TRUE() -> 1
A64: 68e86704-9ac8-426b-80d5-5e1e04d89464 | B64: South America | C64: NA | D64: NA | E64: -55.757543 | F64: -82.099132 | G64: 12.555231 | H64: -33.545738 | I64: =TRUE() -> TRUE
A65: 28730545-664b-479f-a684-2de043a42bb7 | B65: Australia_Oceania | C65: Australia | D65: NA | E65: -34.790969 | F65: 138.63214 | G65: -34.785436 | H65: 138.64082 | I65: =TRUE() -> 1
A66: 46f446eb-a58b-4100-a43f-f27e135a28bd | B66: North America | C66: USA | D66: Permian Basin | E66: 29.462935 | F66: -105.21988 | G66: 34.021515 | H66: -100.03611 | I66: =TRUE() -> 1
A67: b79eca4e-1d49-4e3f-b7c8-ba1617e5cf02 | B67: Asia | C67: Turkmenistan | D67: Balkan Region | E67: 37.58806 | F67: 52.040222 | G67: 40.173582 | H67: 54.875839 | I67: =TRUE() -> TRUE
A68: 8e92b34b-430d-4add-9de7-4493542342f0 | B68: Europe | C68: Spain | D68: Madrid | E68: 40.300396 | F68: -3.8770473 | G68: 40.551173 | H68: -3.5233763 | I68: =TRUE() -> TRUE
A69: e8e24a53-c02d-4cf9-94b5-dd1c51e56373 | B69: South America | C69: Colombia | D69: Colombia (Several Regions) | E69: -4.226944 | F69: -79.008056 | G69: 12.652488 | H69: -67.130508 | I69: =TRUE() -> TRUE
A70: 178c75a4-5c5f-48f9-8794-828cbf1687e3 | B70: South America | C70: Colombia | D70: Several Regions | E70: -4.226944 | F70: -79.008056 | G70: 12.582488 | H70: -67.403721 | I70: =TRUE() -> TRUE
A71: ed655758-d5ff-40de-810f-8dea21e9dd8a | B71: South America | C71: Colombia | D71: Several Regions | E71: -4.226944 | F71: -79.008056 | G71: 12.158333 | H71: -66.850278 | I71: =TRUE() -> TRUE
A72: eada962d-d450-4a03-a68a-50387d3b4b71 | B72: Asia | C72: India | D72: India (Countrywide) | E72: 9.4998928 | F72: 67.65267 | G72: 32.971948 | H72: 89.943465 | I72: =TRUE() -> 1
... A76: 4c082d4b-baea-4b3d-92cf-eb2072ae73c6 | B76: North America | C76: USA | D76: USA (Countrywide) | E76: 25.594206 | F76: -125.86888 | G76: 49.018545 | H76: -66.971824 | I76: =TRUE() -> TRUE
A77: 64bd905c-815a-4d4f-8ab7-5ac89e1d4b28 | B77: North America | C77: Canada | D77: Canada (Countrywide) | E77: NA | F77: NA | G77: NA | H77: NA | I77: NA
A78: 6ade0c9e-91d6-4d3e-afac-bdb4cab297f6 | B78: South America | C78: Argentina | D78: Argentina (Countrywide) | E78: NA | F78: NA | G78: NA | H78: NA | I78: NA
A79: 1959b484-0005-4d19-ab1c-c4fe70ba8f17 | B79: South America | C79: Bolivia | D79: Bolivia (Countrywide) | E79: NA | F79: NA | G79: NA | H79: NA | I79: NA
A80: 1358c927-aa21-401b-81d8-e8855d8edc91 | B80: South America | C80: Brazil | D80: Brazil (Countrywide) | E80: NA | F80: NA | G80: NA | H80: NA | I80: NA
A81: 27fb3548-cafb-4c34-9cdf-a4fbd625f063 | B81: South America | C81: Chile | D81: Chile (Countrywide) | E81: NA | F81: NA | G81: NA | H81: NA | I81: NA
A82: 86c2e4cb-631d-4311-80fa-d8519a151186 | B82: South America | C82: Ecuador | D82: Ecuador (Countrywide) | E82: NA | F82: NA | G82: NA | H82: NA | I82: NA
A83: df1d07fe-091b-476b-9113-5fab52f8c8fb | B83: South America | C83: French Guiana | D83: French Guiana (Countrywide) | E83: NA | F83: NA | G83: NA | H83: NA | I83: NA
A84: e6d990bc-4d1f-414e-9165-944eb8d2d107 | B84: South America | C84: Guyana | D84: Guyana (Countrywide) | E84: NA | F84: NA | G84: NA | H84: NA | I84: NA
A85: 26b1d9ba-7d77-4a14-8cc7-80b527fe639d | B85: South America | C85: Paraguay | D85: Paraguay (Countrywide) | E85: NA | F85: NA | G85: NA | H85: NA | I85: NA
A86: b16484fe-79c8-45cd-b3f6-61874d0d8133 | B86: South America | C86: Peru | D86: Peru (Countrywide) | E86: NA | F86: NA | G86: NA | H86: NA | I86: NA
A87: d4cac3c7-dc6b-4cee-a77e-f1b5564dc4c2 | B87: South America | C87: Suriname | D87: Suriname (Countrywide) | E87: NA | F87: NA | G87: NA | H87: NA | I87: NA
A88: 4252ed9d-730a-4fc1-bb37-c52054498cbb | B88: South America | C88: Uruguay | D88: Uruguay (Countrywide) | E88: NA | F88: NA | G88: NA | H88: NA | I88: NA
... A91: d24f6e1a-92a1-4f31-9402-2a5e9236963d | B91: Africa | C91: Algeria | D91: Hassi R'Mel | E91: 33.15 | F91: 2.55 | G91: 33.45 | H91: 3 | I91: NA
A92: e5670442-e869-4bcc-99b3-5634d6c7653b | B92: Europe | C92: Romania | D92: Ploiești | E92: 44.933334 | F92: 26.033333 | G92: 44.933334 | H92: 26.033333 | I92: NA
A93: 0723a1e1-b84a-4b67-9be3-1f7a424f16a7 | B93: Europe | C93: Romania | D93: Drumul Potcoavei | E93: 44.505 | F93: 26.133 | G93: 44.505 | H93: 26.133 | I93: NA
A94: e517bef1-917c-4d0c-baaf-e3c5e3777698 | B94: Europe | C94: Germany | D94: Hamburg | E94: 53.2 | F94: 9.25 | G94: 53.8 | H94: 10.75 | I94: NA
A95: d84f282c-b864-4fab-898f-e55c22e8a004 | B95: Europe | C95: Romania | D95: Several Regions | E95: 44.2 | F95: 25.25 | G95: 45.2 | H95: 27 | I95: NA
A96: ad6b2e7f-09cc-407f-b639-def4f5495508 | B96: Asia | C96: China | D96: China (Countrywide) | E96: 15.72 | F96: 72.25 | G96: 54.75 | H96: 135.25 | I96: NA
A97: e9b8e83a-3b2d-4dee-99ad-d3cf27ab570b | B97: Asia | C97: Bangladesh | D97: Bangladesh (Countrywide) | E97: 20.34 | F97: 88.01 | G97: 26.38 | H97: 92.41 | I97: NA
A98: 23ace4e9-1100-4519-a370-43b3fc9ff7ff | B98: Asia | C98: Vietnam | D98: Vietnam (Countrywide) | E98: 8.1 | F98: 102.09 | G98: 123.24 | H98: 109.3 | I98: NA
A99: 77660e6e-dc17-4540-bb57-30681f7e1ee2 | B99: Asia | C99: Thailand | D99: Thailand (Countrywide) | E99: 5.37 | F99: 97.22 | G99: 20.27 | H99: 105.37 | I99: NA
A100: 78ae91eb-a358-4c05-9eb8-04049c1fa25f | B100: Africa | C100: Nigeria | D100: Nigeria (Countrywide) | E100: 4 | F100: 2 | G100: 14 | H100: 14 | I100: =FALSE() -> 0
A101: a881d501-0ccc-410f-a319-313e3b2b2565 | B101: Africa | C101: Madagascar | D101: Madagascar (Countrywide) | E101: 41 | F101: 13 | G101: 51 | H101: 26 | I101: NA
A102: 6d288d82-4cfe-407f-b146-df4d08905a3c | B102: Africa | C102: Egypt | D102: Egypt (Countrywide) | E102: 22 | F102: 25 | G102: 32 | H102: 35 | I102: NA
A103: 57f1d020-b141-4b7f-96cb-3f9d4efb2714 | B103: Europe | C103: Spain | D103: Spain (Countrywide) | E103: 27 | F103: 19 | G103: 44 | H103: 5 | I103: NA
A104: b3f35237-5733-4cc6-a80a-c80dd8810309 | B104: South America | C104: NA | D104: South America (Region) | E104: 57.5 | F104: 13.25 | G104: -82.8125 | H104: -33.75 | I104: NA
A105: ebef2377-4e09-4309-a832-88ca3822edc5 | B105: Asia | C105: India | D105: Jharia Coalfield | E105: 23.4 | F105: 86.15 | G105: 23.47 | H105: 86.3 | I105: NA
A106: 5a2412ab-2f3d-4221-baa1-5c4c5eb33037 | B106: Asia | C106: China | D106: Shanxi Province | E106: 35 | F106: 110 | G106: 40 | H106: 115 | I106: NA
A107: 2c9a7032-2bfc-46b9-ad87-3f17170713c5 | B107: North America | C107: USA | D107: Cambria County, PA | E107: 39.4953 | F107: -79.71 | G107: 40.4953 | H107: -77.71 | I107: NA
A108: d8990385-519a-476a-842f-0015b684e564 | B108: Asia | C108: China | D108: Jincheng Coalfield | E108: 35.490701 | F108: 112.851831 | G108: 35.490701 | H108: 112.851831 | I108: NA
A109: d404c140-5b5a-420e-9034-90a025523000 | B109: Asia | C109: China | D109: Huainan–Huaibei Coalfield | E109: 32.625477 | F109: 116.99993 | G109: 32.625477 | H109: 116.99993 | I109: NA
A110: 3e9b434c-cd97-4b4a-a8a0-46e679875244 | B110: Asia | C110: India | D110: Coalfields in India (Gondwana and Tertiary formations) | E110: 44.2883667 | F110: 25.3813917 | G110: 45.1541567 | H110: 26.97952115 | I110: NA
A111: 94c18ee8-32a1-46e5-9666-7e9fde2656e4 | B111: North America | C111: USA | D111: Weld County, CO | E111: 40.52 | F111: 104.47 | G111: 40.52 | H111: 104.47 | I111: NA
A112: 71ec89bd-c1f6-4f87-a871-1521153da716 | B112: North America | C112: USA | D112: Appalachian Basin | E112: 38 | F112: -83.53 | G112: 43.75 | H112: -74.5 | I112: NA
A113: 34df7f60-e391-460c-8432-58961198b42c | B113: North America | C113: USA | D113: Greater Green River Basin | E113: 38.59 | F113: 110.09 | G113: 38.59 | H113: 110.09 | I113: NA
A114: eaad33be-1f1a-4534-952f-564af3aad39e | B114: North America | C114: USA | D114: Fayetteville Shale study area, Arkansas | E114: 36.0619 | F114: 94.1579 | G114: 36.0619 | H114: 94.1579 | I114: NA
A115: 2e69a418-d6d4-4729-9eea-c37be0dea410 | B115: Asia | C115: Turkey | D115: Kilimli district, Zonguldak Hard Coal Basin | E115: 41.48 | F115: 31.83 | G115: 41.48 | H115: 31.83 | I115: NA
A116: 8ccfd510-f608-4cfd-a59b-82e1682e0102 | B116: North America | C116: USA | D116: Pennsylvania | E116: 39.5 | F116: -81 | G116: 42 | H116: -77 | I116: NA
A117: 76d87c69-f8ef-47fc-8cf6-c6d281c27d40 | B117: North America | C117: USA | D117: West Virginia | E117: 37 | F117: -83 | G117: 41 | H117: -78 | I117: NA
A118: ffce7890-a6e7-47e3-b100-a73e0c380a08 | B118: North America | C118: USA | D118: Marcellus Shale Basin | E118: 36.5 | F118: -84.5 | G118: 43.5 | H118: -73 | I118: NA
A119: 8db4c06d-552a-46da-bf9b-0e1d60c6c4f0 | B119: North America | C119: USA | D119: East Texas | E119: 29.5 | F119: -96.2 | G119: 33.9 | H119: -93.5 | I119: NA
...

Sheet Measurement_ID
A1: id _measurement | B1: id_location | C1: paper_id | D1: id_study | E1: sector | F1: subsector | G1: sub-subsector | H1: OGMP | I1: activity | J1: emission_source | K1: spatial_resolution | L1: spatial_resolution_other_specification | M1: temporal_resolution | N1: temporal_resolution_other_specification | O1: notes | P1: measurement_start | Q1: measurement_end | R1: Number | S1: estimate_type | T1: emission_value | U1: uncertainty_min | V1: uncertainty_max | W1: units | X1: Uncertainty type | Y1: FLAG - Repeated/Aggregated value | Z1: FLAG -Eye_on_Methane
E2: {=_xlfn.unique(cat_table[Sector])} -> #NAME? | H2: Upstream oil and gas | K2: Component | M2: Second or sub-second | P2: MM/DD/YYYY | Q2: MM/DD/YYYY | S2: Average | X2: Calculated | Z2: 0
E3: #NAME? | H3: Midstream oil and gas | K3: Functional element | M3: Snapshot | S3: Central estimate | X3: Provided in-paper - Standard deviation | Z3: 1
E4: #NAME? | H4: Downstream oil and gas | K4: Site | M4: Minutely | S4: Sum of site level | X4: Provided in-paper - Confidence Interval
E5: #NAME? | K5: Regional | M5: Hourly | S5: Area Total | X5: Other
E6: #NAME? | K6: National | M6: Daily | S6: Point-Source
E7: #NAME? | K7: Global | M7: Monthly | S7: Other
E8: #NAME? | K8: Other | M8: Annually
E9: #NAME? | M9: Other
A10: 02c32d82-a465-4920-a6a3-826e3850d74e | B10: 55d6e423-92c7-4774-a664-3132cd2c03ae | C10: 6fcc0d8d-bb28-4548-9495-e31cb3fa2e99 | D10: 70f2024b-e279-4d03-9ca1-d8c1be5c09b0 | E10: Energy | F10: Fugitive Emissions from Fuels | G10: Fugitive Emissions from Oil Production | H10: Upstream oil and gas | I10: Shipboard measurement campaign of offshore oil and gas production | J10: Plumes from shallow and deepwater offshore platforms and drillships | K10: Site | L10: Gulf of Mexico | M10: Second or sub-second | N10: 1 s TILDAS measurements | O10: Average emission value across all platforms | P10: 43143 | Q10: 43153 | R10: 103 | S10: Average | T10: 17 | W10: kg/h | Y10: 1 | Z10: 1 | AE10: {=_xlfn.torow(_xlfn.unique(_xlfn._xlws.filter(cat_table[Subsector],$E10=cat_table[Sector],"")))} -> #NAME? | AF10: #NAME? | AG10: #NAME? | AH10: #NAME? | AI10: #NAME? | AJ10: #NAME? | AK10: #NAME? | AO10: {=_xlfn.torow(_xlfn.unique(_xlfn._xlws.filter(cat_table[Sub-subsector],($E10=cat_table[Sector])*($F10=cat_table[Subsector]),"")))} -> #NAME? | AP10: #NAME? | AQ10: #NAME? | AR10: #NAME? | AS10: #NAME? | AT10: #NAME?
A11: 973f1e24-45ab-4113-a9ed-d42417389636 | B11: 55d6e423-92c7-4774-a664-3132cd2c03ae | C11: 6fcc0d8d-bb28-4548-9495-e31cb3fa2e99 | D11: 70f2024b-e279-4d03-9ca1-d8c1be5c09b0 | E11: Energy | F11: Fugitive Emissions from Fuels | G11: Fugitive Emissions from Oil Production | H11: Upstream oil and gas | I11: Shipboard measurement campaign of offshore oil and gas production | J11: Platforms with no detected downwind methane enhancement | K11: Site | L11: Gulf of Mexico | M11: Second or sub-second | N11: 1 s TILDAS measurements | O11: “Null” sites: no plume detected | P11: 43143 | Q11: 43153 | R11: 28 | S11: Other | T11: 0 | W11: kg/h | Y11: 1 | Z11: 1 | AE11: {=_xlfn.torow(_xlfn.unique(_xlfn._xlws.filter(cat_table[Subsector],$E11=cat_table[Sector],"")))} -> #NAME? | AF11: #NAME? | AG11: #NAME? | AH11: #NAME? | AI11: #NAME? | AJ11: #NAME? | AK11: #NAME? | AO11: {=_xlfn.torow(_xlfn.unique(_xlfn._xlws.filter(cat_table[Sub-subsector],($E11=cat_table[Sector])*($F11=cat_table[Subsector]),"")))} -> #NAME? | AP11: #NAME? | AQ11: #NAME? | AR11: #NAME? | AS11: #NAME? | AT11: #NAME?
A12: a90b8953-d89c-429d-ac85-a2597139b3a5 | B12: 55d6e423-92c7-4774-a664-3132cd2c03ae | C12: 6fcc0d8d-bb28-4548-9495-e31cb3fa2e99 | D12: 70f2024b-e279-4d03-9ca1-d8c1be5c09b0 | E12: Energy | F12: Fugitive Emissions from Fuels | G12: Fugitive Emissions from Oil Production | H12: Upstream oil and gas | I12: Shipboard measurement campaign of offshore oil and gas production | J12: Median platform emission rate from shallow and deepwater offshore platforms and drillships | K12: Site | L12: Gulf of Mexico | M12: Second or sub-second | N12: 1 s TILDAS measurements | O12: Median across all 103 platforms | P12: 43143 | Q12: 43153 | R12: 103 | S12: Central estimate | T12: 5.3 | W12: kg/h | Y12: 1 | Z12: 1 | AE12: {=_xlfn.torow(_xlfn.unique(_xlfn._xlws.filter(cat_table[Subsector],$E12=cat_table[Sector],"")))} -> #NAME? | AF12: #NAME? | AG12: #NAME? | AH12: #NAME? | AI12: #NAME? | AJ12: #NAME? | AK12: #NAME? | AO12: {=_xlfn.torow(_xlfn.unique(_xlfn._xlws.filter(cat_table[Sub-subsector],($E12=cat_table[Sector])*($F12=cat_table[Subsector]),"")))} -> #NAME? | AP12: #NAME? | AQ12: #NAME? | AR12: #NAME? | AS12: #NAME? | AT12: #NAME?
A13: 80733ef0-6a8e-4a56-ad47-e043822a482b | B13: 55d6e423-92c7-4774-a664-3132cd2c03ae | C13: 6fcc0d8d-bb28-4548-9495-e31cb3fa2e99 | D13: 70f2024b-e279-4d03-9ca1-d8c1be5c09b0 | E13: Energy | F13: Fugitive Emissions from Fuels | G13: Fugitive Emissions from Oil Production | H13: Upstream oil and gas | I13: Shipboard measurement campaign of offshore oil and gas production | J13: Maximum observed platform emission rate | K13: Site | L13: Gulf of Mexico | M13: Second or sub-second | N13: 1 s TILDAS measurements | O13: Highest single‐site value | P13: 43143 | Q13: 43153 | R13: 1 | S13: Point-Source | T13: 185 | W13: kg/h | Y13: 0 | Z13: 1 | AE13: {=_xlfn.torow(_xlfn.unique(_xlfn._xlws.filter(cat_table[Subsector],$E13=cat_table[Sector],"")))} -> #NAME? | AF13: #NAME? | AG13: #NAME? | AH13: #NAME? | AI13: #NAME? | AJ13: #NAME? | AK13: #NAME? | AO13: {=_xlfn.torow(_xlfn.unique(_xlfn._xlws.filter(cat_table[Sub-subsector],($E13=cat_table[Sector])*($F13=cat_table[Subsector]),"")))} -> #NAME? | AP13: #NAME? | AQ13: #NAME? | AR13: #NAME? | AS13: #NAME? | AT13: #NAME?
A14: 06a89a92-a94f-4d11-9a38-8b961e91adda | B14: 2cd1fa0d-1746-4baa-a4b5-812ef763645f | C14: 6fcc0d8d-bb28-4548-9495-e31cb3fa2e99 | D14: 70f2024b-e279-4d03-9ca1-d8c1be5c09b0 | E14: Energy | F14: Fugitive Emissions from Fuels | G14: Fugitive Emissions from Oil Production | H14: Upstream oil and gas | I14: Shipboard measurement campaign of offshore oil and gas production | J14: Fixed Leg Platform | K14: Site | L14: Gulf of Mexico Offshore Platform 1 | M14: Second or sub-second | N14: 1 s TILDAS measurements | O14: Lat/Lon: 29.18051, -94.52122 | Structure: A | Field: HI179 | Lease: G03236 | Complex ID: 10082 | Water depth (ft): 54.0 | Valid plumes counted: 7 | P14: 43143 | Q14: 43143 | R14: 7 (plumes) | S14: Point-Source | T14: 8.9361385 | U14: 0.89 | V14: 89.4 | W14: kg/h | X14: Provided in-paper - Confidence Interval | Y14: 0 | Z14: 1
A15: 402d914a-16aa-4df1-8856-3fb8822e1d5a | B15: dae31a83-36a6-4c7e-b4c8-5875fb337582 | C15: 6fcc0d8d-bb28-4548-9495-e31cb3fa2e99 | D15: 70f2024b-e279-4d03-9ca1-d8c1be5c09b0 | E15: Energy | F15: Fugitive Emissions from Fuels | G15: Fugitive Emissions from Oil Production | H15: Upstream oil and gas | I15: Shipboard measurement campaign of offshore oil and gas production | J15: Fixed Leg Platform | K15: Site | L15: Gulf of Mexico Offshore Platform 2 | M15: Second or sub-second | N15: 1 s TILDAS measurements | O15: Lat/Lon: 29.13032, -94.54623 | Structure: C | Field: GA209 | Lease: G06093 | Complex ID: 28051 | Water depth (ft): 58.0 | Valid plumes counted: 7 | 95% CI present | Analyst note: 2 sites with inventory emissions, We choose point in between. // 29.130284-94.546568 // 2.2// 29.130363-94.545972 // 2.4// 1 site with no inventory emisions // 29.129991,-94.545957 | P15: 43143 | Q15: 43143 | R15: 7 | S15: Sum of site level | T15: 25.012797 | U15: 2.5 | V15: 250.1 | W15: kg/h | X15: Provided in-paper - Confidence Interval | Y15: 0 | Z15: 1
A16: 61339072-d796-4a0d-ba85-3c49059ec4e9 | B16: 5673b0a8-44c8-4812-8e88-7a36ed2b9561 | C16: 6fcc0d8d-bb28-4548-9495-e31cb3fa2e99 | D16: 70f2024b-e279-4d03-9ca1-d8c1be5c09b0 | E16: Energy | F16: Fugitive Emissions from Fuels | G16: Fugitive Emissions from Oil Production | H16: Upstream oil and gas | I16: Shipboard measurement campaign of offshore oil and gas production | J16: Caisson | K16: Site | L16: Gulf of Mexico Offshore Platform 3 | M16: Second or sub-second | N16: 1 s TILDAS measurements | O16: Lat/Lon: 29.13185, -94.60696 | Structure: 1 | Field: 1 | Lease: G25524 | Complex ID: 1620 | Water depth (ft): 60.0 | Valid plumes counted: 5 | 95% CI present | Analyst note: one site with production, other two none | P16: 43143 | Q16: 43143 | R16: 5 | S16: Point-Source | T16: 1.7587947 | U16: 0.18 | V16: 17.6 | W16: kg/h | X16: Provided in-paper - Confidence Interval | Y16: 0 | Z16: 1
A17: 6a907fa2-6818-46a4-aba1-a5914f12e062 | B17: df22bf5f-b6d7-4a3e-b0b7-ecda0d155034 | C17: 6fcc0d8d-bb28-4548-9495-e31cb3fa2e99 | D17: 70f2024b-e279-4d03-9ca1-d8c1be5c09b0 | E17: Energy | F17: Fugitive Emissions from Fuels | G17: Fugitive Emissions from Oil Production | H17: Upstream oil and gas | I17: Shipboard measurement campaign of offshore oil and gas production | J17: Fixed Leg Platform | K17: Site | L17: Gulf of Mexico Offshore Platform 4 | M17: Second or sub-second | N17: 1 s TILDAS measurements | O17: Lat/Lon: 29.27174, -93.78466 | Structure: 5 | Field: HI129 | Lease: G01848 | Complex ID: 10070 | Water depth (ft): 49.0 | Valid plumes counted: 6 | 95% CI present | Analyst note: site ID is uncertain. Could be Site 5, which has emissions in inventory. | P17: 43145 | Q17: 43145 | R17: 6 | S17: Point-Source | T17: 35.661196 | U17: 3.57 | V17: 356.6 | W17: kg/h | X17: Provided in-paper - Confidence Interval | Y17: 0 | Z17: 1
A18: df112a1e-7d15-48e4-b7e0-2fda3c0f15a7 | B18: 10bc4dea-ebb6-4854-b1e5-8aee751dc2b7 | C18: 6fcc0d8d-bb28-4548-9495-e31cb3fa2e99 | D18: 70f2024b-e279-4d03-9ca1-d8c1be5c09b0 | E18: Energy | F18: Fugitive Emissions from Fuels | G18: Fugitive Emissions from Oil Production | H18: Upstream oil and gas | I18: Shipboard measurement campaign of offshore oil and gas production | J18: Well Protector | K18: Site | L18: Gulf of Mexico Offshore Platform 5 | M18: Second or sub-second | N18: 1 s TILDAS measurements | O18: Lat/Lon: 29.26776, -93.77714 | Structure: 18 | Field: HI129 | Lease: G01848 | Complex ID: 1391 | Water depth (ft): 50.0 | Valid plumes counted: 1 | 95% CI present | Analyst note: site ID is uncertain. Has emissions in inventory, could be site 4. | P18: 43145 | Q18: 43145 | R18: 1 | S18: Point-Source | T18: 0 | U18: 0 | V18: 3.8 | W18: kg/h | X18: Provided in-paper - Confidence Interval | Y18: 0 | Z18: 1
A19: 4fba8a91-b330-4c9f-ad11-6d18737c513e | B19: 2d9c6ba9-5081-4ef8-87f6-4a02b4a241f8 | C19: 6fcc0d8d-bb28-4548-9495-e31cb3fa2e99 | D19: 70f2024b-e279-4d03-9ca1-d8c1be5c09b0 | E19: Energy | F19: Fugitive Emissions from Fuels | G19: Fugitive Emissions from Oil Production | H19: Upstream oil and gas | I19: Shipboard measurement campaign of offshore oil and gas production | J19: Caisson | K19: Site | L19: Gulf of Mexico Offshore Platform 6 | M19: Second or sub-second | N19: 1 s TILDAS measurements | O19: Lat/Lon: 29.24039, -93.79456 | Structure: 16 | Field: HI129 | Lease: G01848 | Complex ID: 1263 | Water depth (ft): 42.0 | Valid plumes counted: 3 | 95% CI present | Analyst note: very low intensity, ethane/methane ~ 4.3% | P19: 43145 | Q19: 43145 | R19: 3 | S19: Point-Source | T19: 0.18366067 | U19: 0.02 | V19: 1.8 | W19: kg/h | X19: Provided in-paper - Confidence Interval | Y19: 0 | Z19: 1
A20: 1d0e04fa-eb08-430d-b461-77ec439af02a | B20: db6fabd1-4d10-4d05-8da4-42618cbc7354 | C20: 6fcc0d8d-bb28-4548-9495-e31cb3fa2e99 | D20: 70f2024b-e279-4d03-9ca1-d8c1be5c09b0 | E20: Energy | F20: Fugitive Emissions from Fuels | G20: Fugitive Emissions from Oil Production | H20: Upstream oil and gas | I20: Shipboard measurement campaign of offshore oil and gas production | J20: Caisson | K20: Site | L20: Gulf of Mexico Offshore Platform 7 | M20: Second or sub-second | N20: 1 s TILDAS measurements | O20: Lat/Lon: 29.24479, -93.79239 | Structure: 1 | Field: HI129 | Lease: G01848 | Complex ID: 10042 | Water depth (ft): 40.0 | Valid plumes counted: 2 | 95% CI present | Analyst note: next to site 14. | P20: 43145 | Q20: 43145 | R20: 2 | S20: Point-Source | T20: 0 | U20: 0 | V20: 0.4 | W20: kg/h | X20: Provided in-paper - Confidence Interval | Y20: 0 | Z20: 1
A21: 2b56df5d-3f0b-4a8e-86a9-03a82305a4e7 | B21: 4dc0e04c-afc0-479c-b60d-b5d268fb10eb | C21: 6fcc0d8d-bb28-4548-9495-e31cb3fa2e99 | D21: 70f2024b-e279-4d03-9ca1-d8c1be5c09b0 | E21: Energy | F21: Fugitive Emissions from Fuels | G21: Fugitive Emissions from Oil Production | H21: Upstream oil and gas | I21: Shipboard measurement campaign of offshore oil and gas production | J21: Fixed Leg Platform | K21: Site | L21: Gulf of Mexico Offshore Platform 8 | M21: Second or sub-second | N21: 1 s TILDAS measurements | O21: Lat/Lon: 29.30568, -93.02510 | Structure: PP-VALVE | Lease: 643 | Complex ID: 25025 | Water depth (ft): 59.0 | Valid plumes counted: 1 | 95% CI present | Analyst note: very low intensity, but ethane is ~3.8% | P21: 43145 | Q21: 43145 | R21: 1 | S21: Point-Source | T21: 0.60472278 | U21: 0.06 | V21: 6 | W21: kg/h | X21: Provided in-paper - Confidence Interval | Y21: 0 | Z21: 1
A22: dc20d70b-578b-4845-843b-8b98f657b9d3 | B22: 503de734-5ed5-4d42-8da2-bd2cd886b5d2 | C22: 6fcc0d8d-bb28-4548-9495-e31cb3fa2e99 | D22: 70f2024b-e279-4d03-9ca1-d8c1be5c09b0 | E22: Energy | F22: Fugitive Emissions from Fuels | G22: Fugitive Emissions from Oil Production | H22: Upstream oil and gas | I22: Shipboard measurement campaign of offshore oil and gas production | J22: Fixed Leg Platform | K22: Site | L22: Gulf of Mexico Offshore Platform 9 | M22: Second or sub-second | N22: 1 s TILDAS measurements | O22: Lat/Lon: 29.33651, -92.98829 | Structure: D | Field: WILD | Lease: G25937 | Complex ID: 2275 | Water depth (ft): 55.0 | Valid plumes counted: 4 | 95% CI present | P22: 43145 | Q22: 43145 | R22: 4 | S22: Point-Source | T22: 17.049237 | U22: 1.7 | V22: 170.5 | W22: kg/h | X22: Provided in-paper - Confidence Interval | Y22: 0 | Z22: 1
A23: 44e14ace-87df-4a5e-aba3-cf962f2dc790 | B23: 6955d04e-3c26-4500-90db-f23ad9f7fd58 | C23: 6fcc0d8d-bb28-4548-9495-e31cb3fa2e99 | D23: 70f2024b-e279-4d03-9ca1-d8c1be5c09b0 | E23: Energy | F23: Fugitive Emissions from Fuels | G23: Fugitive Emissions from Oil Production | H23: Upstream oil and gas | I23: Shipboard measurement campaign of offshore oil and gas production | J23: Caisson | K23: Site | L23: Gulf of Mexico Offshore Platform 10 | M23: Second or sub-second | N23: 1 s TILDAS measurements | O23: Lat/Lon: 29.46360, -92.05065 | Structure: 230 | Field: LP000 | Lease: 310 | Complex ID: 2158 | Water depth (ft): 14.0 | Valid plumes counted: 2 | 95% CI present | Analyst note: congested area with lots of removed sites | P23: 43145 | Q23: 43145 | R23: 2 | S23: Point-Source | T23: 0 | U23: 0 | V23: 0.4 | W23: kg/h | X23: Provided in-paper - Confidence Interval | Y23: 0 | Z23: 1
A24: da655b26-f730-464a-aeda-5259a4a15221 | B24: 8ae1e267-5049-429c-80ec-8ade58017d7d | C24: 6fcc0d8d-bb28-4548-9495-e31cb3fa2e99 | D24: 70f2024b-e279-4d03-9ca1-d8c1be5c09b0 | E24: Energy | F24: Fugitive Emissions from Fuels | G24: Fugitive Emissions from Oil Production | H24: Upstream oil and gas | I24: Shipboard measurement campaign of offshore oil and gas production | J24: Caisson | K24: Site | L24: Gulf of Mexico Offshore Platform 11 | M24: Second or sub-second | N24: 1 s TILDAS measurements | O24: Lat/Lon: 29.47290, -92.04869 | Structure: 228 | Field: LP000 | Lease: 310 | Complex ID: 2121 | Water depth (ft): 11.0 | Valid plumes counted: 4 | 95% CI present | P24: 43145 | Q24: 43145 | R24: 4 | S24: Point-Source | T24: 0.93219242 | U24: 0.09 | V24: 9.3 | W24: kg/h | X24: Provided in-paper - Confidence Interval | Y24: 0 | Z24: 1
A25: d868119e-4d46-47a0-8eec-c24fc2c58af0 | B25: 5dc56435-81ad-40df-aab4-24680d44c61d | C25: 6fcc0d8d-bb28-4548-9495-e31cb3fa2e99 | D25: 70f2024b-e279-4d03-9ca1-d8c1be5c09b0 | E25: Energy | F25: Fugitive Emissions from Fuels | G25: Fugitive Emissions from Oil Production | H25: Upstream oil and gas | I25: Shipboard measurement campaign of offshore oil and gas production | J25: Caisson | K25: Site | L25: Gulf of Mexico Offshore Platform 12 | M25: Second or sub-second | N25: 1 s TILDAS measurements | O25: Lat/Lon: 29.48740, -92.05338 | Structure: 229 | Field: LP000 | Lease: 310 | Complex ID: 2159 | Water depth (ft): 11.0 | Valid plumes counted: 4 | 95% CI present | P25: 43145 | Q25: 43145 | R25: 4 | S25: Point-Source | T25: 0.14032674 | U25: 0.01 | V25: 1.4 | W25: kg/h | X25: Provided in-paper - Confidence Interval | Y25: 0 | Z25: 1
A26: 1adeeb67-ea5b-4145-9804-df241dce9d85 | B26: 2938dfa3-2c21-480c-8c19-7fe9b62e2537 | C26: 6fcc0d8d-bb28-4548-9495-e31cb3fa2e99 | D26: 70f2024b-e279-4d03-9ca1-d8c1be5c09b0 | E26: Energy | F26: Fugitive Emissions from Fuels | G26: Fugitive Emissions from Oil Production | H26: Upstream oil and gas | I26: Shipboard measurement campaign of offshore oil and gas production | J26: Caisson | K26: Site | L26: Gulf of Mexico Offshore Platform 13 | M26: Second or sub-second | N26: 1 s TILDAS measurements | O26: Lat/Lon: 29.48019, -92.05100 | Structure: 232 | Field: LP000 | Lease: 310 | Complex ID: 2220 | Water depth (ft): 12.0 | Valid plumes counted: 3 | 95% CI present | Analyst note: two upwind sites with no emissions. | P26: 43145 | Q26: 43145 | R26: 3 | S26: Sum of site level | T26: 0.39407051 | U26: 0.04 | V26: 3.9 | W26: kg/h | X26: Provided in-paper - Confidence Interval | Y26: 0 | Z26: 1
... A28: 42c07eaf-0219-49bf-947c-c2e192f15b89 | B28: 36e171ee-afb9-4224-99d9-567f0f4b1177 | C28: 6fcc0d8d-bb28-4548-9495-e31cb3fa2e99 | D28: 70f2024b-e279-4d03-9ca1-d8c1be5c09b0 | E28: Energy | F28: Fugitive Emissions from Fuels | G28: Fugitive Emissions from Oil Production | H28: Upstream oil and gas | I28: Shipboard measurement campaign of offshore oil and gas production | J28: Fixed Leg Platform | K28: Site | L28: Gulf of Mexico Offshore Platform 15 | M28: Second or sub-second | N28: 1 s TILDAS measurements | O28: Lat/Lon: 29.38232, -91.77993 | Structure: G | Field: EI024 | Lease: G23851 | Complex ID: 2253 | Water depth (ft): 12.0 | Valid plumes counted: 6 | 95% CI present | Analyst note: One of a cluster of sites, all emitting. Individual platform assignment uncertain due to congestion | P28: 43145 | Q28: 43145 | R28: 6 | S28: Sum of site level | T28: 37.291298 | U28: 3.73 | V28: 372.9 | W28: kg/h | X28: Provided in-paper - Confidence Interval | Y28: 0 | Z28: 1
A29: b3a2aac0-0ef7-4f51-808f-9ced6f5bb66a | B29: 42f0daad-303a-4168-b5f0-5b8f2ccd39e9 | C29: 6fcc0d8d-bb28-4548-9495-e31cb3fa2e99 | D29: 70f2024b-e279-4d03-9ca1-d8c1be5c09b0 | E29: Energy | F29: Fugitive Emissions from Fuels | G29: Fugitive Emissions from Oil Production | H29: Upstream oil and gas | I29: Shipboard measurement campaign of offshore oil and gas production | K29: Site | L29: Gulf of Mexico Offshore Platform 16 | M29: Second or sub-second | N29: 1 s TILDAS measurements | O29: Lat/Lon: 29.39715, -91.79681 | Valid plumes counted: 2 | 95% CI present | Analyst note: One of a cluster of sites, all emitting. Individual platform assignment uncertain due to congestion | P29: 43145 | Q29: 43145 | R29: 2 | S29: Sum of site level | T29: 2.7040548 | U29: 0.27 | V29: 27 | W29: kg/h | X29: Provided in-paper - Confidence Interval | Y29: 0 | Z29: 1
A30: c00f0c7b-af0f-41ff-99f8-bda66a086e15 | B30: 3f3b7e1c-6b54-4233-90ed-7b350826baa3 | C30: 6fcc0d8d-bb28-4548-9495-e31cb3fa2e99 | D30: 70f2024b-e279-4d03-9ca1-d8c1be5c09b0 | E30: Energy | F30: Fugitive Emissions from Fuels | G30: Fugitive Emissions from Oil Production | H30: Upstream oil and gas | I30: Shipboard measurement campaign of offshore oil and gas production | J30: Fixed Leg Platform | K30: Site | L30: Gulf of Mexico Offshore Platform 17 | M30: Second or sub-second | N30: 1 s TILDAS measurements | O30: Lat/Lon: 29.38884, -91.77606 | Structure: I | Field: EI024 | Lease: G23851 | Complex ID: 2360 | Water depth (ft): 12.0 | Valid plumes counted: 5 | 95% CI present | Analyst note: One of a cluster of sites, all emitting. Individual platform assignment uncertain due to congestion | P30: 43145 | Q30: 43145 | R30: 5 | S30: Sum of site level | T30: 16.383826 | U30: 1.64 | V30: 163.8 | W30: kg/h | X30: Provided in-paper - Confidence Interval | Y30: 0 | Z30: 1
A31: 8c6baafb-4ee2-4bfe-8d11-b295ba39bb3d | B31: b225cd59-ac4c-4c7a-9afd-badb363b1275 | C31: 6fcc0d8d-bb28-4548-9495-e31cb3fa2e99 | D31: 70f2024b-e279-4d03-9ca1-d8c1be5c09b0 | E31: Energy | F31: Fugitive Emissions from Fuels | G31: Fugitive Emissions from Oil Production | H31: Upstream oil and gas | I31: Shipboard measurement campaign of offshore oil and gas production | J31: Caisson | K31: Site | L31: Gulf of Mexico Offshore Platform 18 | M31: Second or sub-second | N31: 1 s TILDAS measurements | O31: Lat/Lon: 29.37725, -91.78925 | Structure: 1 | Field: EI024 | Lease: G02892 | Complex ID: 22521 | Valid plumes counted: 3 | 95% CI present | Analyst note: One of a cluster of sites, all emitting. Individual platform assignment uncertain due to congestion | P31: 43145 | Q31: 43145 | R31: 3 | S31: Sum of site level | T31: 3.8890807 | U31: 0.39 | V31: 38.9 | W31: kg/h | X31: Provided in-paper - Confidence Interval | Y31: 0 | Z31: 1
A32: 5f05573b-095f-4451-8906-c06579ea33d5 | B32: d69ef76e-db5a-46b0-a97f-79707c15bf53 | C32: 6fcc0d8d-bb28-4548-9495-e31cb3fa2e99 | D32: 70f2024b-e279-4d03-9ca1-d8c1be5c09b0 | E32: Energy | F32: Fugitive Emissions from Fuels | G32: Fugitive Emissions from Oil Production | H32: Upstream oil and gas | I32: Shipboard measurement campaign of offshore oil and gas production | J32: Caisson | K32: Site | L32: Gulf of Mexico Offshore Platform 19 | M32: Second or sub-second | N32: 1 s TILDAS measurements | O32: Lat/Lon: 29.35728, -91.78587 | Structure: C | Field: EI024 | Lease: G02893 | Complex ID: 1178 | Water depth (ft): 17.0 | Valid plumes counted: 3 | 95% CI present | Analyst note: neighboring site with inventory. | P32: 43145 | Q32: 43145 | R32: 3 | S32: Point-Source | T32: 14.44877 | U32: 1.44 | V32: 144.5 | W32: kg/h | X32: Provided in-paper - Confidence Interval | Y32: 0 | Z32: 1
A33: 8c2fec19-a146-426b-a8e8-820d12a3fed8 | B33: b49d578f-6a11-4abe-adfb-060a808140fb | C33: 6fcc0d8d-bb28-4548-9495-e31cb3fa2e99 | D33: 70f2024b-e279-4d03-9ca1-d8c1be5c09b0 | E33: Energy | F33: Fugitive Emissions from Fuels | G33: Fugitive Emissions from Oil Production | H33: Upstream oil and gas | I33: Shipboard measurement campaign of offshore oil and gas production | J33: Caisson | K33: Site | L33: Gulf of Mexico Offshore Platform 20 | M33: Second or sub-second | N33: 1 s TILDAS measurements | O33: Lat/Lon: 29.13247, -91.17956 | Structure: CAIS.#39 | Field: SS028 | Lease: 346 | Complex ID: 717 | Water depth (ft): 12.0 | Valid plumes counted: 2 | 95% CI present | Analyst note: neighboring sites that are removed or with no emissions | P33: 43145 | Q33: 43145 | R33: 2 | S33: Sum of site level | T33: 15.361978 | U33: 1.54 | V33: 153.6 | W33: kg/h | X33: Provided in-paper - Confidence Interval | Y33: 0 | Z33: 1
A34: 3b2bd7b3-1765-4867-b115-01f996ebfeb9 | B34: 361835ac-608b-430a-95eb-f62883f0b42f | C34: 6fcc0d8d-bb28-4548-9495-e31cb3fa2e99 | D34: 70f2024b-e279-4d03-9ca1-d8c1be5c09b0 | E34: Energy | F34: Fugitive Emissions from Fuels | G34: Fugitive Emissions from Oil Production | H34: Upstream oil and gas | I34: Shipboard measurement campaign of offshore oil and gas production | J34: Caisson | K34: Site | L34: Gulf of Mexico Offshore Platform 21 | M34: Second or sub-second | N34: 1 s TILDAS measurements | O34: Lat/Lon: 29.13892, -91.17203 | Structure: 2 | Field: SS028 | Lease: G01359 | Complex ID: 23103 | Water depth (ft): 15.0 | Valid plumes counted: 2 | 95% CI present | P34: 43145 | Q34: 43145 | R34: 2 | S34: Point-Source | T34: 8.460651 | U34: 0.85 | V34: 84.6 | W34: kg/h | X34: Provided in-paper - Confidence Interval | Y34: 0 | Z34: 1
A35: fd7f8828-1462-4c3f-ab3c-3418aa5bffd8 | B35: 3b7d8167-b5a2-4cb3-89ad-58953f29b36d | C35: 6fcc0d8d-bb28-4548-9495-e31cb3fa2e99 | D35: 70f2024b-e279-4d03-9ca1-d8c1be5c09b0 | E35: Energy | F35: Fugitive Emissions from Fuels | G35: Fugitive Emissions from Oil Production | H35: Upstream oil and gas | I35: Shipboard measurement campaign of offshore oil and gas production | J35: Caisson | K35: Site | L35: Gulf of Mexico Offshore Platform 22 | M35: Second or sub-second | N35: 1 s TILDAS measurements | O35: Lat/Lon: 29.12370, -91.11842 | Structure: 6 | Field: SS028 | Lease: 347 | Complex ID: 21245 | Water depth (ft): 12.0 | Valid plumes counted: 2 | 95% CI present | P35: 43145 | Q35: 43145 | R35: 2 | S35: Point-Source | T35: 0 | U35: 0 | V35: 0.7 | W35: kg/h | X35: Provided in-paper - Confidence Interval | Y35: 0 | Z35: 1
A36: 594445b3-56ab-4144-b227-a7316da13cb4 | B36: d83ffad6-cbba-4553-9649-10e65e4bdfad | C36: 6fcc0d8d-bb28-4548-9495-e31cb3fa2e99 | D36: 70f2024b-e279-4d03-9ca1-d8c1be5c09b0 | E36: Energy | F36: Fugitive Emissions from Fuels | G36: Fugitive Emissions from Oil Production | H36: Upstream oil and gas | I36: Shipboard measurement campaign of offshore oil and gas production | J36: Caisson | K36: Site | L36: Gulf of Mexico Offshore Platform 23 | M36: Second or sub-second | N36: 1 s TILDAS measurements | O36: Lat/Lon: 29.13084, -91.11455 | Structure: 2 | Field: SS015 | Lease: 347 | Complex ID: 22485 | Water depth (ft): 9.0 | Valid plumes counted: 3 | 95% CI present | Analyst note: site with emissions that can be quantified | P36: 43145 | Q36: 43145 | R36: 3 | S36: Point-Source | T36: 0 | U36: 0 | V36: 3.1 | W36: kg/h | X36: Provided in-paper - Confidence Interval | Y36: 0 | Z36: 1
A37: 0c888cea-7313-4179-977f-838091c2a1d7 | B37: d0f56512-e867-4511-9889-f549d880f930 | C37: 6fcc0d8d-bb28-4548-9495-e31cb3fa2e99 | D37: 70f2024b-e279-4d03-9ca1-d8c1be5c09b0 | E37: Energy | F37: Fugitive Emissions from Fuels | G37: Fugitive Emissions from Oil Production | H37: Upstream oil and gas | I37: Shipboard measurement campaign of offshore oil and gas production | J37: Caisson | K37: Site | L37: Gulf of Mexico Offshore Platform 24 | M37: Second or sub-second | N37: 1 s TILDAS measurements | O37: Lat/Lon: 29.12716, -91.17885 | Structure: 33 | Field: SS028 | Lease: 346 | Complex ID: 22120 | Water depth (ft): 14.0 | Valid plumes counted: 1 | 95% CI present | P37: 43145 | Q37: 43145 | R37: 1 | S37: Point-Source | T37: 0 | U37: 0 | V37: 2.9 | W37: kg/h | X37: Provided in-paper - Confidence Interval | Y37: 0 | Z37: 1
A38: 3a0dbb34-a3fb-456c-ac8d-441148bf4626 | B38: b2314150-04c2-4427-aca8-ed9523e2149f | C38: 6fcc0d8d-bb28-4548-9495-e31cb3fa2e99 | D38: 70f2024b-e279-4d03-9ca1-d8c1be5c09b0 | E38: Energy | F38: Fugitive Emissions from Fuels | G38: Fugitive Emissions from Oil Production | H38: Upstream oil and gas | I38: Shipboard measurement campaign of offshore oil and gas production | J38: Fixed Leg Platform | K38: Site | L38: Gulf of Mexico Offshore Platform 25 | M38: Second or sub-second | N38: 1 s TILDAS measurements | O38: Lat/Lon: 29.12078, -91.17691 | Structure: D | Field: SS028 | Lease: 346 | Complex ID: 21225 | Water depth (ft): 15.0 | Valid plumes counted: 1 | 95% CI present | Analyst note: One of a cluster of sites. Cluster is called 27. | P38: 43145 | Q38: 43145 | R38: 1 | S38: Point-Source | T38: 118.2216 | U38: 11.82 | V38: 1182.2 | W38: kg/h | X38: Provided in-paper - Confidence Interval | Y38: 0 | Z38: 1
A39: 434044de-f50c-4269-8dc5-4f1211cafb32 | B39: a6f8b1fb-122b-4b8d-b70e-60c806c5df67 | C39: 6fcc0d8d-bb28-4548-9495-e31cb3fa2e99 | D39: 70f2024b-e279-4d03-9ca1-d8c1be5c09b0 | E39: Energy | F39: Fugitive Emissions from Fuels | G39: Fugitive Emissions from Oil Production | H39: Upstream oil and gas | I39: Shipboard measurement campaign of offshore oil and gas production | J39: Fixed Leg Platform | K39: Site | L39: Gulf of Mexico Offshore Platform 26 | M39: Second or sub-second | N39: 1 s TILDAS measurements | O39: Lat/Lon: 29.11941, -91.17707 | Structure: D | Field: SS028 | Lease: 346 | Complex ID: 21225 | Water depth (ft): 15.0 | Valid plumes counted: 1 | 95% CI present | Analyst note: One of a cluster of sites. Cluster is called 27. | P39: 43145 | Q39: 43145 | R39: 1 | S39: Point-Source | T39: 10.333238 | U39: 1.03 | V39: 103.3 | W39: kg/h | X39: Provided in-paper - Confidence Interval | Y39: 0 | Z39: 1
A40: 30aa07ad-92cc-4c64-8f69-4ad245fb1de6 | B40: 6ce3f8a0-0751-4d98-87a1-66dc16511076 | C40: 6fcc0d8d-bb28-4548-9495-e31cb3fa2e99 | D40: 70f2024b-e279-4d03-9ca1-d8c1be5c09b0 | E40: Energy | F40: Fugitive Emissions from Fuels | G40: Fugitive Emissions from Oil Production | H40: Upstream oil and gas | I40: Shipboard measurement campaign of offshore oil and gas production | J40: Well Protector | K40: Site | L40: Gulf of Mexico Offshore Platform 27 | M40: Second or sub-second | N40: 1 s TILDAS measurements | O40: Lat/Lon: 29.12001, -91.17911 | Structure: E | Field: SS028 | Lease: 346 | Complex ID: 16 | Water depth (ft): 12.0 | Valid plumes counted: 1 | 95% CI present | Analyst note: One of a cluster of sites. Cluster is called 27, there is a site further upwind too | P40: 43145 | Q40: 43145 | R40: 1 | S40: Point-Source | T40: 63.222343 | U40: 6.32 | V40: 632.2 | W40: kg/h | X40: Provided in-paper - Confidence Interval | Y40: 0 | Z40: 1
A41: 811da7d9-12a9-454e-a182-d44eec594894 | B41: 468fd231-9594-44d6-9bbc-ae8e2f20c11f | C41: 6fcc0d8d-bb28-4548-9495-e31cb3fa2e99 | D41: 70f2024b-e279-4d03-9ca1-d8c1be5c09b0 | E41: Energy | F41: Fugitive Emissions from Fuels | G41: Fugitive Emissions from Oil Production | H41: Upstream oil and gas | I41: Shipboard measurement campaign of offshore oil and gas production | J41: Fixed Leg Platform | K41: Site | L41: Gulf of Mexico Offshore Platform 28 | M41: Second or sub-second | N41: 1 s TILDAS measurements | O41: Lat/Lon: 29.11127, -91.16098 | Field: SS028 | Lease: G16013;G01504;700 | Complex ID: 23521;2648 | Valid plumes counted: 1 | 95% CI present | Analyst note: three sites, 29.111369,-91.160534 // 29.111300,-91.160400 // 29.111191,-91.161545 | P41: 43145 | Q41: 43145 | R41: 1 | S41: Point-Source | T41: 0 | U41: 0 | V41: 1.8 | W41: kg/h | X41: Provided in-paper - Confidence Interval | Y41: 0 | Z41: 1
... A116: 52f20189-5ced-4223-af8d-4f19e6957173 | B116: 4dfd7bc2-f164-49f2-b007-de0b30dc60b6 | C116: 6fcc0d8d-bb28-4548-9495-e31cb3fa2e99 | D116: 70f2024b-e279-4d03-9ca1-d8c1be5c09b0 | E116: Energy | F116: Fugitive Emissions from Fuels | G116: Fugitive Emissions from Oil Production | H116: Upstream oil and gas | I116: Shipboard measurement campaign of offshore oil and gas production | J116: Fixed Leg Platform | K116: Site | L116: Gulf of Mexico Offshore Platform 103 | M116: Second or sub-second | N116: 1 s TILDAS measurements | O116: Lat/Lon: 29.00029, -94.76462 | Structure: A | Field: GA255 | Lease: G30195 | Complex ID: 10050 | Water depth (ft): 61.0 | Valid plumes counted: 2 | 95% CI present | P116: 43152 | Q116: 43152 | R116: 2 | S116: Point-Source | T116: 0 | U116: 0 | V116: 1.8 | W116: kg/h | X116: Provided in-paper - Confidence Interval | Y116: 0 | Z116: 1
A117: 7293589e-6a88-44c8-a2f4-b769f5c60199 | B117: 55d6e423-92c7-4774-a664-3132cd2c03ae | C117: a317553a-aa01-43b9-96f4-9419b52fc09e | D117: 70f2024b-e279-4d03-9ca1-d8c1be5c09b0 | E117: Energy | F117: Fugitive Emissions from Fuels | G117: Fugitive Emissions from Oil Production | H117: Upstream oil and gas | I117: Offshore oil and gas production | J117: Plumes from offshore platforms under normal operating conditions | K117: Regional | L117: Gulf of Mexico | M117: Second or sub-second | N117: Continuous in situ measurement of methane made at a frequency of 0.33 to 0.5 Hz with a total uncertainty of 1.4 ppb. | O117: Facility weighted mean (median) emission rate for the 10 sites, excluding the drill ship | P117: 43117 | Q117: 43124 | R117: 10 | S117: Average | T117: 373 | U117: 310 | V117: 436 | W117: kg/h | X117: Provided in-paper - Confidence Interval | Y117: 1 | Z117: 1 | AE117: {=_xlfn.torow(_xlfn.unique(_xlfn._xlws.filter(cat_table[Subsector],$E117=cat_table[Sector],"")))} -> #NAME? | AF117: #NAME? | AG117: #NAME? | AH117: #NAME? | AI117: #NAME? | AJ117: #NAME? | AK117: #NAME? | AO117: {=_xlfn.torow(_xlfn.unique(_xlfn._xlws.filter(cat_table[Sub-subsector],($E117=cat_table[Sector])*($F117=cat_table[Subsector]),"")))} -> #NAME? | AP117: #NAME? | AQ117: #NAME? | AR117: #NAME? | AS117: #NAME? | AT117: #NAME?
A118: ca417887-d63e-47d0-9e43-06ff2882945d | B118: 55d6e423-92c7-4774-a664-3132cd2c03ae | C118: a317553a-aa01-43b9-96f4-9419b52fc09e | D118: 70f2024b-e279-4d03-9ca1-d8c1be5c09b0 | E118: Energy | F118: Fugitive Emissions from Fuels | G118: Fugitive Emissions from Oil Production | H118: Upstream oil and gas | I118: Offshore oil and gas production | J118: Large Shallow Central Hub - AS1 | K118: Site | L118: Gulf of Mexico | M118: Second or sub-second | N118: Continuous in situ measurement of methane made at a frequency of 0.33 to 0.5 Hz with a total uncertainty of 1.4 ppb. | O118: Site name: AS1 | P118: 43117 | Q118: 43117 | R118: 1 | S118: Point-Source | T118: 1400 | U118: 900 | V118: 1900 | W118: kg/h | X118: Provided in-paper - Confidence Interval | Z118: 0 | AE118: {=_xlfn.torow(_xlfn.unique(_xlfn._xlws.filter(cat_table[Subsector],$E118=cat_table[Sector],"")))} -> #NAME? | AF118: #NAME? | AG118: #NAME? | AH118: #NAME? | AI118: #NAME? | AJ118: #NAME? | AK118: #NAME? | AO118: {=_xlfn.torow(_xlfn.unique(_xlfn._xlws.filter(cat_table[Sub-subsector],($E118=cat_table[Sector])*($F118=cat_table[Subsector]),"")))} -> #NAME? | AP118: #NAME? | AQ118: #NAME? | AR118: #NAME? | AS118: #NAME? | AT118: #NAME?
A119: 8358fca0-8bb9-48b1-a1b7-b5eaa49ce31e | B119: 55d6e423-92c7-4774-a664-3132cd2c03ae | C119: a317553a-aa01-43b9-96f4-9419b52fc09e | D119: 70f2024b-e279-4d03-9ca1-d8c1be5c09b0 | E119: Energy | F119: Fugitive Emissions from Fuels | G119: Fugitive Emissions from Oil Production | H119: Upstream oil and gas | I119: Offshore oil and gas production | J119: Large Shallow Central Hub - AS1 | K119: Site | L119: Gulf of Mexico | M119: Second or sub-second | N119: Continuous in situ measurement of methane made at a frequency of 0.33 to 0.5 Hz with a total uncertainty of 1.4 ppb. | O119: Site name: AS1 | P119: 43118 | Q119: 43118 | R119: 1 | S119: Point-Source | T119: 520 | U119: 390 | V119: 650 | W119: kg/h | X119: Provided in-paper - Confidence Interval | Z119: 0 | AE119: {=_xlfn.torow(_xlfn.unique(_xlfn._xlws.filter(cat_table[Subsector],$E119=cat_table[Sector],"")))} -> #NAME? | AF119: #NAME? | AG119: #NAME? | AH119: #NAME? | AI119: #NAME? | AJ119: #NAME? | AK119: #NAME? | AO119: {=_xlfn.torow(_xlfn.unique(_xlfn._xlws.filter(cat_table[Sub-subsector],($E119=cat_table[Sector])*($F119=cat_table[Subsector]),"")))} -> #NAME? | AP119: #NAME? | AQ119: #NAME? | AR119: #NAME? | AS119: #NAME? | AT119: #NAME?
A120: c3e302b8-f3cb-4703-b431-3c15f71fde68 | B120: 55d6e423-92c7-4774-a664-3132cd2c03ae | C120: a317553a-aa01-43b9-96f4-9419b52fc09e | D120: 70f2024b-e279-4d03-9ca1-d8c1be5c09b0 | E120: Energy | F120: Fugitive Emissions from Fuels | G120: Fugitive Emissions from Oil Production | H120: Upstream oil and gas | I120: Offshore oil and gas production | J120: Large Shallow Central Hub - AS4 | K120: Site | L120: Gulf of Mexico | M120: Second or sub-second | N120: Continuous in situ measurement of methane made at a frequency of 0.33 to 0.5 Hz with a total uncertainty of 1.4 ppb. | O120: Site name: AS4 | P120: 43117 | Q120: 43117 | R120: 1 | S120: Point-Source | T120: 3800 | U120: 1600 | V120: 6000 | W120: kg/h | X120: Provided in-paper - Confidence Interval | Z120: 0 | AE120: {=_xlfn.torow(_xlfn.unique(_xlfn._xlws.filter(cat_table[Subsector],$E120=cat_table[Sector],"")))} -> #NAME? | AF120: #NAME? | AG120: #NAME? | AH120: #NAME? | AI120: #NAME? | AJ120: #NAME? | AK120: #NAME? | AO120: {=_xlfn.torow(_xlfn.unique(_xlfn._xlws.filter(cat_table[Sub-subsector],($E120=cat_table[Sector])*($F120=cat_table[Subsector]),"")))} -> #NAME? | AP120: #NAME? | AQ120: #NAME? | AR120: #NAME? | AS120: #NAME? | AT120: #NAME?
A121: 0731a425-13f3-4c00-9347-d71378ed57a0 | B121: 55d6e423-92c7-4774-a664-3132cd2c03ae | C121: a317553a-aa01-43b9-96f4-9419b52fc09e | D121: 70f2024b-e279-4d03-9ca1-d8c1be5c09b0 | E121: Energy | F121: Fugitive Emissions from Fuels | G121: Fugitive Emissions from Oil Production | H121: Upstream oil and gas | I121: Offshore oil and gas production | J121: Large Shallow Central Hub - AS4 | K121: Site | L121: Gulf of Mexico | M121: Second or sub-second | N121: Continuous in situ measurement of methane made at a frequency of 0.33 to 0.5 Hz with a total uncertainty of 1.4 ppb. | O121: Site name: AS4 | P121: 43118 | Q121: 43118 | R121: 1 | S121: Point-Source | T121: 1000 | U121: -500 | V121: 2500 | W121: kg/h | X121: Provided in-paper - Confidence Interval | Z121: 0 | AE121: {=_xlfn.torow(_xlfn.unique(_xlfn._xlws.filter(cat_table[Subsector],$E121=cat_table[Sector],"")))} -> #NAME? | AF121: #NAME? | AG121: #NAME? | AH121: #NAME? | AI121: #NAME? | AJ121: #NAME? | AK121: #NAME? | AO121: {=_xlfn.torow(_xlfn.unique(_xlfn._xlws.filter(cat_table[Sub-subsector],($E121=cat_table[Sector])*($F121=cat_table[Subsector]),"")))} -> #NAME? | AP121: #NAME? | AQ121: #NAME? | AR121: #NAME? | AS121: #NAME? | AT121: #NAME?
A122: df5ab2bc-5548-4d4d-88b2-26d901a8bc33 | B122: 55d6e423-92c7-4774-a664-3132cd2c03ae | C122: a317553a-aa01-43b9-96f4-9419b52fc09e | D122: 70f2024b-e279-4d03-9ca1-d8c1be5c09b0 | E122: Energy | F122: Fugitive Emissions from Fuels | G122: Fugitive Emissions from Oil Production | H122: Upstream oil and gas | I122: Offshore oil and gas production | J122: Large Shallow Central Hub - AS4 | K122: Site | L122: Gulf of Mexico | M122: Second or sub-second | N122: Continuous in situ measurement of methane made at a frequency of 0.33 to 0.5 Hz with a total uncertainty of 1.4 ppb. | O122: Site name: AS4 | P122: 43118 | Q122: 43118 | R122: 1 | S122: Point-Source | T122: 66 | U122: 53 | V122: 79 | W122: kg/h | X122: Provided in-paper - Confidence Interval | Z122: 0 | AE122: {=_xlfn.torow(_xlfn.unique(_xlfn._xlws.filter(cat_table[Subsector],$E122=cat_table[Sector],"")))} -> #NAME? | AF122: #NAME? | AG122: #NAME? | AH122: #NAME? | AI122: #NAME? | AJ122: #NAME? | AK122: #NAME? | AO122: {=_xlfn.torow(_xlfn.unique(_xlfn._xlws.filter(cat_table[Sub-subsector],($E122=cat_table[Sector])*($F122=cat_table[Subsector]),"")))} -> #NAME? | AP122: #NAME? | AQ122: #NAME? | AR122: #NAME? | AS122: #NAME? | AT122: #NAME?
A123: 58a27a53-455f-495e-a066-ea4a356e800 | B123: 55d6e423-92c7-4774-a664-3132cd2c03ae | C123: a317553a-aa01-43b9-96f4-9419b52fc09e | D123: 70f2024b-e279-4d03-9ca1-d8c1be5c09b0 | E123: Energy | F123: Fugitive Emissions from Fuels | G123: Fugitive Emissions from Oil Production | H123: Upstream oil and gas | I123: Offshore oil and gas production | J123: Fixed Leg - BS6 | K123: Site | L123: Gulf of Mexico | M123: Second or sub-second | N123: Continuous in situ measurement of methane made at a frequency of 0.33 to 0.5 Hz with a total uncertainty of 1.4 ppb. | O123: Site name: BS6 | P123: 43119 | Q123: 43122 | R123: 1 | S123: Point-Source | T123: 31 | U123: 19 | V123: 43 | W123: kg/h | X123: Provided in-paper - Confidence Interval | Z123: 0 | AE123: {=_xlfn.torow(_xlfn.unique(_xlfn._xlws.filter(cat_table[Subsector],$E123=cat_table[Sector],"")))} -> #NAME? | AF123: #NAME? | AG123: #NAME? | AH123: #NAME? | AI123: #NAME? | AJ123: #NAME? | AK123: #NAME? | AO123: {=_xlfn.torow(_xlfn.unique(_xlfn._xlws.filter(cat_table[Sub-subsector],($E123=cat_table[Sector])*($F123=cat_table[Subsector]),"")))} -> #NAME? | AP123: #NAME? | AQ123: #NAME? | AR123: #NAME? | AS123: #NAME? | AT123: #NAME?
A124: 57564624-c00e-490a-83bc-51369729f03a | B124: 55d6e423-92c7-4774-a664-3132cd2c03ae | C124: a317553a-aa01-43b9-96f4-9419b52fc09e | D124: 70f2024b-e279-4d03-9ca1-d8c1be5c09b0 | E124: Energy | F124: Fugitive Emissions from Fuels | G124: Fugitive Emissions from Oil Production | H124: Upstream oil and gas | I124: Offshore oil and gas production | J124: Fixed Leg - BS7 | K124: Site | L124: Gulf of Mexico | M124: Second or sub-second | N124: Continuous in situ measurement of methane made at a frequency of 0.33 to 0.5 Hz with a total uncertainty of 1.4 ppb. | O124: Site name: BS7 | P124: 43119 | Q124: 43122 | R124: 1 | S124: Point-Source | T124: 86 | U124: 58 | V124: 114 | W124: kg/h | X124: Provided in-paper - Confidence Interval | Z124: 0 | AE124: {=_xlfn.torow(_xlfn.unique(_xlfn._xlws.filter(cat_table[Subsector],$E124=cat_table[Sector],"")))} -> #NAME? | AF124: #NAME? | AG124: #NAME? | AH124: #NAME? | AI124: #NAME? | AJ124: #NAME? | AK124: #NAME? | AO124: {=_xlfn.torow(_xlfn.unique(_xlfn._xlws.filter(cat_table[Sub-subsector],($E124=cat_table[Sector])*($F124=cat_table[Subsector]),"")))} -> #NAME? | AP124: #NAME? | AQ124: #NAME? | AR124: #NAME? | AS124: #NAME? | AT124: #NAME?
A125: 8b3d200a-dab3-4ca8-a8bd-1f75297028b8 | B125: 55d6e423-92c7-4774-a664-3132cd2c03ae | C125: a317553a-aa01-43b9-96f4-9419b52fc09e | D125: 70f2024b-e279-4d03-9ca1-d8c1be5c09b0 | E125: Energy | F125: Fugitive Emissions from Fuels | G125: Fugitive Emissions from Oil Production | H125: Upstream oil and gas | I125: Offshore oil and gas production | J125: Tension Leg Platform - CS8 | K125: Site | L125: Gulf of Mexico | M125: Second or sub-second | N125: Continuous in situ measurement of methane made at a frequency of 0.33 to 0.5 Hz with a total uncertainty of 1.4 ppb. | O125: Site name: CS8 | P125: 43123 | Q125: 43124 | R125: 1 | S125: Point-Source | T125: 92 | U125: 56 | V125: 128 | W125: kg/h | X125: Provided in-paper - Confidence Interval | Z125: 0 | AE125: {=_xlfn.torow(_xlfn.unique(_xlfn._xlws.filter(cat_table[Subsector],$E125=cat_table[Sector],"")))} -> #NAME? | AF125: #NAME? | AG125: #NAME? | AH125: #NAME? | AI125: #NAME? | AJ125: #NAME? | AK125: #NAME? | AO125: {=_xlfn.torow(_xlfn.unique(_xlfn._xlws.filter(cat_table[Sub-subsector],($E125=cat_table[Sector])*($F125=cat_table[Subsector]),"")))} -> #NAME? | AP125: #NAME? | AQ125: #NAME? | AR125: #NAME? | AS125: #NAME? | AT125: #NAME?
A126: 462276a2-ea07-4de5-a9bb-c0fc2f0d67f9 | B126: 55d6e423-92c7-4774-a664-3132cd2c03ae | C126: a317553a-aa01-43b9-96f4-9419b52fc09e | D126: 70f2024b-e279-4d03-9ca1-d8c1be5c09b0 | E126: Energy | F126: Fugitive Emissions from Fuels | G126: Fugitive Emissions from Oil Production | H126: Upstream oil and gas | I126: Offshore oil and gas production | J126: SPAR Floating Production System - CS9 | K126: Site | L126: Gulf of Mexico | M126: Second or sub-second | N126: Continuous in situ measurement of methane made at a frequency of 0.33 to 0.5 Hz with a total uncertainty of 1.4 ppb. | O126: Site name: CS9 | P126: 43123 | Q126: 43124 | R126: 1 | S126: Point-Source | T126: 96 | U126: 62 | V126: 130 | W126: kg/h | X126: Provided in-paper - Confidence Interval | Z126: 0 | AE126: {=_xlfn.torow(_xlfn.unique(_xlfn._xlws.filter(cat_table[Subsector],$E126=cat_table[Sector],"")))} -> #NAME? | AF126: #NAME? | AG126: #NAME? | AH126: #NAME? | AI126: #NAME? | AJ126: #NAME? | AK126: #NAME? | AO126: {=_xlfn.torow(_xlfn.unique(_xlfn._xlws.filter(cat_table[Sub-subsector],($E126=cat_table[Sector])*($F126=cat_table[Subsector]),"")))} -> #NAME? | AP126: #NAME? | AQ126: #NAME? | AR126: #NAME? | AS126: #NAME? | AT126: #NAME?
A127: cfe40312-f17e-4ad6-8dc8-8563c8537be1 | B127: 55d6e423-92c7-4774-a664-3132cd2c03ae | C127: a317553a-aa01-43b9-96f4-9419b52fc09e | D127: 70f2024b-e279-4d03-9ca1-d8c1be5c09b0 | E127: Energy | F127: Fugitive Emissions from Fuels | G127: Fugitive Emissions from Oil Production | H127: Upstream oil and gas | I127: Offshore oil and gas production | J127: Drill Ship - CS10 | K127: Site | L127: Gulf of Mexico | M127: Second or sub-second | N127: Continuous in situ measurement of methane made at a frequency of 0.33 to 0.5 Hz with a total uncertainty of 1.4 ppb. | O127: Site name: CS10 | P127: 43123 | Q127: 43124 | R127: 1 | S127: Point-Source | T127: 59 | U127: 20 | V127: 98 | W127: kg/h | X127: Provided in-paper - Confidence Interval | Z127: 0 | AE127: {=_xlfn.torow(_xlfn.unique(_xlfn._xlws.filter(cat_table[Subsector],$E127=cat_table[Sector],"")))} -> #NAME? | AF127: #NAME? | AG127: #NAME? | AH127: #NAME? | AI127: #NAME? | AJ127: #NAME? | AK127: #NAME? | AO127: {=_xlfn.torow(_xlfn.unique(_xlfn._xlws.filter(cat_table[Sub-subsector],($E127=cat_table[Sector])*($F127=cat_table[Subsector]),"")))} -> #NAME? | AP127: #NAME? | AQ127: #NAME? | AR127: #NAME? | AS127: #NAME? | AT127: #NAME?
A128: 88987b0c-809a-456d-93d8-0c1bef33efe5 | B128: 55d6e423-92c7-4774-a664-3132cd2c03ae | C128: a317553a-aa01-43b9-96f4-9419b52fc09e | D128: 70f2024b-e279-4d03-9ca1-d8c1be5c09b0 | E128: Energy | F128: Fugitive Emissions from Fuels | G128: Fugitive Emissions from Oil Production | H128: Upstream oil and gas | I128: Offshore oil and gas production | J128: Tension Leg Platform - CS11 | K128: Site | L128: Gulf of Mexico | M128: Second or sub-second | N128: Continuous in situ measurement of methane made at a frequency of 0.33 to 0.5 Hz with a total uncertainty of 1.4 ppb. | O128: Site name: CS11 | P128: 43123 | Q128: 43124 | R128: 1 | S128: Point-Source | T128: 40 | U128: 26 | V128: 54 | W128: kg/h | X128: Provided in-paper - Confidence Interval | Z128: 0 | AE128: {=_xlfn.torow(_xlfn.unique(_xlfn._xlws.filter(cat_table[Subsector],$E128=cat_table[Sector],"")))} -> #NAME? | AF128: #NAME? | AG128: #NAME? | AH128: #NAME? | AI128: #NAME? | AJ128: #NAME? | AK128: #NAME? | AO128: {=_xlfn.torow(_xlfn.unique(_xlfn._xlws.filter(cat_table[Sub-subsector],($E128=cat_table[Sector])*($F128=cat_table[Subsector]),"")))} -> #NAME? | AP128: #NAME? | AQ128: #NAME? | AR128: #NAME? | AS128: #NAME? | AT128: #NAME?
A129: a36fdf5a-e763-41bd-89c2-8ffb3a32fb1d | B129: 55d6e423-92c7-4774-a664-3132cd2c03ae | C129: a317553a-aa01-43b9-96f4-9419b52fc09e | D129: 70f2024b-e279-4d03-9ca1-d8c1be5c09b0 | E129: Energy | F129: Fugitive Emissions from Fuels | G129: Fugitive Emissions from Oil Production | H129: Upstream oil and gas | I129: Offshore oil and gas production | J129: SPAR Floating Production System - CS12 | K129: Site | L129: Gulf of Mexico | M129: Second or sub-second | N129: Continuous in situ measurement of methane made at a frequency of 0.33 to 0.5 Hz with a total uncertainty of 1.4 ppb. | O129: Site name: CS12 | P129: 43123 | Q129: 43124 | R129: 1 | S129: Point-Source | T129: 23 | U129: 8 | V129: 38 | W129: kg/h | X129: Provided in-paper - Confidence Interval | Z129: 0 | AE129: {=_xlfn.torow(_xlfn.unique(_xlfn._xlws.filter(cat_table[Subsector],$E129=cat_table[Sector],"")))} -> #NAME? | AF129: #NAME? | AG129: #NAME? | AH129: #NAME? | AI129: #NAME? | AJ129: #NAME? | AK129: #NAME? | AO129: {=_xlfn.torow(_xlfn.unique(_xlfn._xlws.filter(cat_table[Sub-subsector],($E129=cat_table[Sector])*($F129=cat_table[Subsector]),"")))} -> #NAME? | AP129: #NAME? | AQ129: #NAME? | AR129: #NAME? | AS129: #NAME? | AT129: #NAME?
A130: 0caee4b8-f93d-42e7-96c8-a1dc431c900a | B130: 55d6e423-92c7-4774-a664-3132cd2c03ae | C130: a317553a-aa01-43b9-96f4-9419b52fc09e | D130: 70f2024b-e279-4d03-9ca1-d8c1be5c09b0 | E130: Energy | F130: Fugitive Emissions from Fuels | G130: Fugitive Emissions from Oil Production | H130: Upstream oil and gas | I130: Offshore oil and gas production | J130: Drill Ship - CS13 | K130: Site | L130: Gulf of Mexico | M130: Second or sub-second | N130: Continuous in situ measurement of methane made at a frequency of 0.33 to 0.5 Hz with a total uncertainty of 1.4 ppb. | O130: Site name: CS13 | P130: 43123 | Q130: 43124 | R130: 1 | S130: Point-Source | T130: -27 | U130: -46 | V130: -8 | W130: kg/h | X130: Provided in-paper - Confidence Interval | Z130: 0 | AE130: {=_xlfn.torow(_xlfn.unique(_xlfn._xlws.filter(cat_table[Subsector],$E130=cat_table[Sector],"")))} -> #NAME? | AF130: #NAME? | AG130: #NAME? | AH130: #NAME? | AI130: #NAME? | AJ130: #NAME? | AK130: #NAME? | AO130: {=_xlfn.torow(_xlfn.unique(_xlfn._xlws.filter(cat_table[Sub-subsector],($E130=cat_table[Sector])*($F130=cat_table[Subsector]),"")))} -> #NAME? | AP130: #NAME? | AQ130: #NAME? | AR130: #NAME? | AS130: #NAME? | AT130: #NAME?
A131: 2cc62365-a986-4b04-8d32-b756ec00eb7c | B131: 90de6911-8cdb-4bbc-b326-0d606644ee29 | C131: 8784d7de-88ad-414a-aa4f-d8d137381d2a | D131: 9efced68-1348-4e0d-a01b-de82fc334aed | E131: Energy | F131: Fugitive Emissions from Fuels | G131: Fugitive Emissions from Oil Production | H131: Upstream oil and gas | I131: Onshore and offshore oil and gas production regions | J131: regional flux estimation is based on the mass balance approach | K131: Regional | L131: offshore | M131: Second or sub-second | N131: frequency of 0.33–0.50 Hz | O131: Central estimate for the offshore study region | P131: 43135 | Q131: 43149 | R131: regional sampling | S131: Area-Based | T131: 2800 | U131: 1700 | V131: 3900 | W131: kg h-1 | X131: Provided in-paper - Confidence Interval | Z131: 1 | AE131: {=_xlfn.torow(_xlfn.unique(_xlfn._xlws.filter(cat_table[Subsector],$E131=cat_table[Sector],"")))} -> #NAME? | AF131: #NAME? | AG131: #NAME? | AH131: #NAME? | AI131: #NAME? | AJ131: #NAME? | AK131: #NAME? | AO131: {=_xlfn.torow(_xlfn.unique(_xlfn._xlws.filter(cat_table[Sub-subsector],($E131=cat_table[Sector])*($F131=cat_table[Subsector]),"")))} -> #NAME? | AP131: #NAME? | AQ131: #NAME? | AR131: #NAME? | AS131: #NAME? | AT131: #NAME?
A132: 389f7afe-029a-4d0e-acc6-9d29f1d000c0 | B132: 90de6911-8cdb-4bbc-b326-0d606644ee29 | C132: 8784d7de-88ad-414a-aa4f-d8d137381d2a | D132: 9efced68-1348-4e0d-a01b-de82fc334aed | E132: Energy | F132: Fugitive Emissions from Fuels | G132: Fugitive Emissions from Oil Production | H132: Upstream oil and gas | I132: Onshore and offshore oil and gas production regions | J132: aircraft-based top-down measurements at the regional and facility-levels | K132: Site | L132: onshore | M132: Second or sub-second | N132: frequency of 0.33–0.50 Hz | O132: Atasta facility | P132: 43141 | Q132: 43141 | R132: 1 | S132: Point-Source | T132: 370 | U132: 220 | V132: 520 | W132: kg h-1 | X132: Provided in-paper - Confidence Interval | Z132: 0 | AE132: {=_xlfn.torow(_xlfn.unique(_xlfn._xlws.filter(cat_table[Subsector],$E132=cat_table[Sector],"")))} -> #NAME? | AF132: #NAME? | AG132: #NAME? | AH132: #NAME? | AI132: #NAME? | AJ132: #NAME? | AK132: #NAME? | AO132: {=_xlfn.torow(_xlfn.unique(_xlfn._xlws.filter(cat_table[Sub-subsector],($E132=cat_table[Sector])*($F132=cat_table[Subsector]),"")))} -> #NAME? | AP132: #NAME? | AQ132: #NAME? | AR132: #NAME? | AS132: #NAME? | AT132: #NAME?
A133: 076cbb70-b697-4c97-9462-753d19f15f92 | B133: 90de6911-8cdb-4bbc-b326-0d606644ee29 | C133: 8784d7de-88ad-414a-aa4f-d8d137381d2a | D133: 9efced68-1348-4e0d-a01b-de82fc334aed | E133: Energy | F133: Fugitive Emissions from Fuels | G133: Fugitive Emissions from Oil Production | H133: Upstream oil and gas | I133: Onshore and offshore oil and gas production regions | J133: aircraft-based top-down measurements at the regional and facility-levels | K133: Site | L133: onshore | M133: Second or sub-second | N133: frequency of 0.33–0.50 Hz | O133: Nuevo Pemex facility | P133: 43145 | Q133: 43146 | R133: 1 | S133: Point-Source | T133: 1600 | U133: 820 | V133: 2380 | W133: kg h-1 | X133: Provided in-paper - Confidence Interval | Z133: 0 | AE133: {=_xlfn.torow(_xlfn.unique(_xlfn._xlws.filter(cat_table[Subsector],$E133=cat_table[Sector],"")))} -> #NAME? | AF133: #NAME? | AG133: #NAME? | AH133: #NAME? | AI133: #NAME? | AJ133: #NAME? | AK133: #NAME? | AO133: {=_xlfn.torow(_xlfn.unique(_xlfn._xlws.filter(cat_table[Sub-subsector],($E133=cat_table[Sector])*($F133=cat_table[Subsector]),"")))} -> #NAME? | AP133: #NAME? | AQ133: #NAME? | AR133: #NAME? | AS133: #NAME? | AT133: #NAME?
A134: 38cb4cbb-6562-4ed3-82ff-0e360e1c9956 | B134: 90de6911-8cdb-4bbc-b326-0d606644ee29 | C134: 8784d7de-88ad-414a-aa4f-d8d137381d2a | D134: 9efced68-1348-4e0d-a01b-de82fc334aed | E134: Energy | F134: Fugitive Emissions from Fuels | G134: Fugitive Emissions from Oil Production | H134: Upstream oil and gas | I134: Onshore and offshore oil and gas production regions | J134: aircraft-based top-down measurements at the regional and facility-levels | K134: Regional | L134: onshore | M134: Second or sub-second | N134: frequency of 1-10 Hz | O134: Airborne-based emission estimates for the onshore study region | P134: 43141 | Q134: 43146 | R134: regional sampling | S134: Area-Based | T134: 37000 | U134: 27000 | V134: 47000 | W134: kg h-1 | X134: Provided in-paper - Confidence Interval | Z134: 1 | AE134: {=_xlfn.torow(_xlfn.unique(_xlfn._xlws.filter(cat_table[Subsector],$E134=cat_table[Sector],"")))} -> #NAME? | AF134: #NAME? | AG134: #NAME? | AH134: #NAME? | AI134: #NAME? | AJ134: #NAME? | AK134: #NAME? | AO134: {=_xlfn.torow(_xlfn.unique(_xlfn._xlws.filter(cat_table[Sub-subsector],($E134=cat_table[Sector])*($F134=cat_table[Subsector]),"")))} -> #NAME? | AP134: #NAME? | AQ134: #NAME? | AR134: #NAME? | AS134: #NAME? | AT134: #NAME?
A135: c33a4276-541d-4d30-b284-11ee449cfd2b | B135: d45dc248-31bc-48c1-8d6c-4cb479faf1b4 | C135: 1711685d-9f0e-4c8a-8a5e-b120c02d52b7 | D135: 36067f76-d150-4489-b59c-e7d016ba0c76 | E135: Energy | F135: Fugitive Emissions from Fuels | G135: Fugitive Emissions from Oil Production | I135: methane emissions from offshore gas facilities | J135: Offshore gas facilities | K135: Site | L135: offshore | M135: Second or sub-second | N135: 10 Hz | O135: P1 Complex | P135: 43585 | Q135: 43585 | R135: 1 | S135: Point-Source | T135: 86.5 | U135: 45.3 | V135: 127.7 | W135: kg h-1 | Z135: 0 | AE135: {=_xlfn.torow(_xlfn.unique(_xlfn._xlws.filter(cat_table[Subsector],$E135=cat_table[Sector],"")))} -> #NAME? | AF135: #NAME? | AG135: #NAME? | AH135: #NAME? | AI135: #NAME? | AJ135: #NAME? | AK135: #NAME? | AO135: {=_xlfn.torow(_xlfn.unique(_xlfn._xlws.filter(cat_table[Sub-subsector],($E135=cat_table[Sector])*($F135=cat_table[Subsector]),"")))} -> #NAME? | AP135: #NAME? | AQ135: #NAME? | AR135: #NAME? | AS135: #NAME? | AT135: #NAME?
A136: e97c7c94-8875-497c-9c48-546cff856e88 | B136: d45dc248-31bc-48c1-8d6c-4cb479faf1b4 | C136: 1711685d-9f0e-4c8a-8a5e-b120c02d52b7 | D136: 36067f76-d150-4489-b59c-e7d016ba0c76 | E136: Energy | F136: Fugitive Emissions from Fuels | G136: Fugitive Emissions from Oil Production | I136: methane emissions from offshore gas facilities | J136: Offshore gas facilities | K136: Site | L136: offshore | M136: Second or sub-second | N136: 10 Hz | O136: P2 Complex | P136: 43585 | Q136: 43585 | R136: 1 | S136: Point-Source | T136: 24.2 | U136: 7.2 | V136: 41.2 | W136: kg h-1 | Z136: 0 | AE136: {=_xlfn.torow(_xlfn.unique(_xlfn._xlws.filter(cat_table[Subsector],$E136=cat_table[Sector],"")))} -> #NAME? | AF136: #NAME? | AG136: #NAME? | AH136: #NAME? | AI136: #NAME? | AJ136: #NAME? | AK136: #NAME? | AO136: {=_xlfn.torow(_xlfn.unique(_xlfn._xlws.filter(cat_table[Sub-subsector],($E136=cat_table[Sector])*($F136=cat_table[Subsector]),"")))} -> #NAME? | AP136: #NAME? | AQ136: #NAME? | AR136: #NAME? | AS136: #NAME? | AT136: #NAME?
A137: 028aef40-a25b-4b1a-bf03-ef7eff3e4410 | B137: d45dc248-31bc-48c1-8d6c-4cb479faf1b4 | C137: 1711685d-9f0e-4c8a-8a5e-b120c02d52b7 | D137: 36067f76-d150-4489-b59c-e7d016ba0c76 | E137: Energy | F137: Fugitive Emissions from Fuels | G137: Fugitive Emissions from Oil Production | I137: methane emissions from offshore gas facilities | J137: Offshore gas facilities | K137: Site | L137: offshore | M137: Second or sub-second | N137: 10 Hz | O137: P4 | P137: 43587 | Q137: 43587 | R137: 1 | S137: Point-Source | T137: 1258.7 | U137: 748.6 | V137: 1768.8 | W137: kg h-1 | Z137: 0 | AE137: {=_xlfn.torow(_xlfn.unique(_xlfn._xlws.filter(cat_table[Subsector],$E137=cat_table[Sector],"")))} -> #NAME? | AF137: #NAME? | AG137: #NAME? | AH137: #NAME? | AI137: #NAME? | AJ137: #NAME? | AK137: #NAME? | AO137: {=_xlfn.torow(_xlfn.unique(_xlfn._xlws.filter(cat_table[Sub-subsector],($E137=cat_table[Sector])*($F137=cat_table[Subsector]),"")))} -> #NAME? | AP137: #NAME? | AQ137: #NAME? | AR137: #NAME? | AS137: #NAME? | AT137: #NAME?
A138: 771c7766-4520-44da-89c0-3b0731726fbd | B138: d45dc248-31bc-48c1-8d6c-4cb479faf1b4 | C138: 1711685d-9f0e-4c8a-8a5e-b120c02d52b7 | D138: 36067f76-d150-4489-b59c-e7d016ba0c76 | E138: Energy | F138: Fugitive Emissions from Fuels | G138: Fugitive Emissions from Oil Production | I138: methane emissions from offshore gas facilities | J138: Offshore gas facilities | K138: Site | L138: offshore | M138: Second or sub-second | N138: 10 Hz | O138: P7 | P138: 43591 | Q138: 43591 | R138: 1 | S138: Point-Source | T138: 43.6 | U138: 28.2 | V138: 59 | W138: kg h-1 | Z138: 0 | AE138: {=_xlfn.torow(_xlfn.unique(_xlfn._xlws.filter(cat_table[Subsector],$E138=cat_table[Sector],"")))} -> #NAME? | AF138: #NAME? | AG138: #NAME? | AH138: #NAME? | AI138: #NAME? | AJ138: #NAME? | AK138: #NAME? | AO138: {=_xlfn.torow(_xlfn.unique(_xlfn._xlws.filter(cat_table[Sub-subsector],($E138=cat_table[Sector])*($F138=cat_table[Subsector]),"")))} -> #NAME? | AP138: #NAME? | AQ138: #NAME? | AR138: #NAME? | AS138: #NAME? | AT138: #NAME?
A139: b8cde5a2-a22c-40e7-a004-2a894a9701da | B139: d45dc248-31bc-48c1-8d6c-4cb479faf1b4 | C139: 1711685d-9f0e-4c8a-8a5e-b120c02d52b7 | D139: 36067f76-d150-4489-b59c-e7d016ba0c76 | E139: Energy | F139: Fugitive Emissions from Fuels | G139: Fugitive Emissions from Oil Production | I139: methane emissions from offshore gas facilities | J139: Offshore gas facilities | K139: Site | L139: offshore | M139: Second or sub-second | N139: 10 Hz | O139: P8 | P139: 43591 | Q139: 43591 | R139: 1 | S139: Point-Source | T139: 35.1 | U139: 25.5 | V139: 44.7 | W139: kg h-1 | Z139: 0 | AE139: {=_xlfn.torow(_xlfn.unique(_xlfn._xlws.filter(cat_table[Subsector],$E139=cat_table[Sector],"")))} -> #NAME? | AF139: #NAME? | AG139: #NAME? | AH139: #NAME? | AI139: #NAME? | AJ139: #NAME? | AK139: #NAME? | AO139: {=_xlfn.torow(_xlfn.unique(_xlfn._xlws.filter(cat_table[Sub-subsector],($E139=cat_table[Sector])*($F139=cat_table[Subsector]),"")))} -> #NAME? | AP139: #NAME? | AQ139: #NAME? | AR139: #NAME? | AS139: #NAME? | AT139: #NAME?
A140: d635ebbc-0ad9-4b1f-96db-51503f08a53d | B140: d45dc248-31bc-48c1-8d6c-4cb479faf1b4 | C140: 1711685d-9f0e-4c8a-8a5e-b120c02d52b7 | D140: 36067f76-d150-4489-b59c-e7d016ba0c76 | E140: Energy | F140: Fugitive Emissions from Fuels | G140: Fugitive Emissions from Oil Production | I140: methane emissions from offshore gas facilities | J140: Offshore gas facilities | K140: Site | L140: offshore | M140: Second or sub-second | N140: 10 Hz | O140: P10 | P140: 43591 | Q140: 43591 | R140: 1 | S140: Point-Source | T140: 32.1 | U140: 23.1 | V140: 41.1 | W140: kg h-1 | Z140: 0 | AE140: {=_xlfn.torow(_xlfn.unique(_xlfn._xlws.filter(cat_table[Subsector],$E140=cat_table[Sector],"")))} -> #NAME? | AF140: #NAME? | AG140: #NAME? | AH140: #NAME? | AI140: #NAME? | AJ140: #NAME? | AK140: #NAME? | AO140: {=_xlfn.torow(_xlfn.unique(_xlfn._xlws.filter(cat_table[Sub-subsector],($E140=cat_table[Sector])*($F140=cat_table[Subsector]),"")))} -> #NAME? | AP140: #NAME? | AQ140: #NAME? | AR140: #NAME? | AS140: #NAME? | AT140: #NAME?
A141: 3d1ca665-324d-417e-9e31-a5f928a4910e | B141: d45dc248-31bc-48c1-8d6c-4cb479faf1b4 | C141: 1711685d-9f0e-4c8a-8a5e-b120c02d52b7 | D141: 36067f76-d150-4489-b59c-e7d016ba0c76 | E141: Energy | F141: Fugitive Emissions from Fuels | G141: Fugitive Emissions from Oil Production | I141: methane emissions from offshore gas facilities | J141: Offshore gas facilities | K141: Site | L141: offshore | M141: Second or sub-second | N141: 10 Hz | O141: P11 | P141: 43591 | Q141: 43591 | R141: 1 | S141: Point-Source | T141: 12.1 | U141: 9.3 | V141: 14.9 | W141: kg h-1 | Z141: 0 | AE141: {=_xlfn.torow(_xlfn.unique(_xlfn._xlws.filter(cat_table[Subsector],$E141=cat_table[Sector],"")))} -> #NAME? | AF141: #NAME? | AG141: #NAME? | AH141: #NAME? | AI141: #NAME? | AJ141: #NAME? | AK141: #NAME? | AO141: {=_xlfn.torow(_xlfn.unique(_xlfn._xlws.filter(cat_table[Sub-subsector],($E141=cat_table[Sector])*($F141=cat_table[Subsector]),"")))} -> #NAME? | AP141: #NAME? | AQ141: #NAME? | AR141: #NAME? | AS141: #NAME? | AT141: #NAME?
A142: a74bea25-1eeb-4102-85c7-12bd0c8afb67 | B142: d45dc248-31bc-48c1-8d6c-4cb479faf1b4 | C142: 1711685d-9f0e-4c8a-8a5e-b120c02d52b7 | D142: 36067f76-d150-4489-b59c-e7d016ba0c76 | E142: Energy | F142: Fugitive Emissions from Fuels | G142: Fugitive Emissions from Oil Production | I142: methane emissions from offshore gas facilities | J142: Offshore gas facilities | K142: Regional | L142: offshore | M142: Second or sub-second | N142: 10 Hz | O142: average emission estimate in the southern North Sea | P142: 43585 | Q142: 43591 | R142: 11 | S142: Average | T142: 136 | W142: kg h-1 | Z142: 1 | AE142: {=_xlfn.torow(_xlfn.unique(_xlfn._xlws.filter(cat_table[Subsector],$E142=cat_table[Sector],"")))} -> #NAME? | AF142: #NAME? | AG142: #NAME? | AH142: #NAME? | AI142: #NAME? | AJ142: #NAME? | AK142: #NAME? | AO142: {=_xlfn.torow(_xlfn.unique(_xlfn._xlws.filter(cat_table[Sub-subsector],($E142=cat_table[Sector])*($F142=cat_table[Subsector]),"")))} -> #NAME? | AP142: #NAME? | AQ142: #NAME? | AR142: #NAME? | AS142: #NAME? | AT142: #NAME?
A143: 87e143c3-617c-48a6-b8ad-f22486e830f3 | B143: 86d4c868-7c32-4f87-8f5b-0eea92d32d46 | C143: 6fd71c20-562a-4cd9-8083-d9fb1c9eec32 | D143: 36067f76-d150-4489-b59c-e7d016ba0c76 | E143: Energy | F143: Fugitive Emissions from Fuels | G143: Fugitive Emissions from Oil Production | I143: Gas flaring from offshore gas facilites | J143: Offshore oil and gas facilities | K143: Regional | L143: the UK North Sea | M143: Second or sub-second | N143: CH4 data were measured at 1 Hz for flights conducted in 2018 and at 10 Hz for flights conducted in 2019 | O143: Estimated emissions from flaring | P143: 43556 | Q143: 43678 | R143: regional sampling | S143: Area-Based | T143: 6.3 | W143: Gg yr-1 | Z143: 1 | AE143: {=_xlfn.torow(_xlfn.unique(_xlfn._xlws.filter(cat_table[Subsector],$E143=cat_table[Sector],"")))} -> #NAME? | AF143: #NAME? | AG143: #NAME? | AH143: #NAME? | AI143: #NAME? | AJ143: #NAME? | AK143: #NAME? | AO143: {=_xlfn.torow(_xlfn.unique(_xlfn._xlws.filter(cat_table[Sub-subsector],($E143=cat_table[Sector])*($F143=cat_table[Subsector]),"")))} -> #NAME? | AP143: #NAME? | AQ143: #NAME? | AR143: #NAME? | AS143: #NAME? | AT143: #NAME?
A144: 7753ea8c-c27c-4203-8ae9-67b7eebef587 | B144: 8eea5480-ab2d-4198-b186-ff3a2a35530b | C144: e405d296-ba95-4de9-ba27-310c58551ea1 | D144: 55b560ec-1523-4186-a81b-043a92b4b04b | E144: Energy | F144: Fugitive Emissions from Fuels | G144: Fugitive Emissions from Oil Production | I144: Methane leak from a well blowout in oil field | J144: Oil field | K144: Site | L144: Well no. 303 in the Karaturun East oil field in the Mangistau region | M144: Daily | N144: Time series constructed with satellite data Plume detections were not daily but many times a month (see Fig 3), and a Bayesian inversion framework was used to infer daily emissions rates | O144: Total emissions from a well blowout | P144: 45086 | Q144: 45305 | R144: 1 | S144: Central estimate | T144: 131 | U144: 97 | V144: 165 | W144: kt | Z144: 1 | AE144: {=_xlfn.torow(_xlfn.unique(_xlfn._xlws.filter(cat_table[Subsector],$E144=cat_table[Sector],"")))} -> #NAME? | AF144: #NAME? | AG144: #NAME? | AH144: #NAME? | AI144: #NAME? | AJ144: #NAME? | AK144: #NAME? | AO144: {=_xlfn.torow(_xlfn.unique(_xlfn._xlws.filter(cat_table[Sub-subsector],($E144=cat_table[Sector])*($F144=cat_table[Subsector]),"")))} -> #NAME? | AP144: #NAME? | AQ144: #NAME? | AR144: #NAME? | AS144: #NAME? | AT144: #NAME?
A145: a0902304-d81f-48d1-8977-509f2c62850b | B145: 601c727b-725c-468f-aa60-e3782eb3ba6b | C145: edc9ce2c-cf1a-447a-a5c2-9ef67b63bc01 | D145: edf2fa58-6b25-42a8-a8b7-61db47fbb4cd | E145: Energy | F145: Transport | G145: Pipeline Transport of Natural Gas | I145: Emissions from Nord Stream Pipeline Leaks | J145: Pipeline ruptures in the Baltic Sea | K145: Regional | L145: Southeast and Northeast of Bornholm | M145: Second or sub-second | N145: From 5 October 2022 to 2 January 2023, dissolved CH4 concentrations were observed continuously | O145: Total atmospheric emissions from leaks | P145: 44839 | Q145: 44928 | R145: 3 | S145: Area-Based | T145: 465 | U145: 445 | V145: 485 | W145: kt | Z145: 1 | AE145: {=_xlfn.torow(_xlfn.unique(_xlfn._xlws.filter(cat_table[Subsector],$E145=cat_table[Sector],"")))} -> #NAME? | AF145: #NAME? | AG145: #NAME? | AH145: #NAME? | AI145: #NAME? | AJ145: #NAME? | AK145: #NAME? | AO145: {=_xlfn.torow(_xlfn.unique(_xlfn._xlws.filter(cat_table[Sub-subsector],($E145=cat_table[Sector])*($F145=cat_table[Subsector]),"")))} -> #NAME? | AP145: #NAME? | AQ145: #NAME? | AR145: #NAME?
A146: e503491f-18c2-42bb-adb7-06bf952f0507 | B146: 601c727b-725c-468f-aa60-e3782eb3ba6b | C146: edc9ce2c-cf1a-447a-a5c2-9ef67b63bc01 | D146: edf2fa58-6b25-42a8-a8b7-61db47fbb4cd | E146: Energy | F146: Transport | G146: Pipeline Transport of Natural Gas | I146: Emissions from Nord Stream Pipeline Leaks | J146: Pipeline ruptures in the Baltic Sea | K146: Component | L146: Southeast and Northeast of Bornholm | M146: Second or sub-second | N146: From 5 October 2022 to 2 January 2023, dissolved CH4 concentrations were observed continuously | O146: Pipeline NS1A | P146: 44839 | Q146: 44928 | R146: 1 | S146: Point-Source | T146: 183 | U146: 178 | V146: 188 | W146: kt | Z146: 0 | AE146: {=_xlfn.torow(_xlfn.unique(_xlfn._xlws.filter(cat_table[Subsector],$E146=cat_table[Sector],"")))} -> #NAME? | AF146: #NAME? | AG146: #NAME? | AH146: #NAME? | AI146: #NAME? | AJ146: #NAME? | AK146: #NAME? | AO146: {=_xlfn.torow(_xlfn.unique(_xlfn._xlws.filter(cat_table[Sub-subsector],($E146=cat_table[Sector])*($F146=cat_table[Subsector]),"")))} -> #NAME? | AP146: #NAME? | AQ146: #NAME? | AR146: #NAME?
A147: a6923fb7-b2e1-4e6c-87a6-53554a89c648 | B147: 601c727b-725c-468f-aa60-e3782eb3ba6b | C147: edc9ce2c-cf1a-447a-a5c2-9ef67b63bc01 | D147: edf2fa58-6b25-42a8-a8b7-61db47fbb4cd | E147: Energy | F147: Transport | G147: Pipeline Transport of Natural Gas | I147: Emissions from Nord Stream Pipeline Leaks | J147: Pipeline ruptures in the Baltic Sea | K147: Component | L147: Southeast and Northeast of Bornholm | M147: Second or sub-second | N147: From 5 October 2022 to 2 January 2023, dissolved CH4 concentrations were observed continuously | O147: Pipeline NS1B | P147: 44839 | Q147: 44928 | R147: 1 | S147: Point-Source | T147: 183 | U147: 178 | V147: 188 | W147: kt | Z147: 0 | AE147: {=_xlfn.torow(_xlfn.unique(_xlfn._xlws.filter(cat_table[Subsector],$E147=cat_table[Sector],"")))} -> #NAME? | AF147: #NAME? | AG147: #NAME? | AH147: #NAME? | AI147: #NAME? | AJ147: #NAME? | AK147: #NAME? | AO147: {=_xlfn.torow(_xlfn.unique(_xlfn._xlws.filter(cat_table[Sub-subsector],($E147=cat_table[Sector])*($F147=cat_table[Subsector]),"")))} -> #NAME? | AP147: #NAME? | AQ147: #NAME? | AR147: #NAME?
A148: 915d648d-fb9c-4562-a630-b9dbb2cb40d2 | B148: 601c727b-725c-468f-aa60-e3782eb3ba6b | C148: edc9ce2c-cf1a-447a-a5c2-9ef67b63bc01 | D148: edf2fa58-6b25-42a8-a8b7-61db47fbb4cd | E148: Energy | F148: Transport | G148: Pipeline Transport of Natural Gas | I148: Emissions from Nord Stream Pipeline Leaks | J148: Pipeline ruptures in the Baltic Sea | K148: Component | L148: Southeast and Northeast of Bornholm | M148: Second or sub-second | N148: From 5 October 2022 to 2 January 2023, dissolved CH4 concentrations were observed continuously | O148: Pipeline NS2A | P148: 44839 | Q148: 44928 | R148: 1 | S148: Point-Source | T148: 106 | U148: 103 | V148: 109 | W148: kt | Z148: 0 | AE148: {=_xlfn.torow(_xlfn.unique(_xlfn._xlws.filter(cat_table[Subsector],$E148=cat_table[Sector],"")))} -> #NAME? | AF148: #NAME? | AG148: #NAME? | AH148: #NAME? | AI148: #NAME? | AJ148: #NAME? | AK148: #NAME? | AO148: {=_xlfn.torow(_xlfn.unique(_xlfn._xlws.filter(cat_table[Sub-subsector],($E148=cat_table[Sector])*($F148=cat_table[Subsector]),"")))} -> #NAME? | AP148: #NAME? | AQ148: #NAME? | AR148: #NAME?
A149: 6cb6f8f6-8e65-43ef-b7d2-f648c5df3ccb | B149: 601c727b-725c-468f-aa60-e3782eb3ba6b | C149: 797bd615-59f5-48b1-92ab-859a4de16dbe | D149: 7fbaef23-727c-4c26-b6de-5190343955f3 | E149: Energy | F149: Transport | G149: Pipeline Transport of Natural Gas | I149: Emissions from Nord Stream Pipeline Leaks | J149: Pipeline ruptures in the Baltic Sea | K149: Regional | L149: The focus area around the northern leak sites covered an along-wind corridor 20 km wide and 70 km long | M149: Second or sub-second | N149: laboratory-determined sampling frequency of 1.3–2 Hz 5 October 2022, ~8:00–15:30 UTC | O149: Value is a range: 19–48 t h−1 Bayesian random uncertainty is 5 t h−1 for the lower bound and 8 t h−1 for the upper bound | P149: 44839 | Q149: 44839 | R149: 1 | S149: Central estimate | T149: 33.5 | U149: 19 | V149: 48 | W149: t h-1 | Z149: 1 | AE149: {=_xlfn.torow(_xlfn.unique(_xlfn._xlws.filter(cat_table[Subsector],$E149=cat_table[Sector],"")))} -> #NAME? | AF149: #NAME? | AG149: #NAME? | AH149: #NAME? | AI149: #NAME? | AJ149: #NAME? | AK149: #NAME? | AO149: {=_xlfn.torow(_xlfn.unique(_xlfn._xlws.filter(cat_table[Sub-subsector],($E149=cat_table[Sector])*($F149=cat_table[Subsector]),"")))} -> #NAME? | AP149: #NAME? | AQ149: #NAME? | AR149: #NAME?
A150: 4cc1dd51-b8b7-4660-8ec7-756ecc2dacf6 | B150: 6c7ad3fe-f54d-4759-836c-a80f8912b3e0 | C150: fd6cb0ce-cf68-4d2f-a8cd-9c403cbeba26 | D150: 1370995b-5032-4a4b-87d5-1a6fd7df10e1 | E150: Energy | F150: Other sectors | G150: Commercial Heating | I150: Emissions from Catalytic heaters used at oil and gas production facilities | J150: Natural gas fired catalytic heaters | K150: Functional element | L150: In situ measurements of the exhaust streams of 38 different catalytic heaters were completed at 7 distinct upstream oil and gas facilities (5 unique operators) in northeastern British Columbia, Canada | M150: Second or sub-second | N150: The FTIR instrument collects individual spectra measurements at 10Hz | O150: Dates estimated -- "late July to mid-August 2023" | P150: 25/07/2023 | Q150: 15/08/2023 | R150: 38 | S150: Average | T150: 0.28 | U150: 0.24 | V150: 0.32 | W150: kg/h | Z150: 1 | AE150: {=_xlfn.torow(_xlfn.unique(_xlfn._xlws.filter(cat_table[Subsector],$E150=cat_table[Sector],"")))} -> #NAME? | AF150: #NAME? | AG150: #NAME? | AH150: #NAME? | AI150: #NAME? | AJ150: #NAME? | AK150: #NAME? | AO150: {=_xlfn.torow(_xlfn.unique(_xlfn._xlws.filter(cat_table[Sub-subsector],($E150=cat_table[Sector])*($F150=cat_table[Subsector]),"")))} -> #NAME? | AP150: #NAME?
A151: 9b2f0c53-3c1c-43a4-a7d4-ee0fbe32d95f | B151: 6c7ad3fe-f54d-4759-836c-a80f8912b3e0 | C151: fd6cb0ce-cf68-4d2f-a8cd-9c403cbeba26 | D151: 1370995b-5032-4a4b-87d5-1a6fd7df10e1 | E151: Energy | F151: Other sectors | G151: Commercial Heating | I151: Emissions from Catalytic heaters used at oil and gas production facilities | J151: Natural gas fired catalytic heaters | K151: Functional element | L151: Subcontracted technicians counted and documented makes, models, and fuel type of catalytic heaters at 407 upstream oil and gas sites in British Columbia, comprising 198 facilities and 1986 individual wells across BC | M151: Other | N151: Equipment survey data for 407 sites in BC were used to derive the mean natural gas use on a per facility type basis and subsequently total methane emissions for all installed catalytic heaters in the province. | O151: Estimated -- "from July to November 2023" | P151: 44933 | Q151: 44937 | R151: 407 | S151: Average | T151: 1.34 | W151: kt/mo | Z151: 1 | AE151: {=_xlfn.torow(_xlfn.unique(_xlfn._xlws.filter(cat_table[Subsector],$E151=cat_table[Sector],"")))} -> #NAME? | AF151: #NAME? | AG151: #NAME? | AH151: #NAME? | AI151: #NAME? | AJ151: #NAME? | AK151: #NAME? | AO151: {=_xlfn.torow(_xlfn.unique(_xlfn._xlws.filter(cat_table[Sub-subsector],($E151=cat_table[Sector])*($F151=cat_table[Subsector]),"")))} -> #NAME? | AP151: #NAME?
A152: 9db2f813-2566-44b8-9967-03f4d746031f | B152: 571ad96c-738d-408e-9b4a-ee48cb91fbca | C152: c225135b-8c23-46ac-84a4-54def66f9a94 | D152: 25e348c0-c485-4f68-b882-c0d489e85e86 | E152: Energy | F152: Fugitive Emissions from Fuels | G152: Fugitive Emissions from Oil Production | I152: Offshore oil and gas production | J152: Offshore oil and gas sector in West Africa | K152: Regional | L152: Emissions from Angolan offshore facilities were quantified using an aircraftbased mass balance method, estimating total sector emissions and assessing 30 individual facilities and 10 facility groups. | M152: Second or sub-second | N152: See Table 1 | O152: calculated as the sum of mean emissions from all facilities | P152: 44809 | Q152: 44830 | R152: 30 | S152: Average | T152: 16.9 | U152: 11.6 | V152: 22.2 | W152: t h-1 | Z152: 1 | AE152: {=_xlfn.torow(_xlfn.unique(_xlfn._xlws.filter(cat_table[Subsector],$E152=cat_table[Sector],"")))} -> #NAME? | AF152: #NAME? | AG152: #NAME? | AH152: #NAME? | AI152: #NAME? | AJ152: #NAME? | AK152: #NAME? | AO152: {=_xlfn.torow(_xlfn.unique(_xlfn._xlws.filter(cat_table[Sub-subsector],($E152=cat_table[Sector])*($F152=cat_table[Subsector]),"")))} -> #NAME? | AP152: #NAME? | AQ152: #NAME? | AR152: #NAME? | AS152: #NAME? | AT152: #NAME?
A153: 6c90c348-f292-45b3-9ad9-a643a3c4671c | B153: 6b02dd20-2700-4d46-ac62-f50833513641 | C153: 2bd022e0-8b29-45bb-8fbd-1311296b23aa | D153: 29df8f34-6a80-4e90-bce4-f22613bc94ee | E153: Energy | F153: Fugitive Emissions from Fuels | G153: Fugitive Emissions from Oil Production | I153: Oil Production | J153: The oil-production-dominated area Hassi Messaoud | K153: Regional | L153: Satellite measurements covering entire field | M153: Daily | N153: Sentinel-2 provides global coverage with a revisit time of 2–5 days. | O153: Total 2020 emissions in Hassi Messaoud | P153: 43831 | Q153: 44197 | R153: regional sampling | S153: Area-Based | T153: 0.22 | U153: 0.13 | V153: 0.28 | W153: Tg/yr | Z153: 1 | AE153: {=_xlfn.torow(_xlfn.unique(_xlfn._xlws.filter(cat_table[Subsector],$E153=cat_table[Sector],"")))} -> #NAME? | AF153: #NAME? | AG153: #NAME? | AH153: #NAME? | AI153: #NAME? | AJ153: #NAME? | AK153: #NAME? | AO153: {=_xlfn.torow(_xlfn.unique(_xlfn._xlws.filter(cat_table[Sub-subsector],($E153=cat_table[Sector])*($F153=cat_table[Subsector]),"")))} -> #NAME? | AP153: #NAME? | AQ153: #NAME? | AR153: #NAME? | AS153: #NAME? | AT153: #NAME?
A154: 70d9771b-2733-4075-a1bc-961580409c1b | B154: d24f6e1a-92a1-4f31-9402-2a5e9236963d | C154: 2bd022e0-8b29-45bb-8fbd-1311296b23aa | D154: 29df8f34-6a80-4e90-bce4-f22613bc94ee | E154: Energy | F154: Fugitive Emissions from Fuels | G154: Fugitive Emissions from Oil Production | I154: Gas Field | J154: The largest gas field in Algeria, Hassi R’Mel | K154: Regional | L154: Satellite measurements covering entire field | M154: Daily | N154: Sentinel-2 provides global coverage with a revisit time of 2–5 days. | O154: Total 2020 emissions in Hassi R'Mel | P154: 43831 | Q154: 44197 | R154: regional sampling | S154: Area-Based | T154: 0.16 | U154: 0.11 | V154: 0.22 | W154: Tg/yr | Z154: 1 | AE154: {=_xlfn.torow(_xlfn.unique(_xlfn._xlws.filter(cat_table[Subsector],$E154=cat_table[Sector],"")))} -> #NAME? | AF154: #NAME? | AG154: #NAME? | AH154: #NAME? | AI154: #NAME? | AJ154: #NAME? | AK154: #NAME? | AO154: {=_xlfn.torow(_xlfn.unique(_xlfn._xlws.filter(cat_table[Sub-subsector],($E154=cat_table[Sector])*($F154=cat_table[Subsector]),"")))} -> #NAME? | AP154: #NAME? | AQ154: #NAME? | AR154: #NAME? | AS154: #NAME? | AT154: #NAME?
A155: f312304b-d00b-452f-a4af-8f192acad914 | B155: d24f6e1a-92a1-4f31-9402-2a5e9236963d | C155: 2bd022e0-8b29-45bb-8fbd-1311296b23aa | D155: 29df8f34-6a80-4e90-bce4-f22613bc94ee | E155: Energy | F155: Fugitive Emissions from Fuels | G155: Fugitive Emissions from Oil Production | I155: Pit Flare in Gas Field | J155: Pit Flare in Hassi R'Mel | K155: Component | M155: Daily | N155: Sentinel-2 provides global coverage with a revisit time of 2–5 days. | O155: R01 | P155: 43831 | Q155: 44197 | R155: 1 | S155: Point-Source | T155: 5.26 | W155: t/hr | Z155: 0 | AE155: {=_xlfn.torow(_xlfn.unique(_xlfn._xlws.filter(cat_table[Subsector],$E155=cat_table[Sector],"")))} -> #NAME? | AF155: #NAME? | AG155: #NAME? | AH155: #NAME? | AI155: #NAME? | AJ155: #NAME? | AK155: #NAME? | AO155: {=_xlfn.torow(_xlfn.unique(_xlfn._xlws.filter(cat_table[Sub-subsector],($E155=cat_table[Sector])*($F155=cat_table[Subsector]),"")))} -> #NAME? | AP155: #NAME? | AQ155: #NAME? | AR155: #NAME? | AS155: #NAME? | AT155: #NAME?
A156: da0a2407-9f66-41a0-9bb8-7cdca548678e | B156: 6b02dd20-2700-4d46-ac62-f50833513641 | C156: 2bd022e0-8b29-45bb-8fbd-1311296b23aa | D156: 29df8f34-6a80-4e90-bce4-f22613bc94ee | E156: Energy | F156: Fugitive Emissions from Fuels | G156: Fugitive Emissions from Oil Production | I156: Ground Flare | J156: Ground Flare in Hassi Messaoud | K156: Component | M156: Daily | N156: Sentinel-2 provides global coverage with a revisit time of 2–5 days. | O156: M01 | P156: 43831 | Q156: 44197 | R156: 1 | S156: Point-Source | T156: 4.43 | W156: t/hr | Z156: 0 | AE156: {=_xlfn.torow(_xlfn.unique(_xlfn._xlws.filter(cat_table[Subsector],$E156=cat_table[Sector],"")))} -> #NAME? | AF156: #NAME? | AG156: #NAME? | AH156: #NAME? | AI156: #NAME? | AJ156: #NAME? | AK156: #NAME? | AO156: {=_xlfn.torow(_xlfn.unique(_xlfn._xlws.filter(cat_table[Sub-subsector],($E156=cat_table[Sector])*($F156=cat_table[Subsector]),"")))} -> #NAME? | AP156: #NAME? | AQ156: #NAME? | AR156: #NAME? | AS156: #NAME? | AT156: #NAME?
